Workbook

Sheet Start
A1: FORMULAS 1 ▸ FORMULA BASICS
A2: Write your first formulas and make them fill down correctly.
A4: HOW TO PLAY
A5: 1 · Each stage: read the BRIEFING, then answer WARM-UP, TRAINING and CHALLENGES.
A6: 2 · Yellow cells are yours: type, pick from a list (Alt+↓), or follow a ▶ ARENA link and do the move there.
A7: 3 · ✔ CLEAR = right · ✘ = try again · · not yet = drill not done. Stuck? Pick 'Show hint' (5 XP instead of 10).
A8: 4 · Formatting or hiding drills: press F9 to refresh the check. Tab jumps between yellow cells.
A9: Needs Windows with Microsoft Excel 365 or 2021+ (English). In Protected View, click Enable Editing.
A11: STAGE SELECT
A12: Stage | B12: Name | C12: Score | D12: Stars | E12: Status | F12: Go
A13: F1-1 | B13: Power Up | C13: {=SUM('F1-1 Power Up'!$G$14:$G$37)&" / 170"} -> 0 / 170 | D13: {=IF(SUM('F1-1 Power Up'!$G$14:$G$37)>=170,"★★★",IF(SUM('F1-1 Power Up'!$G$14:$G$37)>=170*0.8,"★★☆",IF(SUM('F1-1 Power Up'!$G$14:$G$37)>=170*0.5,"★☆☆","☆☆☆")))} -> ☆☆☆ | E13: {=IF(SUM('F1-1 Power Up'!$G$14:$G$37)>=170,"PERFECT",IF(SUM('F1-1 Power Up'!$G$14:$G$37)>=170*0.5,"CLEARED",IF(SUM('F1-1 Power Up'!$G$14:$G$37)>0,"IN PROGRESS","NEW")))} -> NEW | F13: Go to F1-1 Power Up
A14: F1-2 | B14: Big Six | C14: {=SUM('F1-2 Big Six'!$G$17:$G$51)&" / 280"} -> 0 / 280 | D14: {=IF(SUM('F1-2 Big Six'!$G$17:$G$51)>=280,"★★★",IF(SUM('F1-2 Big Six'!$G$17:$G$51)>=280*0.8,"★★☆",IF(SUM('F1-2 Big Six'!$G$17:$G$51)>=280*0.5,"★☆☆","☆☆☆")))} -> ☆☆☆ | E14: {=IF(SUM('F1-2 Big Six'!$G$17:$G$51)>=280,"PERFECT",IF(SUM('F1-2 Big Six'!$G$17:$G$51)>=280*0.5,"CLEARED",IF(SUM('F1-2 Big Six'!$G$17:$G$51)>0,"IN PROGRESS","NEW")))} -> NEW | F14: Go to F1-2 Big Six
A15: F1-3 | B15: Anchors | C15: {=SUM('F1-3 Anchors'!$G$14:$G$40)&" / 200"} -> 0 / 200 | D15: {=IF(SUM('F1-3 Anchors'!$G$14:$G$40)>=200,"★★★",IF(SUM('F1-3 Anchors'!$G$14:$G$40)>=200*0.8,"★★☆",IF(SUM('F1-3 Anchors'!$G$14:$G$40)>=200*0.5,"★☆☆","☆☆☆")))} -> ☆☆☆ | E15: {=IF(SUM('F1-3 Anchors'!$G$14:$G$40)>=200,"PERFECT",IF(SUM('F1-3 Anchors'!$G$14:$G$40)>=200*0.5,"CLEARED",IF(SUM('F1-3 Anchors'!$G$14:$G$40)>0,"IN PROGRESS","NEW")))} -> NEW | F15: Go to F1-3 Anchors
A16: F1-4 | B16: Precision | C16: {=SUM('F1-4 Precision'!$G$13:$G$33)&" / 140"} -> 0 / 140 | D16: {=IF(SUM('F1-4 Precision'!$G$13:$G$33)>=140,"★★★",IF(SUM('F1-4 Precision'!$G$13:$G$33)>=140*0.8,"★★☆",IF(SUM('F1-4 Precision'!$G$13:$G$33)>=140*0.5,"★☆☆","☆☆☆")))} -> ☆☆☆ | E16: {=IF(SUM('F1-4 Precision'!$G$13:$G$33)>=140,"PERFECT",IF(SUM('F1-4 Precision'!$G$13:$G$33)>=140*0.5,"CLEARED",IF(SUM('F1-4 Precision'!$G$13:$G$33)>0,"IN PROGRESS","NEW")))} -> NEW | F16: Go to F1-4 Precision
A17: F1-5 | B17: X-Ray | C17: {=SUM('F1-5 X-Ray'!$G$15:$G$42)&" / 210"} -> 0 / 210 | D17: {=IF(SUM('F1-5 X-Ray'!$G$15:$G$42)>=210,"★★★",IF(SUM('F1-5 X-Ray'!$G$15:$G$42)>=210*0.8,"★★☆",IF(SUM('F1-5 X-Ray'!$G$15:$G$42)>=210*0.5,"★☆☆","☆☆☆")))} -> ☆☆☆ | E17: {=IF(SUM('F1-5 X-Ray'!$G$15:$G$42)>=210,"PERFECT",IF(SUM('F1-5 X-Ray'!$G$15:$G$42)>=210*0.5,"CLEARED",IF(SUM('F1-5 X-Ray'!$G$15:$G$42)>0,"IN PROGRESS","NEW")))} -> NEW | F17: Go to F1-5 X-Ray
A18: BOSS | B18: Boss | C18: {=SUM(Boss!$G$14:$G$33)&" / 160"} -> 0 / 160 | D18: {=IF(SUM(Boss!$G$14:$G$33)>=160,"★★★",IF(SUM(Boss!$G$14:$G$33)>=160*0.8,"★★☆",IF(SUM(Boss!$G$14:$G$33)>=160*0.5,"★☆☆","☆☆☆")))} -> ☆☆☆ | E18: {=IF(Boss!$C$10="OPEN",IF(SUM(Boss!$G$14:$G$33)>=160*0.5,"DEFEATED","OPEN"),"LOCKED")} -> LOCKED | F18: Go to the Boss
A20: TOTAL SCORE | B20: {=(SUM('F1-1 Power Up'!$G$14:$G$37)+SUM('F1-2 Big Six'!$G$17:$G$51)+SUM('F1-3 Anchors'!$G$14:$G$40)+SUM('F1-4 Precision'!$G$13:$G$33)+SUM('F1-5 X-Ray'!$G$15:$G$42)+SUM(Boss!$G$14:$G$33))&" / 1160"} -> 0 / 1160
A21: RANK | B21: {=_xlfn.LET(_xlpm.p,(SUM('F1-1 Power Up'!$G$14:$G$37)+SUM('F1-2 Big Six'!$G$17:$G$51)+SUM('F1-3 Anchors'!$G$14:$G$40)+SUM('F1-4 Precision'!$G$13:$G$33)+SUM('F1-5 X-Ray'!$G$15:$G$42)+SUM(Boss!$G$14:$G$33))/1160,IF(AND(_xlpm.p>=1,ISNUMBER(Boss!$C$8),Boss!$C$8<=15),"S",IF(_xlpm.p>=0.9,"A",IF(_xlpm.p>=0.75,"B",IF(_xlpm.p>=0.5,"C","D")))))} -> D | C21: S = 100% and under par · A ≥ 90% · B ≥ 75% · C ≥ 50%
A22: BEST TIME | B22: {=IF(ISNUMBER(Boss!$C$8),Boss!$C$8&" min (par 15)","—")} -> —
A23: NEXT UP | B23: {=IFERROR(INDEX($A$13:$A$17,MATCH("☆☆☆",$D$13:$D$17,0))&" "&INDEX($B$13:$B$17,MATCH("☆☆☆",$D$13:$D$17,0)),IF(Boss!$C$10="OPEN","the Boss","All clear! Aim for rank S"))} -> F1-1 Power Up
A25: Replay a stage: select its yellow answer cells and press Delete. Undo an arena drill with Ctrl+Z.

Sheet F1-1 Power Up
A1: STAGE F1-1 ▸ POWER UP
A2: Goal: write formulas that calculate from cells
A3: {="SCORE "&TEXT(SUM($G$14:$G$37),"0000")&" / 0170"} -> SCORE 0000 / 0170 | C3: {=IF(SUM($G$14:$G$37)>=170,"★★★",IF(SUM($G$14:$G$37)>=170*0.8,"★★☆",IF(SUM($G$14:$G$37)>=170*0.5,"★☆☆","☆☆☆")))} -> ☆☆☆ | D3: {=REPT("█",ROUND(10*SUM($G$14:$G$37)/170,0))&REPT("░",10-ROUND(10*SUM($G$14:$G$37)/170,0))&" "&TEXT(SUM($G$14:$G$37)/170,"0%")} -> ░░░░░░░░░░ 0% | F3: {=IF(SUM($G$14:$G$37)>=170*0.5,"STAGE CLEAR! ▶ Next: F1-2 Big Six","")}
A5: BRIEFING · new moves in this stage
A6: # | B6: What it does · Pro tip | C6: Keys / Syntax
A7: 1 | B7: Every formula starts with an equals sign. Tip: Without =, Excel stores what you typed as plain text. | C7: =
A8: 2 | B8: Arithmetic: add, subtract, multiply, divide, power. Tip: * multiplies, / divides, ^ raises to a power (2^3 = 8). | C8: + - * / ^
A9: 3 | B9: Order: parentheses, then ^, then * and /, then + and -. Tip: =2+3*4 is 14, but =(2+3)*4 is 20. | C9: ( ) first
A10: 4 | B10: Point at cells instead of typing numbers. Tip: Change B2 and the result updates by itself. | C10: =B2*C2
A12: WARM-UP · flashback to earlier stages
A13: # | B13: Mission | C13: Your answer | D13: Result | E13: Hint? | F13: Hint | G13: XP
A14: W1 | B14: Which key opens the Go To box? (from S1-2 Teleport) | D14: {=IFERROR(_xlfn.LET(_xlpm.a,'F1-1 Power Up'!$C$14,IF(TRIM(_xlpm.a&"")="","",IF(OR(SUBSTITUTE(SUBSTITUTE(SUBSTITUTE(SUBSTITUTE(SUBSTITUTE(SUBSTITUTE(SUBSTITUTE(SUBSTITUTE(SUBSTITUTE(SUBSTITUTE(SUBSTITUTE(SUBSTITUTE(SUBSTITUTE(SUBSTITUTE(SUBSTITUTE(SUBSTITUTE(SUBSTITUTE(SUBSTITUTE(SUBSTITUTE(SUBSTITUTE(SUBSTITUTE(SUBSTITUTE(SUBSTITUTE(SUBSTITUTE(SUBSTITUTE(SUBSTITUTE(SUBSTITUTE(UPPER(_xlpm.a)," ",""),"CONTROL","CTRL"),"CTL","CTRL"),"ESCAPE","ESC"),"RETURN","ENTER"),"PAGEDOWN","PGDN"),"PGDOWN","PGDN"),"PAGEUP","PGUP"),"ARROWKEYS","ARROW"),"ARROWKEY","ARROW"),"ARROWS","ARROW"),"DOWNARROW","DOWN"),"UPARROW","UP"),"LEFTARROW","LEFT"),"RIGHTARROW","RIGHT"),"ARROWDOWN","DOWN"),"ARROWUP","UP"),"ARROWLEFT","LEFT"),"ARROWRIGHT","RIGHT"),"↓","DOWN"),"↑","UP"),"←","LEFT"),"→","RIGHT"),"SPACEBAR","SPACE"),"−","-"),"MINUS","-"),"PLUS","+")=Key!$E$2:$F$2),"✔ CLEAR","✘ TRY AGAIN"))),"✘ TRY AGAIN")} | F14: {=IF(E14="Show hint",Key!$B$2,"")} | G14: {=IF(LEFT(D14,1)="✔",IF(E14="Show hint",5,10),0)} -> 0
A15: W2 | B15: Which keys move to the next sheet? (from S1-2 Teleport) | D15: {=IFERROR(_xlfn.LET(_xlpm.a,'F1-1 Power Up'!$C$15,IF(TRIM(_xlpm.a&"")="","",IF(OR(SUBSTITUTE(SUBSTITUTE(SUBSTITUTE(SUBSTITUTE(SUBSTITUTE(SUBSTITUTE(SUBSTITUTE(SUBSTITUTE(SUBSTITUTE(SUBSTITUTE(SUBSTITUTE(SUBSTITUTE(SUBSTITUTE(SUBSTITUTE(SUBSTITUTE(SUBSTITUTE(SUBSTITUTE(SUBSTITUTE(SUBSTITUTE(SUBSTITUTE(SUBSTITUTE(SUBSTITUTE(SUBSTITUTE(SUBSTITUTE(SUBSTITUTE(SUBSTITUTE(SUBSTITUTE(UPPER(_xlpm.a)," ",""),"CONTROL","CTRL"),"CTL","CTRL"),"ESCAPE","ESC"),"RETURN","ENTER"),"PAGEDOWN","PGDN"),"PGDOWN","PGDN"),"PAGEUP","PGUP"),"ARROWKEYS","ARROW"),"ARROWKEY","ARROW"),"ARROWS","ARROW"),"DOWNARROW","DOWN"),"UPARROW","UP"),"LEFTARROW","LEFT"),"RIGHTARROW","RIGHT"),"ARROWDOWN","DOWN"),"ARROWUP","UP"),"ARROWLEFT","LEFT"),"ARROWRIGHT","RIGHT"),"↓","DOWN"),"↑","UP"),"←","LEFT"),"→","RIGHT"),"SPACEBAR","SPACE"),"−","-"),"MINUS","-"),"PLUS","+")=Key!$E$3:$E$3),"✔ CLEAR","✘ TRY AGAIN"))),"✘ TRY AGAIN")} | F15: {=IF(E15="Show hint",Key!$B$3,"")} | G15: {=IF(LEFT(D15,1)="✔",IF(E15="Show hint",5,10),0)} -> 0
A16: W3 | B16: Which keys move to the previous sheet? (from S1-2 Teleport) | D16: {=IFERROR(_xlfn.LET(_xlpm.a,'F1-1 Power Up'!$C$16,IF(TRIM(_xlpm.a&"")="","",IF(OR(SUBSTITUTE(SUBSTITUTE(SUBSTITUTE(SUBSTITUTE(SUBSTITUTE(SUBSTITUTE(SUBSTITUTE(SUBSTITUTE(SUBSTITUTE(SUBSTITUTE(SUBSTITUTE(SUBSTITUTE(SUBSTITUTE(SUBSTITUTE(SUBSTITUTE(SUBSTITUTE(SUBSTITUTE(SUBSTITUTE(SUBSTITUTE(SUBSTITUTE(SUBSTITUTE(SUBSTITUTE(SUBSTITUTE(SUBSTITUTE(SUBSTITUTE(SUBSTITUTE(SUBSTITUTE(UPPER(_xlpm.a)," ",""),"CONTROL","CTRL"),"CTL","CTRL"),"ESCAPE","ESC"),"RETURN","ENTER"),"PAGEDOWN","PGDN"),"PGDOWN","PGDN"),"PAGEUP","PGUP"),"ARROWKEYS","ARROW"),"ARROWKEY","ARROW"),"ARROWS","ARROW"),"DOWNARROW","DOWN"),"UPARROW","UP"),"LEFTARROW","LEFT"),"RIGHTARROW","RIGHT"),"ARROWDOWN","DOWN"),"ARROWUP","UP"),"ARROWLEFT","LEFT"),"ARROWRIGHT","RIGHT"),"↓","DOWN"),"↑","UP"),"←","LEFT"),"→","RIGHT"),"SPACEBAR","SPACE"),"−","-"),"MINUS","-"),"PLUS","+")=Key!$E$4:$E$4),"✔ CLEAR","✘ TRY AGAIN"))),"✘ TRY AGAIN")} | F16: {=IF(E16="Show hint",Key!$B$4,"")} | G16: {=IF(LEFT(D16,1)="✔",IF(E16="Show hint",5,10),0)} -> 0
A17: W4 | B17: Which key scrolls one screen down? (from S1-2 Teleport) | D17: {=IFERROR(_xlfn.LET(_xlpm.a,'F1-1 Power Up'!$C$17,IF(TRIM(_xlpm.a&"")="","",IF(OR(SUBSTITUTE(SUBSTITUTE(SUBSTITUTE(SUBSTITUTE(SUBSTITUTE(SUBSTITUTE(SUBSTITUTE(SUBSTITUTE(SUBSTITUTE(SUBSTITUTE(SUBSTITUTE(SUBSTITUTE(SUBSTITUTE(SUBSTITUTE(SUBSTITUTE(SUBSTITUTE(SUBSTITUTE(SUBSTITUTE(SUBSTITUTE(SUBSTITUTE(SUBSTITUTE(SUBSTITUTE(SUBSTITUTE(SUBSTITUTE(SUBSTITUTE(SUBSTITUTE(SUBSTITUTE(UPPER(_xlpm.a)," ",""),"CONTROL","CTRL"),"CTL","CTRL"),"ESCAPE","ESC"),"RETURN","ENTER"),"PAGEDOWN","PGDN"),"PGDOWN","PGDN"),"PAGEUP","PGUP"),"ARROWKEYS","ARROW"),"ARROWKEY","ARROW"),"ARROWS","ARROW"),"DOWNARROW","DOWN"),"UPARROW","UP"),"LEFTARROW","LEFT"),"RIGHTARROW","RIGHT"),"ARROWDOWN","DOWN"),"ARROWUP","UP"),"ARROWLEFT","LEFT"),"ARROWRIGHT","RIGHT"),"↓","DOWN"),"↑","UP"),"←","LEFT"),"→","RIGHT"),"SPACEBAR","SPACE"),"−","-"),"MINUS","-"),"PLUS","+")=Key!$E$5:$E$5),"✔ CLEAR","✘ TRY AGAIN"))),"✘ TRY AGAIN")} | F17: {=IF(E17="Show hint",Key!$B$5,"")} | G17: {=IF(LEFT(D17,1)="✔",IF(E17="Show hint",5,10),0)} -> 0
A18: W5 | B18: Which keys scroll one screen to the right? (from S1-2 Teleport) | D18: {=IFERROR(_xlfn.LET(_xlpm.a,'F1-1 Power Up'!$C$18,IF(TRIM(_xlpm.a&"")="","",IF(OR(SUBSTITUTE(SUBSTITUTE(SUBSTITUTE(SUBSTITUTE(SUBSTITUTE(SUBSTITUTE(SUBSTITUTE(SUBSTITUTE(SUBSTITUTE(SUBSTITUTE(SUBSTITUTE(SUBSTITUTE(SUBSTITUTE(SUBSTITUTE(SUBSTITUTE(SUBSTITUTE(SUBSTITUTE(SUBSTITUTE(SUBSTITUTE(SUBSTITUTE(SUBSTITUTE(SUBSTITUTE(SUBSTITUTE(SUBSTITUTE(SUBSTITUTE(SUBSTITUTE(SUBSTITUTE(UPPER(_xlpm.a)," ",""),"CONTROL","CTRL"),"CTL","CTRL"),"ESCAPE","ESC"),"RETURN","ENTER"),"PAGEDOWN","PGDN"),"PGDOWN","PGDN"),"PAGEUP","PGUP"),"ARROWKEYS","ARROW"),"ARROWKEY","ARROW"),"ARROWS","ARROW"),"DOWNARROW","DOWN"),"UPARROW","UP"),"LEFTARROW","LEFT"),"RIGHTARROW","RIGHT"),"ARROWDOWN","DOWN"),"ARROWUP","UP"),"ARROWLEFT","LEFT"),"ARROWRIGHT","RIGHT"),"↓","DOWN"),"↑","UP"),"←","LEFT"),"→","RIGHT"),"SPACEBAR","SPACE"),"−","-"),"MINUS","-"),"PLUS","+")=Key!$E$6:$E$6),"✔ CLEAR","✘ TRY AGAIN"))),"✘ TRY AGAIN")} | F18: {=IF(E18="Show hint",Key!$B$6,"")} | G18: {=IF(LEFT(D18,1)="✔",IF(E18="Show hint",5,10),0)} -> 0
A20: TRAINING · recognize the move (pick from the list)
A21: # | B21: Mission | C21: Your answer | D21: Result | E21: Hint? | F21: Hint | G21: XP
A22: T1 | B22: Which character must every formula start with? | D22: {=IFERROR(IF('F1-1 Power Up'!$C$22&""="","",IF('F1-1 Power Up'!$C$22&""=Key!$C$7&"","✔ CLEAR","✘ TRY AGAIN")),"✘ TRY AGAIN")} | F22: {=IF(E22="Show hint",Key!$B$7,"")} | G22: {=IF(LEFT(D22,1)="✔",IF(E22="Show hint",5,10),0)} -> 0
A23: T2 | B23: Which move is this? Arithmetic: add, subtract, multiply, divide, power. | D23: {=IFERROR(IF('F1-1 Power Up'!$C$23&""="","",IF('F1-1 Power Up'!$C$23&""=Key!$C$8&"","✔ CLEAR","✘ TRY AGAIN")),"✘ TRY AGAIN")} | F23: {=IF(E23="Show hint",Key!$B$8,"")} | G23: {=IF(LEFT(D23,1)="✔",IF(E23="Show hint",5,10),0)} -> 0
A24: T3 | B24: Which move is this? Order: parentheses, then ^, then * and /, then + and -. | D24: {=IFERROR(IF('F1-1 Power Up'!$C$24&""="","",IF('F1-1 Power Up'!$C$24&""=Key!$C$9&"","✔ CLEAR","✘ TRY AGAIN")),"✘ TRY AGAIN")} | F24: {=IF(E24="Show hint",Key!$B$9,"")} | G24: {=IF(LEFT(D24,1)="✔",IF(E24="Show hint",5,10),0)} -> 0
A25: T4 | B25: Pick the formula that multiplies cell B2 by cell C2. | D25: {=IFERROR(IF('F1-1 Power Up'!$C$25&""="","",IF('F1-1 Power Up'!$C$25&""=Key!$C$10&"","✔ CLEAR","✘ TRY AGAIN")),"✘ TRY AGAIN")} | F25: {=IF(E25="Show hint",Key!$B$10,"")} | G25: {=IF(LEFT(D25,1)="✔",IF(E25="Show hint",5,10),0)} -> 0
A27: CHALLENGES · recall it, then do it
B28: ▶ Open F1-1 Arena (or press Ctrl+PgDn)
A29: # | B29: Mission | C29: Your answer | D29: Result | E29: Hint? | F29: Hint | G29: XP
A30: C1 | B30: Which character must every formula start with? | D30: {=IFERROR(_xlfn.LET(_xlpm.a,'F1-1 Power Up'!$C$30,IF(TRIM(_xlpm.a&"")="","",IF(OR(SUBSTITUTE(SUBSTITUTE(SUBSTITUTE(SUBSTITUTE(SUBSTITUTE(SUBSTITUTE(SUBSTITUTE(SUBSTITUTE(SUBSTITUTE(SUBSTITUTE(SUBSTITUTE(SUBSTITUTE(SUBSTITUTE(SUBSTITUTE(SUBSTITUTE(SUBSTITUTE(SUBSTITUTE(SUBSTITUTE(SUBSTITUTE(SUBSTITUTE(SUBSTITUTE(SUBSTITUTE(SUBSTITUTE(SUBSTITUTE(SUBSTITUTE(SUBSTITUTE(SUBSTITUTE(UPPER(_xlpm.a)," ",""),"CONTROL","CTRL"),"CTL","CTRL"),"ESCAPE","ESC"),"RETURN","ENTER"),"PAGEDOWN","PGDN"),"PGDOWN","PGDN"),"PAGEUP","PGUP"),"ARROWKEYS","ARROW"),"ARROWKEY","ARROW"),"ARROWS","ARROW"),"DOWNARROW","DOWN"),"UPARROW","UP"),"LEFTARROW","LEFT"),"RIGHTARROW","RIGHT"),"ARROWDOWN","DOWN"),"ARROWUP","UP"),"ARROWLEFT","LEFT"),"ARROWRIGHT","RIGHT"),"↓","DOWN"),"↑","UP"),"←","LEFT"),"→","RIGHT"),"SPACEBAR","SPACE"),"−","-"),"MINUS","-"),"PLUS","+")=Key!$E$11:$H$11),"✔ CLEAR","✘ TRY AGAIN"))),"✘ TRY AGAIN")} | F30: {=IF(E30="Show hint",Key!$B$11,"")} | G30: {=IF(LEFT(D30,1)="✔",IF(E30="Show hint",5,10),0)} -> 0
A31: C2 | B31: Which operator raises a number to a power? | D31: {=IFERROR(_xlfn.LET(_xlpm.a,'F1-1 Power Up'!$C$31,IF(TRIM(_xlpm.a&"")="","",IF(OR(SUBSTITUTE(SUBSTITUTE(SUBSTITUTE(SUBSTITUTE(SUBSTITUTE(SUBSTITUTE(SUBSTITUTE(SUBSTITUTE(SUBSTITUTE(SUBSTITUTE(SUBSTITUTE(SUBSTITUTE(SUBSTITUTE(SUBSTITUTE(SUBSTITUTE(SUBSTITUTE(SUBSTITUTE(SUBSTITUTE(SUBSTITUTE(SUBSTITUTE(SUBSTITUTE(SUBSTITUTE(SUBSTITUTE(SUBSTITUTE(SUBSTITUTE(SUBSTITUTE(SUBSTITUTE(UPPER(_xlpm.a)," ",""),"CONTROL","CTRL"),"CTL","CTRL"),"ESCAPE","ESC"),"RETURN","ENTER"),"PAGEDOWN","PGDN"),"PGDOWN","PGDN"),"PAGEUP","PGUP"),"ARROWKEYS","ARROW"),"ARROWKEY","ARROW"),"ARROWS","ARROW"),"DOWNARROW","DOWN"),"UPARROW","UP"),"LEFTARROW","LEFT"),"RIGHTARROW","RIGHT"),"ARROWDOWN","DOWN"),"ARROWUP","UP"),"ARROWLEFT","LEFT"),"ARROWRIGHT","RIGHT"),"↓","DOWN"),"↑","UP"),"←","LEFT"),"→","RIGHT"),"SPACEBAR","SPACE"),"−","-"),"MINUS","-"),"PLUS","+")=Key!$E$12:$F$12),"✔ CLEAR","✘ TRY AGAIN"))),"✘ TRY AGAIN")} | F31: {=IF(E31="Show hint",Key!$B$12,"")} | G31: {=IF(LEFT(D31,1)="✔",IF(E31="Show hint",5,10),0)} -> 0
A32: C3 | B32: What does =2+3*4 return? | D32: {=IFERROR(_xlfn.LET(_xlpm.a,'F1-1 Power Up'!$C$32,IF(TRIM(_xlpm.a&"")="","",IF(OR(SUBSTITUTE(SUBSTITUTE(SUBSTITUTE(SUBSTITUTE(SUBSTITUTE(SUBSTITUTE(SUBSTITUTE(SUBSTITUTE(SUBSTITUTE(SUBSTITUTE(SUBSTITUTE(SUBSTITUTE(SUBSTITUTE(SUBSTITUTE(SUBSTITUTE(SUBSTITUTE(SUBSTITUTE(SUBSTITUTE(SUBSTITUTE(SUBSTITUTE(SUBSTITUTE(SUBSTITUTE(SUBSTITUTE(SUBSTITUTE(SUBSTITUTE(SUBSTITUTE(SUBSTITUTE(UPPER(_xlpm.a)," ",""),"CONTROL","CTRL"),"CTL","CTRL"),"ESCAPE","ESC"),"RETURN","ENTER"),"PAGEDOWN","PGDN"),"PGDOWN","PGDN"),"PAGEUP","PGUP"),"ARROWKEYS","ARROW"),"ARROWKEY","ARROW"),"ARROWS","ARROW"),"DOWNARROW","DOWN"),"UPARROW","UP"),"LEFTARROW","LEFT"),"RIGHTARROW","RIGHT"),"ARROWDOWN","DOWN"),"ARROWUP","UP"),"ARROWLEFT","LEFT"),"ARROWRIGHT","RIGHT"),"↓","DOWN"),"↑","UP"),"←","LEFT"),"→","RIGHT"),"SPACEBAR","SPACE"),"−","-"),"MINUS","-"),"PLUS","+")=Key!$E$13:$E$13),"✔ CLEAR","✘ TRY AGAIN"))),"✘ TRY AGAIN")} | F32: {=IF(E32="Show hint",Key!$B$13,"")} | G32: {=IF(LEFT(D32,1)="✔",IF(E32="Show hint",5,10),0)} -> 0
A33: C4 | B33: Type the formula that multiplies cell B2 by cell C2. | D33: {=IFERROR(_xlfn.LET(_xlpm.a,'F1-1 Power Up'!$C$33,IF(TRIM(_xlpm.a&"")="","",IF(OR(SUBSTITUTE(SUBSTITUTE(SUBSTITUTE(SUBSTITUTE(SUBSTITUTE(SUBSTITUTE(SUBSTITUTE(SUBSTITUTE(SUBSTITUTE(SUBSTITUTE(SUBSTITUTE(SUBSTITUTE(SUBSTITUTE(SUBSTITUTE(SUBSTITUTE(SUBSTITUTE(SUBSTITUTE(SUBSTITUTE(SUBSTITUTE(SUBSTITUTE(SUBSTITUTE(SUBSTITUTE(SUBSTITUTE(SUBSTITUTE(SUBSTITUTE(SUBSTITUTE(SUBSTITUTE(UPPER(_xlpm.a)," ",""),"CONTROL","CTRL"),"CTL","CTRL"),"ESCAPE","ESC"),"RETURN","ENTER"),"PAGEDOWN","PGDN"),"PGDOWN","PGDN"),"PAGEUP","PGUP"),"ARROWKEYS","ARROW"),"ARROWKEY","ARROW"),"ARROWS","ARROW"),"DOWNARROW","DOWN"),"UPARROW","UP"),"LEFTARROW","LEFT"),"RIGHTARROW","RIGHT"),"ARROWDOWN","DOWN"),"ARROWUP","UP"),"ARROWLEFT","LEFT"),"ARROWRIGHT","RIGHT"),"↓","DOWN"),"↑","UP"),"←","LEFT"),"→","RIGHT"),"SPACEBAR","SPACE"),"−","-"),"MINUS","-"),"PLUS","+")=Key!$E$14:$H$14),"✔ CLEAR","✘ TRY AGAIN"))),"✘ TRY AGAIN")} | F33: {=IF(E33="Show hint",Key!$B$14,"")} | G33: {=IF(LEFT(D33,1)="✔",IF(E33="Show hint",5,10),0)} -> 0
A34: C5 | B34: In the arena, select F6 and type a formula that multiplies the Price of Pens (C6) by its Qty (D6). Press Enter. | C34: ▶ ARENA C5 (cell F6) | D34: {=IF(ISBLANK('F1-1 Arena'!$F$6),"",IF(NOT(_xlfn.ISFORMULA('F1-1 Arena'!$F$6)),"✘ That's a typed value · enter a formula",IF(ISERROR('F1-1 Arena'!$F$6),"✘ Your formula returns "&IFERROR(CHOOSE(ERROR.TYPE('F1-1 Arena'!$F$6),"#NULL!","#DIV/0!","#VALUE!","#REF!","#NAME?","#NUM!","#N/A","#GETTING_DATA","#SPILL!","#CONNECT!","#BLOCKED!","#UNKNOWN!","#FIELD!","#CALC!"),"an error"),IF(NOT(AND(IFERROR(AND(ISNUMBER('F1-1 Arena'!$F$6),ABS('F1-1 Arena'!$F$6-Key!$C$15)<=1E-9*MAX(1,ABS(Key!$C$15))),FALSE))),"✘ TRY AGAIN","✔ CLEAR"))))} | F34: {=IF(E34="Show hint",Key!$B$15,"")} | G34: {=IF(LEFT(D34,1)="✔",IF(E34="Show hint",5,10),0)} -> 0
A35: C6 | B35: In F7, add 3 to the Price of Pads (C7), then multiply by its Qty (D7). Use parentheses so the addition happens first. | C35: ▶ ARENA C6 (cell F7) | D35: {=IF(ISBLANK('F1-1 Arena'!$F$7),"",IF(NOT(_xlfn.ISFORMULA('F1-1 Arena'!$F$7)),"✘ That's a typed value · enter a formula",IF(ISERROR('F1-1 Arena'!$F$7),"✘ Your formula returns "&IFERROR(CHOOSE(ERROR.TYPE('F1-1 Arena'!$F$7),"#NULL!","#DIV/0!","#VALUE!","#REF!","#NAME?","#NUM!","#N/A","#GETTING_DATA","#SPILL!","#CONNECT!","#BLOCKED!","#UNKNOWN!","#FIELD!","#CALC!"),"an error"),IF(NOT(AND(IFERROR(AND(ISNUMBER('F1-1 Arena'!$F$7),ABS('F1-1 Arena'!$F$7-Key!$C$16)<=1E-9*MAX(1,ABS(Key!$C$16))),FALSE))),"✘ TRY AGAIN","✔ CLEAR"))))} | F35: {=IF(E35="Show hint",Key!$B$16,"")} | G35: {=IF(LEFT(D35,1)="✔",IF(E35="Show hint",5,10),0)} -> 0
A36: C7 | B36: In F8, raise the Qty of Tape (D8) to the power of 2 using ^. | C36: ▶ ARENA C7 (cell F8) | D36: {=IF(ISBLANK('F1-1 Arena'!$F$8),"",IF(NOT(_xlfn.ISFORMULA('F1-1 Arena'!$F$8)),"✘ That's a typed value · enter a formula",IF(ISERROR('F1-1 Arena'!$F$8),"✘ Your formula returns "&IFERROR(CHOOSE(ERROR.TYPE('F1-1 Arena'!$F$8),"#NULL!","#DIV/0!","#VALUE!","#REF!","#NAME?","#NUM!","#N/A","#GETTING_DATA","#SPILL!","#CONNECT!","#BLOCKED!","#UNKNOWN!","#FIELD!","#CALC!"),"an error"),IF(NOT(AND(IFERROR(AND(ISNUMBER('F1-1 Arena'!$F$8),ABS('F1-1 Arena'!$F$8-Key!$C$17)<=1E-9*MAX(1,ABS(Key!$C$17))),FALSE))),"✘ TRY AGAIN",IF(ISNUMBER(FIND("^",_xlfn.FORMULATEXT('F1-1 Arena'!$F$8))),"✔ CLEAR","✘ CLOSE · your formula needs ^")))))} | F36: {=IF(E36="Show hint",Key!$B$17,"")} | G36: {=IF(LEFT(D36,1)="✔",IF(E36="Show hint",5,10),0)} -> 0
A37: C8 | B37: Work it out first, then test it in F9 if you like: what does =10-2*3 return? Type the number. | D37: {=IFERROR(_xlfn.LET(_xlpm.a,'F1-1 Power Up'!$C$37,IF(TRIM(_xlpm.a&"")="","",IF(ABS(IF(ISNUMBER(_xlpm.a),_xlpm.a,VALUE(_xlpm.a&""))-Key!$C$18)<=1E-9*MAX(1,ABS(Key!$C$18)),"✔ CLEAR","✘ TRY AGAIN"))),"✘ TRY AGAIN")} | F37: {=IF(E37="Show hint",Key!$B$18,"")} | G37: {=IF(LEFT(D37,1)="✔",IF(E37="Show hint",5,10),0)} -> 0

Sheet F1-1 Arena
A1: ARENA ▸ F1-1 POWER UP
A2: Practice area · everything here is editable. Missions and their checks are on the stage sheet.
A3: PASS CODE | B3: IGNITE | D3: ◀ Back to F1-1 Power Up
B5: Item | C5: Price | D5: Qty | E5: Your answers ▼
B6: Pens | C6: 2.5 | D6: 4 | E6: Pens: Price × Qty
B7: Pads | C7: 3 | D7: 6 | E7: Pads: (Price + 3) × Qty
B8: Tape | C8: 1.75 | D8: 8 | E8: Tape: Qty squared
B9: Clips | C9: 0.5 | D9: 20 | E9: Scratch pad

Sheet F1-2 Big Six
A1: STAGE F1-2 ▸ BIG SIX
A2: Goal: summarize a column with six core functions
A3: {="SCORE "&TEXT(SUM($G$17:$G$51),"0000")&" / 0280"} -> SCORE 0000 / 0280 | C3: {=IF(SUM($G$17:$G$51)>=280,"★★★",IF(SUM($G$17:$G$51)>=280*0.8,"★★☆",IF(SUM($G$17:$G$51)>=280*0.5,"★☆☆","☆☆☆")))} -> ☆☆☆ | D3: {=REPT("█",ROUND(10*SUM($G$17:$G$51)/280,0))&REPT("░",10-ROUND(10*SUM($G$17:$G$51)/280,0))&" "&TEXT(SUM($G$17:$G$51)/280,"0%")} -> ░░░░░░░░░░ 0% | F3: {=IF(SUM($G$17:$G$51)>=280*0.5,"STAGE CLEAR! ▶ Next: F1-3 Anchors","")}
A5: BRIEFING · new moves in this stage
A6: # | B6: What it does · Pro tip | C6: Keys / Syntax
A7: 1 | B7: Add up numbers: =SUM(B2:B10). Tip: A range is first:last joined by a colon. | C7: SUM
A8: 2 | B8: The mean of the numbers in a range. Tip: Blank cells and text are skipped, not counted as 0. | C8: AVERAGE
A9: 3 | B9: The largest number in a range. Tip: Pair it with MIN to see the spread. | C9: MAX
A10: 4 | B10: The smallest number in a range. Tip: Text such as n/a is ignored. | C10: MIN
A11: 5 | B11: Count the cells that hold numbers. Tip: Text doesn't count: use COUNTA for any filled cell. | C11: COUNT
A12: 6 | B12: Count the cells that are not empty (numbers, text, anything). Tip: The A stands for 'all'. | C12: COUNTA
A13: 7 | B13: AutoSum: insert =SUM() over the numbers above or to the left. Tip: Select the cell under a column of numbers, press Alt+=, then Enter. | C13: Alt+=
A15: WARM-UP · flashback to earlier stages
A16: # | B16: Mission | C16: Your answer | D16: Result | E16: Hint? | F16: Hint | G16: XP
A17: W1 | B17: Which character must every formula start with? (from F1-1 Power Up) | D17: {=IFERROR(_xlfn.LET(_xlpm.a,'F1-2 Big Six'!$C$17,IF(TRIM(_xlpm.a&"")="","",IF(OR(SUBSTITUTE(SUBSTITUTE(SUBSTITUTE(SUBSTITUTE(SUBSTITUTE(SUBSTITUTE(SUBSTITUTE(SUBSTITUTE(SUBSTITUTE(SUBSTITUTE(SUBSTITUTE(SUBSTITUTE(SUBSTITUTE(SUBSTITUTE(SUBSTITUTE(SUBSTITUTE(SUBSTITUTE(SUBSTITUTE(SUBSTITUTE(SUBSTITUTE(SUBSTITUTE(SUBSTITUTE(SUBSTITUTE(SUBSTITUTE(SUBSTITUTE(SUBSTITUTE(SUBSTITUTE(UPPER(_xlpm.a)," ",""),"CONTROL","CTRL"),"CTL","CTRL"),"ESCAPE","ESC"),"RETURN","ENTER"),"PAGEDOWN","PGDN"),"PGDOWN","PGDN"),"PAGEUP","PGUP"),"ARROWKEYS","ARROW"),"ARROWKEY","ARROW"),"ARROWS","ARROW"),"DOWNARROW","DOWN"),"UPARROW","UP"),"LEFTARROW","LEFT"),"RIGHTARROW","RIGHT"),"ARROWDOWN","DOWN"),"ARROWUP","UP"),"ARROWLEFT","LEFT"),"ARROWRIGHT","RIGHT"),"↓","DOWN"),"↑","UP"),"←","LEFT"),"→","RIGHT"),"SPACEBAR","SPACE"),"−","-"),"MINUS","-"),"PLUS","+")=Key!$E$19:$H$19),"✔ CLEAR","✘ TRY AGAIN"))),"✘ TRY AGAIN")} | F17: {=IF(E17="Show hint",Key!$B$19,"")} | G17: {=IF(LEFT(D17,1)="✔",IF(E17="Show hint",5,10),0)} -> 0
A18: W2 | B18: Which operator raises a number to a power? (from F1-1 Power Up) | D18: {=IFERROR(_xlfn.LET(_xlpm.a,'F1-2 Big Six'!$C$18,IF(TRIM(_xlpm.a&"")="","",IF(OR(SUBSTITUTE(SUBSTITUTE(SUBSTITUTE(SUBSTITUTE(SUBSTITUTE(SUBSTITUTE(SUBSTITUTE(SUBSTITUTE(SUBSTITUTE(SUBSTITUTE(SUBSTITUTE(SUBSTITUTE(SUBSTITUTE(SUBSTITUTE(SUBSTITUTE(SUBSTITUTE(SUBSTITUTE(SUBSTITUTE(SUBSTITUTE(SUBSTITUTE(SUBSTITUTE(SUBSTITUTE(SUBSTITUTE(SUBSTITUTE(SUBSTITUTE(SUBSTITUTE(SUBSTITUTE(UPPER(_xlpm.a)," ",""),"CONTROL","CTRL"),"CTL","CTRL"),"ESCAPE","ESC"),"RETURN","ENTER"),"PAGEDOWN","PGDN"),"PGDOWN","PGDN"),"PAGEUP","PGUP"),"ARROWKEYS","ARROW"),"ARROWKEY","ARROW"),"ARROWS","ARROW"),"DOWNARROW","DOWN"),"UPARROW","UP"),"LEFTARROW","LEFT"),"RIGHTARROW","RIGHT"),"ARROWDOWN","DOWN"),"ARROWUP","UP"),"ARROWLEFT","LEFT"),"ARROWRIGHT","RIGHT"),"↓","DOWN"),"↑","UP"),"←","LEFT"),"→","RIGHT"),"SPACEBAR","SPACE"),"−","-"),"MINUS","-"),"PLUS","+")=Key!$E$20:$F$20),"✔ CLEAR","✘ TRY AGAIN"))),"✘ TRY AGAIN")} | F18: {=IF(E18="Show hint",Key!$B$20,"")} | G18: {=IF(LEFT(D18,1)="✔",IF(E18="Show hint",5,10),0)} -> 0
A19: W3 | B19: What does =2+3*4 return? (from F1-1 Power Up) | D19: {=IFERROR(_xlfn.LET(_xlpm.a,'F1-2 Big Six'!$C$19,IF(TRIM(_xlpm.a&"")="","",IF(OR(SUBSTITUTE(SUBSTITUTE(SUBSTITUTE(SUBSTITUTE(SUBSTITUTE(SUBSTITUTE(SUBSTITUTE(SUBSTITUTE(SUBSTITUTE(SUBSTITUTE(SUBSTITUTE(SUBSTITUTE(SUBSTITUTE(SUBSTITUTE(SUBSTITUTE(SUBSTITUTE(SUBSTITUTE(SUBSTITUTE(SUBSTITUTE(SUBSTITUTE(SUBSTITUTE(SUBSTITUTE(SUBSTITUTE(SUBSTITUTE(SUBSTITUTE(SUBSTITUTE(SUBSTITUTE(UPPER(_xlpm.a)," ",""),"CONTROL","CTRL"),"CTL","CTRL"),"ESCAPE","ESC"),"RETURN","ENTER"),"PAGEDOWN","PGDN"),"PGDOWN","PGDN"),"PAGEUP","PGUP"),"ARROWKEYS","ARROW"),"ARROWKEY","ARROW"),"ARROWS","ARROW"),"DOWNARROW","DOWN"),"UPARROW","UP"),"LEFTARROW","LEFT"),"RIGHTARROW","RIGHT"),"ARROWDOWN","DOWN"),"ARROWUP","UP"),"ARROWLEFT","LEFT"),"ARROWRIGHT","RIGHT"),"↓","DOWN"),"↑","UP"),"←","LEFT"),"→","RIGHT"),"SPACEBAR","SPACE"),"−","-"),"MINUS","-"),"PLUS","+")=Key!$E$21:$E$21),"✔ CLEAR","✘ TRY AGAIN"))),"✘ TRY AGAIN")} | F19: {=IF(E19="Show hint",Key!$B$21,"")} | G19: {=IF(LEFT(D19,1)="✔",IF(E19="Show hint",5,10),0)} -> 0
A20: W4 | B20: Type the formula that multiplies cell B2 by cell C2. (from F1-1 Power Up) | D20: {=IFERROR(_xlfn.LET(_xlpm.a,'F1-2 Big Six'!$C$20,IF(TRIM(_xlpm.a&"")="","",IF(OR(SUBSTITUTE(SUBSTITUTE(SUBSTITUTE(SUBSTITUTE(SUBSTITUTE(SUBSTITUTE(SUBSTITUTE(SUBSTITUTE(SUBSTITUTE(SUBSTITUTE(SUBSTITUTE(SUBSTITUTE(SUBSTITUTE(SUBSTITUTE(SUBSTITUTE(SUBSTITUTE(SUBSTITUTE(SUBSTITUTE(SUBSTITUTE(SUBSTITUTE(SUBSTITUTE(SUBSTITUTE(SUBSTITUTE(SUBSTITUTE(SUBSTITUTE(SUBSTITUTE(SUBSTITUTE(UPPER(_xlpm.a)," ",""),"CONTROL","CTRL"),"CTL","CTRL"),"ESCAPE","ESC"),"RETURN","ENTER"),"PAGEDOWN","PGDN"),"PGDOWN","PGDN"),"PAGEUP","PGUP"),"ARROWKEYS","ARROW"),"ARROWKEY","ARROW"),"ARROWS","ARROW"),"DOWNARROW","DOWN"),"UPARROW","UP"),"LEFTARROW","LEFT"),"RIGHTARROW","RIGHT"),"ARROWDOWN","DOWN"),"ARROWUP","UP"),"ARROWLEFT","LEFT"),"ARROWRIGHT","RIGHT"),"↓","DOWN"),"↑","UP"),"←","LEFT"),"→","RIGHT"),"SPACEBAR","SPACE"),"−","-"),"MINUS","-"),"PLUS","+")=Key!$E$22:$H$22),"✔ CLEAR","✘ TRY AGAIN"))),"✘ TRY AGAIN")} | F20: {=IF(E20="Show hint",Key!$B$22,"")} | G20: {=IF(LEFT(D20,1)="✔",IF(E20="Show hint",5,10),0)} -> 0
A21: W5 | B21: Which keys grow the selection by one cell? (from S1-3 Lasso) | D21: {=IFERROR(_xlfn.LET(_xlpm.a,'F1-2 Big Six'!$C$21,IF(TRIM(_xlpm.a&"")="","",IF(OR(SUBSTITUTE(SUBSTITUTE(SUBSTITUTE(SUBSTITUTE(SUBSTITUTE(SUBSTITUTE(SUBSTITUTE(SUBSTITUTE(SUBSTITUTE(SUBSTITUTE(SUBSTITUTE(SUBSTITUTE(SUBSTITUTE(SUBSTITUTE(SUBSTITUTE(SUBSTITUTE(SUBSTITUTE(SUBSTITUTE(SUBSTITUTE(SUBSTITUTE(SUBSTITUTE(SUBSTITUTE(SUBSTITUTE(SUBSTITUTE(SUBSTITUTE(SUBSTITUTE(SUBSTITUTE(UPPER(_xlpm.a)," ",""),"CONTROL","CTRL"),"CTL","CTRL"),"ESCAPE","ESC"),"RETURN","ENTER"),"PAGEDOWN","PGDN"),"PGDOWN","PGDN"),"PAGEUP","PGUP"),"ARROWKEYS","ARROW"),"ARROWKEY","ARROW"),"ARROWS","ARROW"),"DOWNARROW","DOWN"),"UPARROW","UP"),"LEFTARROW","LEFT"),"RIGHTARROW","RIGHT"),"ARROWDOWN","DOWN"),"ARROWUP","UP"),"ARROWLEFT","LEFT"),"ARROWRIGHT","RIGHT"),"↓","DOWN"),"↑","UP"),"←","LEFT"),"→","RIGHT"),"SPACEBAR","SPACE"),"−","-"),"MINUS","-"),"PLUS","+")=Key!$E$23:$I$23),"✔ CLEAR","✘ TRY AGAIN"))),"✘ TRY AGAIN")} | F21: {=IF(E21="Show hint",Key!$B$23,"")} | G21: {=IF(LEFT(D21,1)="✔",IF(E21="Show hint",5,10),0)} -> 0
A22: W6 | B22: Which keys extend the selection all the way to the edge of the data? (from S1-3 Lasso) | D22: {=IFERROR(_xlfn.LET(_xlpm.a,'F1-2 Big Six'!$C$22,IF(TRIM(_xlpm.a&"")="","",IF(OR(SUBSTITUTE(SUBSTITUTE(SUBSTITUTE(SUBSTITUTE(SUBSTITUTE(SUBSTITUTE(SUBSTITUTE(SUBSTITUTE(SUBSTITUTE(SUBSTITUTE(SUBSTITUTE(SUBSTITUTE(SUBSTITUTE(SUBSTITUTE(SUBSTITUTE(SUBSTITUTE(SUBSTITUTE(SUBSTITUTE(SUBSTITUTE(SUBSTITUTE(SUBSTITUTE(SUBSTITUTE(SUBSTITUTE(SUBSTITUTE(SUBSTITUTE(SUBSTITUTE(SUBSTITUTE(UPPER(_xlpm.a)," ",""),"CONTROL","CTRL"),"CTL","CTRL"),"ESCAPE","ESC"),"RETURN","ENTER"),"PAGEDOWN","PGDN"),"PGDOWN","PGDN"),"PAGEUP","PGUP"),"ARROWKEYS","ARROW"),"ARROWKEY","ARROW"),"ARROWS","ARROW"),"DOWNARROW","DOWN"),"UPARROW","UP"),"LEFTARROW","LEFT"),"RIGHTARROW","RIGHT"),"ARROWDOWN","DOWN"),"ARROWUP","UP"),"ARROWLEFT","LEFT"),"ARROWRIGHT","RIGHT"),"↓","DOWN"),"↑","UP"),"←","LEFT"),"→","RIGHT"),"SPACEBAR","SPACE"),"−","-"),"MINUS","-"),"PLUS","+")=Key!$E$24:$N$24),"✔ CLEAR","✘ TRY AGAIN"))),"✘ TRY AGAIN")} | F22: {=IF(E22="Show hint",Key!$B$24,"")} | G22: {=IF(LEFT(D22,1)="✔",IF(E22="Show hint",5,10),0)} -> 0
A23: W7 | B23: Which keys extend the selection to the last used cell? (from S1-3 Lasso) | D23: {=IFERROR(_xlfn.LET(_xlpm.a,'F1-2 Big Six'!$C$23,IF(TRIM(_xlpm.a&"")="","",IF(OR(SUBSTITUTE(SUBSTITUTE(SUBSTITUTE(SUBSTITUTE(SUBSTITUTE(SUBSTITUTE(SUBSTITUTE(SUBSTITUTE(SUBSTITUTE(SUBSTITUTE(SUBSTITUTE(SUBSTITUTE(SUBSTITUTE(SUBSTITUTE(SUBSTITUTE(SUBSTITUTE(SUBSTITUTE(SUBSTITUTE(SUBSTITUTE(SUBSTITUTE(SUBSTITUTE(SUBSTITUTE(SUBSTITUTE(SUBSTITUTE(SUBSTITUTE(SUBSTITUTE(SUBSTITUTE(UPPER(_xlpm.a)," ",""),"CONTROL","CTRL"),"CTL","CTRL"),"ESCAPE","ESC"),"RETURN","ENTER"),"PAGEDOWN","PGDN"),"PGDOWN","PGDN"),"PAGEUP","PGUP"),"ARROWKEYS","ARROW"),"ARROWKEY","ARROW"),"ARROWS","ARROW"),"DOWNARROW","DOWN"),"UPARROW","UP"),"LEFTARROW","LEFT"),"RIGHTARROW","RIGHT"),"ARROWDOWN","DOWN"),"ARROWUP","UP"),"ARROWLEFT","LEFT"),"ARROWRIGHT","RIGHT"),"↓","DOWN"),"↑","UP"),"←","LEFT"),"→","RIGHT"),"SPACEBAR","SPACE"),"−","-"),"MINUS","-"),"PLUS","+")=Key!$E$25:$F$25),"✔ CLEAR","✘ TRY AGAIN"))),"✘ TRY AGAIN")} | F23: {=IF(E23="Show hint",Key!$B$25,"")} | G23: {=IF(LEFT(D23,1)="✔",IF(E23="Show hint",5,10),0)} -> 0
A24: W8 | B24: Which keys extend the selection back to cell A1? (from S1-3 Lasso) | D24: {=IFERROR(_xlfn.LET(_xlpm.a,'F1-2 Big Six'!$C$24,IF(TRIM(_xlpm.a&"")="","",IF(OR(SUBSTITUTE(SUBSTITUTE(SUBSTITUTE(SUBSTITUTE(SUBSTITUTE(SUBSTITUTE(SUBSTITUTE(SUBSTITUTE(SUBSTITUTE(SUBSTITUTE(SUBSTITUTE(SUBSTITUTE(SUBSTITUTE(SUBSTITUTE(SUBSTITUTE(SUBSTITUTE(SUBSTITUTE(SUBSTITUTE(SUBSTITUTE(SUBSTITUTE(SUBSTITUTE(SUBSTITUTE(SUBSTITUTE(SUBSTITUTE(SUBSTITUTE(SUBSTITUTE(SUBSTITUTE(UPPER(_xlpm.a)," ",""),"CONTROL","CTRL"),"CTL","CTRL"),"ESCAPE","ESC"),"RETURN","ENTER"),"PAGEDOWN","PGDN"),"PGDOWN","PGDN"),"PAGEUP","PGUP"),"ARROWKEYS","ARROW"),"ARROWKEY","ARROW"),"ARROWS","ARROW"),"DOWNARROW","DOWN"),"UPARROW","UP"),"LEFTARROW","LEFT"),"RIGHTARROW","RIGHT"),"ARROWDOWN","DOWN"),"ARROWUP","UP"),"ARROWLEFT","LEFT"),"ARROWRIGHT","RIGHT"),"↓","DOWN"),"↑","UP"),"←","LEFT"),"→","RIGHT"),"SPACEBAR","SPACE"),"−","-"),"MINUS","-"),"PLUS","+")=Key!$E$26:$F$26),"✔ CLEAR","✘ TRY AGAIN"))),"✘ TRY AGAIN")} | F24: {=IF(E24="Show hint",Key!$B$26,"")} | G24: {=IF(LEFT(D24,1)="✔",IF(E24="Show hint",5,10),0)} -> 0
A26: TRAINING · recognize the move (pick from the list)
A27: # | B27: Mission | C27: Your answer | D27: Result | E27: Hint? | F27: Hint | G27: XP
A28: T1 | B28: Which function adds up a range of numbers? | D28: {=IFERROR(IF('F1-2 Big Six'!$C$28&""="","",IF('F1-2 Big Six'!$C$28&""=Key!$C$27&"","✔ CLEAR","✘ TRY AGAIN")),"✘ TRY AGAIN")} | F28: {=IF(E28="Show hint",Key!$B$27,"")} | G28: {=IF(LEFT(D28,1)="✔",IF(E28="Show hint",5,10),0)} -> 0
A29: T2 | B29: Which function returns the mean of a range? | D29: {=IFERROR(IF('F1-2 Big Six'!$C$29&""="","",IF('F1-2 Big Six'!$C$29&""=Key!$C$28&"","✔ CLEAR","✘ TRY AGAIN")),"✘ TRY AGAIN")} | F29: {=IF(E29="Show hint",Key!$B$28,"")} | G29: {=IF(LEFT(D29,1)="✔",IF(E29="Show hint",5,10),0)} -> 0
A30: T3 | B30: Which function returns the largest number in a range? | D30: {=IFERROR(IF('F1-2 Big Six'!$C$30&""="","",IF('F1-2 Big Six'!$C$30&""=Key!$C$29&"","✔ CLEAR","✘ TRY AGAIN")),"✘ TRY AGAIN")} | F30: {=IF(E30="Show hint",Key!$B$29,"")} | G30: {=IF(LEFT(D30,1)="✔",IF(E30="Show hint",5,10),0)} -> 0
A31: T4 | B31: Which function returns the smallest number in a range? | D31: {=IFERROR(IF('F1-2 Big Six'!$C$31&""="","",IF('F1-2 Big Six'!$C$31&""=Key!$C$30&"","✔ CLEAR","✘ TRY AGAIN")),"✘ TRY AGAIN")} | F31: {=IF(E31="Show hint",Key!$B$30,"")} | G31: {=IF(LEFT(D31,1)="✔",IF(E31="Show hint",5,10),0)} -> 0
A32: T5 | B32: Which function counts only the cells that hold numbers? | D32: {=IFERROR(IF('F1-2 Big Six'!$C$32&""="","",IF('F1-2 Big Six'!$C$32&""=Key!$C$31&"","✔ CLEAR","✘ TRY AGAIN")),"✘ TRY AGAIN")} | F32: {=IF(E32="Show hint",Key!$B$31,"")} | G32: {=IF(LEFT(D32,1)="✔",IF(E32="Show hint",5,10),0)} -> 0
A33: T6 | B33: Which function counts every non-empty cell? | D33: {=IFERROR(IF('F1-2 Big Six'!$C$33&""="","",IF('F1-2 Big Six'!$C$33&""=Key!$C$32&"","✔ CLEAR","✘ TRY AGAIN")),"✘ TRY AGAIN")} | F33: {=IF(E33="Show hint",Key!$B$32,"")} | G33: {=IF(LEFT(D33,1)="✔",IF(E33="Show hint",5,10),0)} -> 0
A34: T7 | B34: Which keys insert an AutoSum formula? | D34: {=IFERROR(IF('F1-2 Big Six'!$C$34&""="","",IF('F1-2 Big Six'!$C$34&""=Key!$C$33&"","✔ CLEAR","✘ TRY AGAIN")),"✘ TRY AGAIN")} | F34: {=IF(E34="Show hint",Key!$B$33,"")} | G34: {=IF(LEFT(D34,1)="✔",IF(E34="Show hint",5,10),0)} -> 0
A36: CHALLENGES · recall it, then do it
B37: ▶ Open F1-2 Arena (or press Ctrl+PgDn)
A38: # | B38: Mission | C38: Your answer | D38: Result | E38: Hint? | F38: Hint | G38: XP
A39: C1 | B39: Which function adds up a range of numbers? | D39: {=IFERROR(_xlfn.LET(_xlpm.a,'F1-2 Big Six'!$C$39,IF(TRIM(_xlpm.a&"")="","",IF(OR(SUBSTITUTE(SUBSTITUTE(SUBSTITUTE(SUBSTITUTE(SUBSTITUTE(SUBSTITUTE(SUBSTITUTE(SUBSTITUTE(SUBSTITUTE(SUBSTITUTE(SUBSTITUTE(SUBSTITUTE(SUBSTITUTE(SUBSTITUTE(SUBSTITUTE(SUBSTITUTE(SUBSTITUTE(SUBSTITUTE(SUBSTITUTE(SUBSTITUTE(SUBSTITUTE(SUBSTITUTE(SUBSTITUTE(SUBSTITUTE(SUBSTITUTE(SUBSTITUTE(SUBSTITUTE(UPPER(_xlpm.a)," ",""),"CONTROL","CTRL"),"CTL","CTRL"),"ESCAPE","ESC"),"RETURN","ENTER"),"PAGEDOWN","PGDN"),"PGDOWN","PGDN"),"PAGEUP","PGUP"),"ARROWKEYS","ARROW"),"ARROWKEY","ARROW"),"ARROWS","ARROW"),"DOWNARROW","DOWN"),"UPARROW","UP"),"LEFTARROW","LEFT"),"RIGHTARROW","RIGHT"),"ARROWDOWN","DOWN"),"ARROWUP","UP"),"ARROWLEFT","LEFT"),"ARROWRIGHT","RIGHT"),"↓","DOWN"),"↑","UP"),"←","LEFT"),"→","RIGHT"),"SPACEBAR","SPACE"),"−","-"),"MINUS","-"),"PLUS","+")=Key!$E$34:$J$34),"✔ CLEAR","✘ TRY AGAIN"))),"✘ TRY AGAIN")} | F39: {=IF(E39="Show hint",Key!$B$34,"")} | G39: {=IF(LEFT(D39,1)="✔",IF(E39="Show hint",5,10),0)} -> 0
A40: C2 | B40: Which function returns the mean of a range? | D40: {=IFERROR(_xlfn.LET(_xlpm.a,'F1-2 Big Six'!$C$40,IF(TRIM(_xlpm.a&"")="","",IF(OR(SUBSTITUTE(SUBSTITUTE(SUBSTITUTE(SUBSTITUTE(SUBSTITUTE(SUBSTITUTE(SUBSTITUTE(SUBSTITUTE(SUBSTITUTE(SUBSTITUTE(SUBSTITUTE(SUBSTITUTE(SUBSTITUTE(SUBSTITUTE(SUBSTITUTE(SUBSTITUTE(SUBSTITUTE(SUBSTITUTE(SUBSTITUTE(SUBSTITUTE(SUBSTITUTE(SUBSTITUTE(SUBSTITUTE(SUBSTITUTE(SUBSTITUTE(SUBSTITUTE(SUBSTITUTE(UPPER(_xlpm.a)," ",""),"CONTROL","CTRL"),"CTL","CTRL"),"ESCAPE","ESC"),"RETURN","ENTER"),"PAGEDOWN","PGDN"),"PGDOWN","PGDN"),"PAGEUP","PGUP"),"ARROWKEYS","ARROW"),"ARROWKEY","ARROW"),"ARROWS","ARROW"),"DOWNARROW","DOWN"),"UPARROW","UP"),"LEFTARROW","LEFT"),"RIGHTARROW","RIGHT"),"ARROWDOWN","DOWN"),"ARROWUP","UP"),"ARROWLEFT","LEFT"),"ARROWRIGHT","RIGHT"),"↓","DOWN"),"↑","UP"),"←","LEFT"),"→","RIGHT"),"SPACEBAR","SPACE"),"−","-"),"MINUS","-"),"PLUS","+")=Key!$E$35:$J$35),"✔ CLEAR","✘ TRY AGAIN"))),"✘ TRY AGAIN")} | F40: {=IF(E40="Show hint",Key!$B$35,"")} | G40: {=IF(LEFT(D40,1)="✔",IF(E40="Show hint",5,10),0)} -> 0
A41: C3 | B41: Which function returns the largest number in a range? | D41: {=IFERROR(_xlfn.LET(_xlpm.a,'F1-2 Big Six'!$C$41,IF(TRIM(_xlpm.a&"")="","",IF(OR(SUBSTITUTE(SUBSTITUTE(SUBSTITUTE(SUBSTITUTE(SUBSTITUTE(SUBSTITUTE(SUBSTITUTE(SUBSTITUTE(SUBSTITUTE(SUBSTITUTE(SUBSTITUTE(SUBSTITUTE(SUBSTITUTE(SUBSTITUTE(SUBSTITUTE(SUBSTITUTE(SUBSTITUTE(SUBSTITUTE(SUBSTITUTE(SUBSTITUTE(SUBSTITUTE(SUBSTITUTE(SUBSTITUTE(SUBSTITUTE(SUBSTITUTE(SUBSTITUTE(SUBSTITUTE(UPPER(_xlpm.a)," ",""),"CONTROL","CTRL"),"CTL","CTRL"),"ESCAPE","ESC"),"RETURN","ENTER"),"PAGEDOWN","PGDN"),"PGDOWN","PGDN"),"PAGEUP","PGUP"),"ARROWKEYS","ARROW"),"ARROWKEY","ARROW"),"ARROWS","ARROW"),"DOWNARROW","DOWN"),"UPARROW","UP"),"LEFTARROW","LEFT"),"RIGHTARROW","RIGHT"),"ARROWDOWN","DOWN"),"ARROWUP","UP"),"ARROWLEFT","LEFT"),"ARROWRIGHT","RIGHT"),"↓","DOWN"),"↑","UP"),"←","LEFT"),"→","RIGHT"),"SPACEBAR","SPACE"),"−","-"),"MINUS","-"),"PLUS","+")=Key!$E$36:$J$36),"✔ CLEAR","✘ TRY AGAIN"))),"✘ TRY AGAIN")} | F41: {=IF(E41="Show hint",Key!$B$36,"")} | G41: {=IF(LEFT(D41,1)="✔",IF(E41="Show hint",5,10),0)} -> 0
A42: C4 | B42: Which function returns the smallest number in a range? | D42: {=IFERROR(_xlfn.LET(_xlpm.a,'F1-2 Big Six'!$C$42,IF(TRIM(_xlpm.a&"")="","",IF(OR(SUBSTITUTE(SUBSTITUTE(SUBSTITUTE(SUBSTITUTE(SUBSTITUTE(SUBSTITUTE(SUBSTITUTE(SUBSTITUTE(SUBSTITUTE(SUBSTITUTE(SUBSTITUTE(SUBSTITUTE(SUBSTITUTE(SUBSTITUTE(SUBSTITUTE(SUBSTITUTE(SUBSTITUTE(SUBSTITUTE(SUBSTITUTE(SUBSTITUTE(SUBSTITUTE(SUBSTITUTE(SUBSTITUTE(SUBSTITUTE(SUBSTITUTE(SUBSTITUTE(SUBSTITUTE(UPPER(_xlpm.a)," ",""),"CONTROL","CTRL"),"CTL","CTRL"),"ESCAPE","ESC"),"RETURN","ENTER"),"PAGEDOWN","PGDN"),"PGDOWN","PGDN"),"PAGEUP","PGUP"),"ARROWKEYS","ARROW"),"ARROWKEY","ARROW"),"ARROWS","ARROW"),"DOWNARROW","DOWN"),"UPARROW","UP"),"LEFTARROW","LEFT"),"RIGHTARROW","RIGHT"),"ARROWDOWN","DOWN"),"ARROWUP","UP"),"ARROWLEFT","LEFT"),"ARROWRIGHT","RIGHT"),"↓","DOWN"),"↑","UP"),"←","LEFT"),"→","RIGHT"),"SPACEBAR","SPACE"),"−","-"),"MINUS","-"),"PLUS","+")=Key!$E$37:$J$37),"✔ CLEAR","✘ TRY AGAIN"))),"✘ TRY AGAIN")} | F42: {=IF(E42="Show hint",Key!$B$37,"")} | G42: {=IF(LEFT(D42,1)="✔",IF(E42="Show hint",5,10),0)} -> 0
A43: C5 | B43: Which function counts only the cells that hold numbers? | D43: {=IFERROR(_xlfn.LET(_xlpm.a,'F1-2 Big Six'!$C$43,IF(TRIM(_xlpm.a&"")="","",IF(OR(SUBSTITUTE(SUBSTITUTE(SUBSTITUTE(SUBSTITUTE(SUBSTITUTE(SUBSTITUTE(SUBSTITUTE(SUBSTITUTE(SUBSTITUTE(SUBSTITUTE(SUBSTITUTE(SUBSTITUTE(SUBSTITUTE(SUBSTITUTE(SUBSTITUTE(SUBSTITUTE(SUBSTITUTE(SUBSTITUTE(SUBSTITUTE(SUBSTITUTE(SUBSTITUTE(SUBSTITUTE(SUBSTITUTE(SUBSTITUTE(SUBSTITUTE(SUBSTITUTE(SUBSTITUTE(UPPER(_xlpm.a)," ",""),"CONTROL","CTRL"),"CTL","CTRL"),"ESCAPE","ESC"),"RETURN","ENTER"),"PAGEDOWN","PGDN"),"PGDOWN","PGDN"),"PAGEUP","PGUP"),"ARROWKEYS","ARROW"),"ARROWKEY","ARROW"),"ARROWS","ARROW"),"DOWNARROW","DOWN"),"UPARROW","UP"),"LEFTARROW","LEFT"),"RIGHTARROW","RIGHT"),"ARROWDOWN","DOWN"),"ARROWUP","UP"),"ARROWLEFT","LEFT"),"ARROWRIGHT","RIGHT"),"↓","DOWN"),"↑","UP"),"←","LEFT"),"→","RIGHT"),"SPACEBAR","SPACE"),"−","-"),"MINUS","-"),"PLUS","+")=Key!$E$38:$J$38),"✔ CLEAR","✘ TRY AGAIN"))),"✘ TRY AGAIN")} | F43: {=IF(E43="Show hint",Key!$B$38,"")} | G43: {=IF(LEFT(D43,1)="✔",IF(E43="Show hint",5,10),0)} -> 0
A44: C6 | B44: Which function counts every non-empty cell? | D44: {=IFERROR(_xlfn.LET(_xlpm.a,'F1-2 Big Six'!$C$44,IF(TRIM(_xlpm.a&"")="","",IF(OR(SUBSTITUTE(SUBSTITUTE(SUBSTITUTE(SUBSTITUTE(SUBSTITUTE(SUBSTITUTE(SUBSTITUTE(SUBSTITUTE(SUBSTITUTE(SUBSTITUTE(SUBSTITUTE(SUBSTITUTE(SUBSTITUTE(SUBSTITUTE(SUBSTITUTE(SUBSTITUTE(SUBSTITUTE(SUBSTITUTE(SUBSTITUTE(SUBSTITUTE(SUBSTITUTE(SUBSTITUTE(SUBSTITUTE(SUBSTITUTE(SUBSTITUTE(SUBSTITUTE(SUBSTITUTE(UPPER(_xlpm.a)," ",""),"CONTROL","CTRL"),"CTL","CTRL"),"ESCAPE","ESC"),"RETURN","ENTER"),"PAGEDOWN","PGDN"),"PGDOWN","PGDN"),"PAGEUP","PGUP"),"ARROWKEYS","ARROW"),"ARROWKEY","ARROW"),"ARROWS","ARROW"),"DOWNARROW","DOWN"),"UPARROW","UP"),"LEFTARROW","LEFT"),"RIGHTARROW","RIGHT"),"ARROWDOWN","DOWN"),"ARROWUP","UP"),"ARROWLEFT","LEFT"),"ARROWRIGHT","RIGHT"),"↓","DOWN"),"↑","UP"),"←","LEFT"),"→","RIGHT"),"SPACEBAR","SPACE"),"−","-"),"MINUS","-"),"PLUS","+")=Key!$E$39:$J$39),"✔ CLEAR","✘ TRY AGAIN"))),"✘ TRY AGAIN")} | F44: {=IF(E44="Show hint",Key!$B$39,"")} | G44: {=IF(LEFT(D44,1)="✔",IF(E44="Show hint",5,10),0)} -> 0
A45: C7 | B45: Which keys insert an AutoSum formula? | D45: {=IFERROR(_xlfn.LET(_xlpm.a,'F1-2 Big Six'!$C$45,IF(TRIM(_xlpm.a&"")="","",IF(OR(SUBSTITUTE(SUBSTITUTE(SUBSTITUTE(SUBSTITUTE(SUBSTITUTE(SUBSTITUTE(SUBSTITUTE(SUBSTITUTE(SUBSTITUTE(SUBSTITUTE(SUBSTITUTE(SUBSTITUTE(SUBSTITUTE(SUBSTITUTE(SUBSTITUTE(SUBSTITUTE(SUBSTITUTE(SUBSTITUTE(SUBSTITUTE(SUBSTITUTE(SUBSTITUTE(SUBSTITUTE(SUBSTITUTE(SUBSTITUTE(SUBSTITUTE(SUBSTITUTE(SUBSTITUTE(UPPER(_xlpm.a)," ",""),"CONTROL","CTRL"),"CTL","CTRL"),"ESCAPE","ESC"),"RETURN","ENTER"),"PAGEDOWN","PGDN"),"PGDOWN","PGDN"),"PAGEUP","PGUP"),"ARROWKEYS","ARROW"),"ARROWKEY","ARROW"),"ARROWS","ARROW"),"DOWNARROW","DOWN"),"UPARROW","UP"),"LEFTARROW","LEFT"),"RIGHTARROW","RIGHT"),"ARROWDOWN","DOWN"),"ARROWUP","UP"),"ARROWLEFT","LEFT"),"ARROWRIGHT","RIGHT"),"↓","DOWN"),"↑","UP"),"←","LEFT"),"→","RIGHT"),"SPACEBAR","SPACE"),"−","-"),"MINUS","-"),"PLUS","+")=Key!$E$40:$E$40),"✔ CLEAR","✘ TRY AGAIN"))),"✘ TRY AGAIN")} | F45: {=IF(E45="Show hint",Key!$B$40,"")} | G45: {=IF(LEFT(D45,1)="✔",IF(E45="Show hint",5,10),0)} -> 0
A46: C8 | B46: In the arena, select C18 (just under Sales) and press Alt+= then Enter. AutoSum writes the SUM formula for you. | C46: ▶ ARENA C8 (cell C18) | D46: {=IF(ISBLANK('F1-2 Arena'!$C$18),"",IF(NOT(_xlfn.ISFORMULA('F1-2 Arena'!$C$18)),"✘ That's a typed value · enter a formula",IF(ISERROR('F1-2 Arena'!$C$18),"✘ Your formula returns "&IFERROR(CHOOSE(ERROR.TYPE('F1-2 Arena'!$C$18),"#NULL!","#DIV/0!","#VALUE!","#REF!","#NAME?","#NUM!","#N/A","#GETTING_DATA","#SPILL!","#CONNECT!","#BLOCKED!","#UNKNOWN!","#FIELD!","#CALC!"),"an error"),IF(NOT(AND(IFERROR(AND(ISNUMBER('F1-2 Arena'!$C$18),ABS('F1-2 Arena'!$C$18-Key!$C$41)<=1E-9*MAX(1,ABS(Key!$C$41))),FALSE))),"✘ TRY AGAIN",IF(AND(OR(ISNUMBER(FIND({"=","(",",","+","-","*","/","&"," ","<",">",":","@","^"}&"SUM"&"(",UPPER(_xlfn.FORMULATEXT('F1-2 Arena'!$C$18)))))),"✔ CLEAR","✘ CLOSE · right value, but use SUM")))))} | F46: {=IF(E46="Show hint",Key!$B$41,"")} | G46: {=IF(LEFT(D46,1)="✔",IF(E46="Show hint",5,10),0)} -> 0
A47: C9 | B47: In G6, find the average monthly Sales with AVERAGE. | C47: ▶ ARENA C9 (cell G6) | D47: {=IF(ISBLANK('F1-2 Arena'!$G$6),"",IF(NOT(_xlfn.ISFORMULA('F1-2 Arena'!$G$6)),"✘ That's a typed value · enter a formula",IF(ISERROR('F1-2 Arena'!$G$6),"✘ Your formula returns "&IFERROR(CHOOSE(ERROR.TYPE('F1-2 Arena'!$G$6),"#NULL!","#DIV/0!","#VALUE!","#REF!","#NAME?","#NUM!","#N/A","#GETTING_DATA","#SPILL!","#CONNECT!","#BLOCKED!","#UNKNOWN!","#FIELD!","#CALC!"),"an error"),IF(NOT(AND(IFERROR(AND(ISNUMBER('F1-2 Arena'!$G$6),ABS('F1-2 Arena'!$G$6-Key!$C$42)<=1E-9*MAX(1,ABS(Key!$C$42))),FALSE))),"✘ TRY AGAIN",IF(AND(OR(ISNUMBER(FIND({"=","(",",","+","-","*","/","&"," ","<",">",":","@","^"}&"AVERAGE"&"(",UPPER(_xlfn.FORMULATEXT('F1-2 Arena'!$G$6)))))),"✔ CLEAR","✘ CLOSE · right value, but use AVERAGE")))))} | F47: {=IF(E47="Show hint",Key!$B$42,"")} | G47: {=IF(LEFT(D47,1)="✔",IF(E47="Show hint",5,10),0)} -> 0
A48: C10 | B48: In G7, find the best month's Sales with MAX. | C48: ▶ ARENA C10 (cell G7) | D48: {=IF(ISBLANK('F1-2 Arena'!$G$7),"",IF(NOT(_xlfn.ISFORMULA('F1-2 Arena'!$G$7)),"✘ That's a typed value · enter a formula",IF(ISERROR('F1-2 Arena'!$G$7),"✘ Your formula returns "&IFERROR(CHOOSE(ERROR.TYPE('F1-2 Arena'!$G$7),"#NULL!","#DIV/0!","#VALUE!","#REF!","#NAME?","#NUM!","#N/A","#GETTING_DATA","#SPILL!","#CONNECT!","#BLOCKED!","#UNKNOWN!","#FIELD!","#CALC!"),"an error"),IF(NOT(AND(IFERROR(AND(ISNUMBER('F1-2 Arena'!$G$7),ABS('F1-2 Arena'!$G$7-Key!$C$43)<=1E-9*MAX(1,ABS(Key!$C$43))),FALSE))),"✘ TRY AGAIN",IF(AND(OR(ISNUMBER(FIND({"=","(",",","+","-","*","/","&"," ","<",">",":","@","^"}&"MAX"&"(",UPPER(_xlfn.FORMULATEXT('F1-2 Arena'!$G$7)))))),"✔ CLEAR","✘ CLOSE · right value, but use MAX")))))} | F48: {=IF(E48="Show hint",Key!$B$43,"")} | G48: {=IF(LEFT(D48,1)="✔",IF(E48="Show hint",5,10),0)} -> 0
A49: C11 | B49: In G8, find the worst month's Sales with MIN. | C49: ▶ ARENA C11 (cell G8) | D49: {=IF(ISBLANK('F1-2 Arena'!$G$8),"",IF(NOT(_xlfn.ISFORMULA('F1-2 Arena'!$G$8)),"✘ That's a typed value · enter a formula",IF(ISERROR('F1-2 Arena'!$G$8),"✘ Your formula returns "&IFERROR(CHOOSE(ERROR.TYPE('F1-2 Arena'!$G$8),"#NULL!","#DIV/0!","#VALUE!","#REF!","#NAME?","#NUM!","#N/A","#GETTING_DATA","#SPILL!","#CONNECT!","#BLOCKED!","#UNKNOWN!","#FIELD!","#CALC!"),"an error"),IF(NOT(AND(IFERROR(AND(ISNUMBER('F1-2 Arena'!$G$8),ABS('F1-2 Arena'!$G$8-Key!$C$44)<=1E-9*MAX(1,ABS(Key!$C$44))),FALSE))),"✘ TRY AGAIN",IF(AND(OR(ISNUMBER(FIND({"=","(",",","+","-","*","/","&"," ","<",">",":","@","^"}&"MIN"&"(",UPPER(_xlfn.FORMULATEXT('F1-2 Arena'!$G$8)))))),"✔ CLEAR","✘ CLOSE · right value, but use MIN")))))} | F49: {=IF(E49="Show hint",Key!$B$44,"")} | G49: {=IF(LEFT(D49,1)="✔",IF(E49="Show hint",5,10),0)} -> 0
A50: C12 | B50: In G9, count how many Returns cells (D6:D17) hold numbers. Use COUNT. | C50: ▶ ARENA C12 (cell G9) | D50: {=IF(ISBLANK('F1-2 Arena'!$G$9),"",IF(NOT(_xlfn.ISFORMULA('F1-2 Arena'!$G$9)),"✘ That's a typed value · enter a formula",IF(ISERROR('F1-2 Arena'!$G$9),"✘ Your formula returns "&IFERROR(CHOOSE(ERROR.TYPE('F1-2 Arena'!$G$9),"#NULL!","#DIV/0!","#VALUE!","#REF!","#NAME?","#NUM!","#N/A","#GETTING_DATA","#SPILL!","#CONNECT!","#BLOCKED!","#UNKNOWN!","#FIELD!","#CALC!"),"an error"),IF(NOT(AND(IFERROR(AND(ISNUMBER('F1-2 Arena'!$G$9),ABS('F1-2 Arena'!$G$9-Key!$C$45)<=1E-9*MAX(1,ABS(Key!$C$45))),FALSE))),"✘ TRY AGAIN",IF(AND(OR(ISNUMBER(FIND({"=","(",",","+","-","*","/","&"," ","<",">",":","@","^"}&"COUNT"&"(",UPPER(_xlfn.FORMULATEXT('F1-2 Arena'!$G$9)))))),"✔ CLEAR","✘ CLOSE · right value, but use COUNT")))))} | F50: {=IF(E50="Show hint",Key!$B$45,"")} | G50: {=IF(LEFT(D50,1)="✔",IF(E50="Show hint",5,10),0)} -> 0
A51: C13 | B51: In G10, count every filled Returns cell, text included. Use COUNTA. | C51: ▶ ARENA C13 (cell G10) | D51: {=IF(ISBLANK('F1-2 Arena'!$G$10),"",IF(NOT(_xlfn.ISFORMULA('F1-2 Arena'!$G$10)),"✘ That's a typed value · enter a formula",IF(ISERROR('F1-2 Arena'!$G$10),"✘ Your formula returns "&IFERROR(CHOOSE(ERROR.TYPE('F1-2 Arena'!$G$10),"#NULL!","#DIV/0!","#VALUE!","#REF!","#NAME?","#NUM!","#N/A","#GETTING_DATA","#SPILL!","#CONNECT!","#BLOCKED!","#UNKNOWN!","#FIELD!","#CALC!"),"an error"),IF(NOT(AND(IFERROR(AND(ISNUMBER('F1-2 Arena'!$G$10),ABS('F1-2 Arena'!$G$10-Key!$C$46)<=1E-9*MAX(1,ABS(Key!$C$46))),FALSE))),"✘ TRY AGAIN",IF(AND(OR(ISNUMBER(FIND({"=","(",",","+","-","*","/","&"," ","<",">",":","@","^"}&"COUNTA"&"(",UPPER(_xlfn.FORMULATEXT('F1-2 Arena'!$G$10)))))),"✔ CLEAR","✘ CLOSE · right value, but use COUNTA")))))} | F51: {=IF(E51="Show hint",Key!$B$46,"")} | G51: {=IF(LEFT(D51,1)="✔",IF(E51="Show hint",5,10),0)} -> 0

Sheet F1-2 Arena
A1: ARENA ▸ F1-2 BIG SIX
A2: Practice area · everything here is editable. Missions and their checks are on the stage sheet.
A3: PASS CODE | B3: TALLY | D3: ◀ Back to F1-2 Big Six
B5: Month | C5: Sales | D5: Returns | F5: Your answers ▼
B6: Jan | C6: 420 | D6: 3 | F6: Average sales
B7: Feb | C7: 515 | D7: 5 | F7: Best month
B8: Mar | C8: 380 | D8: n/a | F8: Worst month
B9: Apr | C9: 610 | D9: 2 | F9: Returns that are numbers
B10: May | C10: 450 | D10: 4 | F10: Filled Returns cells
B11: Jun | C11: 555 | D11: 6
B12: Jul | C12: 700 | D12: n/a
B13: Aug | C13: 640 | D13: 1
B14: Sep | C14: 480 | D14: 0
B15: Oct | C15: 530 | D15: 2
B16: Nov | C16: 690 | D16: 3
B17: Dec | C17: 720 | D17: 5
B18: TOTAL ▶

Sheet F1-3 Anchors
A1: STAGE F1-3 ▸ ANCHORS
A2: Goal: lock references so formulas fill correctly
A3: {="SCORE "&TEXT(SUM($G$14:$G$40),"0000")&" / 0200"} -> SCORE 0000 / 0200 | C3: {=IF(SUM($G$14:$G$40)>=200,"★★★",IF(SUM($G$14:$G$40)>=200*0.8,"★★☆",IF(SUM($G$14:$G$40)>=200*0.5,"★☆☆","☆☆☆")))} -> ☆☆☆ | D3: {=REPT("█",ROUND(10*SUM($G$14:$G$40)/200,0))&REPT("░",10-ROUND(10*SUM($G$14:$G$40)/200,0))&" "&TEXT(SUM($G$14:$G$40)/200,"0%")} -> ░░░░░░░░░░ 0% | F3: {=IF(SUM($G$14:$G$40)>=200*0.5,"STAGE CLEAR! ▶ Next: F1-4 Precision","")}
A5: BRIEFING · new moves in this stage
A6: # | B6: What it does · Pro tip | C6: Keys / Syntax
A7: 1 | B7: An absolute reference never shifts when the formula is copied. Tip: Use it for one fixed cell that every row needs, like a tax rate. | C7: $A$1
A8: 2 | B8: Mixed reference: lock only the column ($A1) or only the row (A$1). Tip: Perfect for grids where one side stays fixed. | C8: $A1 / A$1
A9: 3 | B9: While editing a reference, cycle A1 → $A$1 → A$1 → $A1. Tip: Click inside the reference in the formula, then tap F4. | C9: F4
A10: 4 | B10: Fill Down: copy the top cell into the selected cells below. Tip: Select the formula cell plus the cells under it, then press Ctrl+D. | C10: Ctrl+D
A12: WARM-UP · flashback to earlier stages
A13: # | B13: Mission | C13: Your answer | D13: Result | E13: Hint? | F13: Hint | G13: XP
A14: W1 | B14: Which function adds up a range of numbers? (from F1-2 Big Six) | D14: {=IFERROR(_xlfn.LET(_xlpm.a,'F1-3 Anchors'!$C$14,IF(TRIM(_xlpm.a&"")="","",IF(OR(SUBSTITUTE(SUBSTITUTE(SUBSTITUTE(SUBSTITUTE(SUBSTITUTE(SUBSTITUTE(SUBSTITUTE(SUBSTITUTE(SUBSTITUTE(SUBSTITUTE(SUBSTITUTE(SUBSTITUTE(SUBSTITUTE(SUBSTITUTE(SUBSTITUTE(SUBSTITUTE(SUBSTITUTE(SUBSTITUTE(SUBSTITUTE(SUBSTITUTE(SUBSTITUTE(SUBSTITUTE(SUBSTITUTE(SUBSTITUTE(SUBSTITUTE(SUBSTITUTE(SUBSTITUTE(UPPER(_xlpm.a)," ",""),"CONTROL","CTRL"),"CTL","CTRL"),"ESCAPE","ESC"),"RETURN","ENTER"),"PAGEDOWN","PGDN"),"PGDOWN","PGDN"),"PAGEUP","PGUP"),"ARROWKEYS","ARROW"),"ARROWKEY","ARROW"),"ARROWS","ARROW"),"DOWNARROW","DOWN"),"UPARROW","UP"),"LEFTARROW","LEFT"),"RIGHTARROW","RIGHT"),"ARROWDOWN","DOWN"),"ARROWUP","UP"),"ARROWLEFT","LEFT"),"ARROWRIGHT","RIGHT"),"↓","DOWN"),"↑","UP"),"←","LEFT"),"→","RIGHT"),"SPACEBAR","SPACE"),"−","-"),"MINUS","-"),"PLUS","+")=Key!$E$47:$J$47),"✔ CLEAR","✘ TRY AGAIN"))),"✘ TRY AGAIN")} | F14: {=IF(E14="Show hint",Key!$B$47,"")} | G14: {=IF(LEFT(D14,1)="✔",IF(E14="Show hint",5,10),0)} -> 0
A15: W2 | B15: Which function returns the mean of a range? (from F1-2 Big Six) | D15: {=IFERROR(_xlfn.LET(_xlpm.a,'F1-3 Anchors'!$C$15,IF(TRIM(_xlpm.a&"")="","",IF(OR(SUBSTITUTE(SUBSTITUTE(SUBSTITUTE(SUBSTITUTE(SUBSTITUTE(SUBSTITUTE(SUBSTITUTE(SUBSTITUTE(SUBSTITUTE(SUBSTITUTE(SUBSTITUTE(SUBSTITUTE(SUBSTITUTE(SUBSTITUTE(SUBSTITUTE(SUBSTITUTE(SUBSTITUTE(SUBSTITUTE(SUBSTITUTE(SUBSTITUTE(SUBSTITUTE(SUBSTITUTE(SUBSTITUTE(SUBSTITUTE(SUBSTITUTE(SUBSTITUTE(SUBSTITUTE(UPPER(_xlpm.a)," ",""),"CONTROL","CTRL"),"CTL","CTRL"),"ESCAPE","ESC"),"RETURN","ENTER"),"PAGEDOWN","PGDN"),"PGDOWN","PGDN"),"PAGEUP","PGUP"),"ARROWKEYS","ARROW"),"ARROWKEY","ARROW"),"ARROWS","ARROW"),"DOWNARROW","DOWN"),"UPARROW","UP"),"LEFTARROW","LEFT"),"RIGHTARROW","RIGHT"),"ARROWDOWN","DOWN"),"ARROWUP","UP"),"ARROWLEFT","LEFT"),"ARROWRIGHT","RIGHT"),"↓","DOWN"),"↑","UP"),"←","LEFT"),"→","RIGHT"),"SPACEBAR","SPACE"),"−","-"),"MINUS","-"),"PLUS","+")=Key!$E$48:$J$48),"✔ CLEAR","✘ TRY AGAIN"))),"✘ TRY AGAIN")} | F15: {=IF(E15="Show hint",Key!$B$48,"")} | G15: {=IF(LEFT(D15,1)="✔",IF(E15="Show hint",5,10),0)} -> 0
A16: W3 | B16: Which function returns the largest number in a range? (from F1-2 Big Six) | D16: {=IFERROR(_xlfn.LET(_xlpm.a,'F1-3 Anchors'!$C$16,IF(TRIM(_xlpm.a&"")="","",IF(OR(SUBSTITUTE(SUBSTITUTE(SUBSTITUTE(SUBSTITUTE(SUBSTITUTE(SUBSTITUTE(SUBSTITUTE(SUBSTITUTE(SUBSTITUTE(SUBSTITUTE(SUBSTITUTE(SUBSTITUTE(SUBSTITUTE(SUBSTITUTE(SUBSTITUTE(SUBSTITUTE(SUBSTITUTE(SUBSTITUTE(SUBSTITUTE(SUBSTITUTE(SUBSTITUTE(SUBSTITUTE(SUBSTITUTE(SUBSTITUTE(SUBSTITUTE(SUBSTITUTE(SUBSTITUTE(UPPER(_xlpm.a)," ",""),"CONTROL","CTRL"),"CTL","CTRL"),"ESCAPE","ESC"),"RETURN","ENTER"),"PAGEDOWN","PGDN"),"PGDOWN","PGDN"),"PAGEUP","PGUP"),"ARROWKEYS","ARROW"),"ARROWKEY","ARROW"),"ARROWS","ARROW"),"DOWNARROW","DOWN"),"UPARROW","UP"),"LEFTARROW","LEFT"),"RIGHTARROW","RIGHT"),"ARROWDOWN","DOWN"),"ARROWUP","UP"),"ARROWLEFT","LEFT"),"ARROWRIGHT","RIGHT"),"↓","DOWN"),"↑","UP"),"←","LEFT"),"→","RIGHT"),"SPACEBAR","SPACE"),"−","-"),"MINUS","-"),"PLUS","+")=Key!$E$49:$J$49),"✔ CLEAR","✘ TRY AGAIN"))),"✘ TRY AGAIN")} | F16: {=IF(E16="Show hint",Key!$B$49,"")} | G16: {=IF(LEFT(D16,1)="✔",IF(E16="Show hint",5,10),0)} -> 0
A17: W4 | B17: Which function returns the smallest number in a range? (from F1-2 Big Six) | D17: {=IFERROR(_xlfn.LET(_xlpm.a,'F1-3 Anchors'!$C$17,IF(TRIM(_xlpm.a&"")="","",IF(OR(SUBSTITUTE(SUBSTITUTE(SUBSTITUTE(SUBSTITUTE(SUBSTITUTE(SUBSTITUTE(SUBSTITUTE(SUBSTITUTE(SUBSTITUTE(SUBSTITUTE(SUBSTITUTE(SUBSTITUTE(SUBSTITUTE(SUBSTITUTE(SUBSTITUTE(SUBSTITUTE(SUBSTITUTE(SUBSTITUTE(SUBSTITUTE(SUBSTITUTE(SUBSTITUTE(SUBSTITUTE(SUBSTITUTE(SUBSTITUTE(SUBSTITUTE(SUBSTITUTE(SUBSTITUTE(UPPER(_xlpm.a)," ",""),"CONTROL","CTRL"),"CTL","CTRL"),"ESCAPE","ESC"),"RETURN","ENTER"),"PAGEDOWN","PGDN"),"PGDOWN","PGDN"),"PAGEUP","PGUP"),"ARROWKEYS","ARROW"),"ARROWKEY","ARROW"),"ARROWS","ARROW"),"DOWNARROW","DOWN"),"UPARROW","UP"),"LEFTARROW","LEFT"),"RIGHTARROW","RIGHT"),"ARROWDOWN","DOWN"),"ARROWUP","UP"),"ARROWLEFT","LEFT"),"ARROWRIGHT","RIGHT"),"↓","DOWN"),"↑","UP"),"←","LEFT"),"→","RIGHT"),"SPACEBAR","SPACE"),"−","-"),"MINUS","-"),"PLUS","+")=Key!$E$50:$J$50),"✔ CLEAR","✘ TRY AGAIN"))),"✘ TRY AGAIN")} | F17: {=IF(E17="Show hint",Key!$B$50,"")} | G17: {=IF(LEFT(D17,1)="✔",IF(E17="Show hint",5,10),0)} -> 0
A18: W5 | B18: Which function counts only the cells that hold numbers? (from F1-2 Big Six) | D18: {=IFERROR(_xlfn.LET(_xlpm.a,'F1-3 Anchors'!$C$18,IF(TRIM(_xlpm.a&"")="","",IF(OR(SUBSTITUTE(SUBSTITUTE(SUBSTITUTE(SUBSTITUTE(SUBSTITUTE(SUBSTITUTE(SUBSTITUTE(SUBSTITUTE(SUBSTITUTE(SUBSTITUTE(SUBSTITUTE(SUBSTITUTE(SUBSTITUTE(SUBSTITUTE(SUBSTITUTE(SUBSTITUTE(SUBSTITUTE(SUBSTITUTE(SUBSTITUTE(SUBSTITUTE(SUBSTITUTE(SUBSTITUTE(SUBSTITUTE(SUBSTITUTE(SUBSTITUTE(SUBSTITUTE(SUBSTITUTE(UPPER(_xlpm.a)," ",""),"CONTROL","CTRL"),"CTL","CTRL"),"ESCAPE","ESC"),"RETURN","ENTER"),"PAGEDOWN","PGDN"),"PGDOWN","PGDN"),"PAGEUP","PGUP"),"ARROWKEYS","ARROW"),"ARROWKEY","ARROW"),"ARROWS","ARROW"),"DOWNARROW","DOWN"),"UPARROW","UP"),"LEFTARROW","LEFT"),"RIGHTARROW","RIGHT"),"ARROWDOWN","DOWN"),"ARROWUP","UP"),"ARROWLEFT","LEFT"),"ARROWRIGHT","RIGHT"),"↓","DOWN"),"↑","UP"),"←","LEFT"),"→","RIGHT"),"SPACEBAR","SPACE"),"−","-"),"MINUS","-"),"PLUS","+")=Key!$E$51:$J$51),"✔ CLEAR","✘ TRY AGAIN"))),"✘ TRY AGAIN")} | F18: {=IF(E18="Show hint",Key!$B$51,"")} | G18: {=IF(LEFT(D18,1)="✔",IF(E18="Show hint",5,10),0)} -> 0
A19: W6 | B19: Which function counts every non-empty cell? (from F1-2 Big Six) | D19: {=IFERROR(_xlfn.LET(_xlpm.a,'F1-3 Anchors'!$C$19,IF(TRIM(_xlpm.a&"")="","",IF(OR(SUBSTITUTE(SUBSTITUTE(SUBSTITUTE(SUBSTITUTE(SUBSTITUTE(SUBSTITUTE(SUBSTITUTE(SUBSTITUTE(SUBSTITUTE(SUBSTITUTE(SUBSTITUTE(SUBSTITUTE(SUBSTITUTE(SUBSTITUTE(SUBSTITUTE(SUBSTITUTE(SUBSTITUTE(SUBSTITUTE(SUBSTITUTE(SUBSTITUTE(SUBSTITUTE(SUBSTITUTE(SUBSTITUTE(SUBSTITUTE(SUBSTITUTE(SUBSTITUTE(SUBSTITUTE(UPPER(_xlpm.a)," ",""),"CONTROL","CTRL"),"CTL","CTRL"),"ESCAPE","ESC"),"RETURN","ENTER"),"PAGEDOWN","PGDN"),"PGDOWN","PGDN"),"PAGEUP","PGUP"),"ARROWKEYS","ARROW"),"ARROWKEY","ARROW"),"ARROWS","ARROW"),"DOWNARROW","DOWN"),"UPARROW","UP"),"LEFTARROW","LEFT"),"RIGHTARROW","RIGHT"),"ARROWDOWN","DOWN"),"ARROWUP","UP"),"ARROWLEFT","LEFT"),"ARROWRIGHT","RIGHT"),"↓","DOWN"),"↑","UP"),"←","LEFT"),"→","RIGHT"),"SPACEBAR","SPACE"),"−","-"),"MINUS","-"),"PLUS","+")=Key!$E$52:$J$52),"✔ CLEAR","✘ TRY AGAIN"))),"✘ TRY AGAIN")} | F19: {=IF(E19="Show hint",Key!$B$52,"")} | G19: {=IF(LEFT(D19,1)="✔",IF(E19="Show hint",5,10),0)} -> 0
A20: W7 | B20: Which keys insert an AutoSum formula? (from F1-2 Big Six) | D20: {=IFERROR(_xlfn.LET(_xlpm.a,'F1-3 Anchors'!$C$20,IF(TRIM(_xlpm.a&"")="","",IF(OR(SUBSTITUTE(SUBSTITUTE(SUBSTITUTE(SUBSTITUTE(SUBSTITUTE(SUBSTITUTE(SUBSTITUTE(SUBSTITUTE(SUBSTITUTE(SUBSTITUTE(SUBSTITUTE(SUBSTITUTE(SUBSTITUTE(SUBSTITUTE(SUBSTITUTE(SUBSTITUTE(SUBSTITUTE(SUBSTITUTE(SUBSTITUTE(SUBSTITUTE(SUBSTITUTE(SUBSTITUTE(SUBSTITUTE(SUBSTITUTE(SUBSTITUTE(SUBSTITUTE(SUBSTITUTE(UPPER(_xlpm.a)," ",""),"CONTROL","CTRL"),"CTL","CTRL"),"ESCAPE","ESC"),"RETURN","ENTER"),"PAGEDOWN","PGDN"),"PGDOWN","PGDN"),"PAGEUP","PGUP"),"ARROWKEYS","ARROW"),"ARROWKEY","ARROW"),"ARROWS","ARROW"),"DOWNARROW","DOWN"),"UPARROW","UP"),"LEFTARROW","LEFT"),"RIGHTARROW","RIGHT"),"ARROWDOWN","DOWN"),"ARROWUP","UP"),"ARROWLEFT","LEFT"),"ARROWRIGHT","RIGHT"),"↓","DOWN"),"↑","UP"),"←","LEFT"),"→","RIGHT"),"SPACEBAR","SPACE"),"−","-"),"MINUS","-"),"PLUS","+")=Key!$E$53:$E$53),"✔ CLEAR","✘ TRY AGAIN"))),"✘ TRY AGAIN")} | F20: {=IF(E20="Show hint",Key!$B$53,"")} | G20: {=IF(LEFT(D20,1)="✔",IF(E20="Show hint",5,10),0)} -> 0
A21: W8 | B21: Which keys select the entire row? (from S1-4 Grab) | D21: {=IFERROR(_xlfn.LET(_xlpm.a,'F1-3 Anchors'!$C$21,IF(TRIM(_xlpm.a&"")="","",IF(OR(SUBSTITUTE(SUBSTITUTE(SUBSTITUTE(SUBSTITUTE(SUBSTITUTE(SUBSTITUTE(SUBSTITUTE(SUBSTITUTE(SUBSTITUTE(SUBSTITUTE(SUBSTITUTE(SUBSTITUTE(SUBSTITUTE(SUBSTITUTE(SUBSTITUTE(SUBSTITUTE(SUBSTITUTE(SUBSTITUTE(SUBSTITUTE(SUBSTITUTE(SUBSTITUTE(SUBSTITUTE(SUBSTITUTE(SUBSTITUTE(SUBSTITUTE(SUBSTITUTE(SUBSTITUTE(UPPER(_xlpm.a)," ",""),"CONTROL","CTRL"),"CTL","CTRL"),"ESCAPE","ESC"),"RETURN","ENTER"),"PAGEDOWN","PGDN"),"PGDOWN","PGDN"),"PAGEUP","PGUP"),"ARROWKEYS","ARROW"),"ARROWKEY","ARROW"),"ARROWS","ARROW"),"DOWNARROW","DOWN"),"UPARROW","UP"),"LEFTARROW","LEFT"),"RIGHTARROW","RIGHT"),"ARROWDOWN","DOWN"),"ARROWUP","UP"),"ARROWLEFT","LEFT"),"ARROWRIGHT","RIGHT"),"↓","DOWN"),"↑","UP"),"←","LEFT"),"→","RIGHT"),"SPACEBAR","SPACE"),"−","-"),"MINUS","-"),"PLUS","+")=Key!$E$54:$E$54),"✔ CLEAR","✘ TRY AGAIN"))),"✘ TRY AGAIN")} | F21: {=IF(E21="Show hint",Key!$B$54,"")} | G21: {=IF(LEFT(D21,1)="✔",IF(E21="Show hint",5,10),0)} -> 0
A22: W9 | B22: Which keys select the entire column? (from S1-4 Grab) | D22: {=IFERROR(_xlfn.LET(_xlpm.a,'F1-3 Anchors'!$C$22,IF(TRIM(_xlpm.a&"")="","",IF(OR(SUBSTITUTE(SUBSTITUTE(SUBSTITUTE(SUBSTITUTE(SUBSTITUTE(SUBSTITUTE(SUBSTITUTE(SUBSTITUTE(SUBSTITUTE(SUBSTITUTE(SUBSTITUTE(SUBSTITUTE(SUBSTITUTE(SUBSTITUTE(SUBSTITUTE(SUBSTITUTE(SUBSTITUTE(SUBSTITUTE(SUBSTITUTE(SUBSTITUTE(SUBSTITUTE(SUBSTITUTE(SUBSTITUTE(SUBSTITUTE(SUBSTITUTE(SUBSTITUTE(SUBSTITUTE(UPPER(_xlpm.a)," ",""),"CONTROL","CTRL"),"CTL","CTRL"),"ESCAPE","ESC"),"RETURN","ENTER"),"PAGEDOWN","PGDN"),"PGDOWN","PGDN"),"PAGEUP","PGUP"),"ARROWKEYS","ARROW"),"ARROWKEY","ARROW"),"ARROWS","ARROW"),"DOWNARROW","DOWN"),"UPARROW","UP"),"LEFTARROW","LEFT"),"RIGHTARROW","RIGHT"),"ARROWDOWN","DOWN"),"ARROWUP","UP"),"ARROWLEFT","LEFT"),"ARROWRIGHT","RIGHT"),"↓","DOWN"),"↑","UP"),"←","LEFT"),"→","RIGHT"),"SPACEBAR","SPACE"),"−","-"),"MINUS","-"),"PLUS","+")=Key!$E$55:$E$55),"✔ CLEAR","✘ TRY AGAIN"))),"✘ TRY AGAIN")} | F22: {=IF(E22="Show hint",Key!$B$55,"")} | G22: {=IF(LEFT(D22,1)="✔",IF(E22="Show hint",5,10),0)} -> 0
A23: W10 | B23: Which keys select the current data block (and the whole sheet if you keep pressing)? (from S1-4 Grab) | D23: {=IFERROR(_xlfn.LET(_xlpm.a,'F1-3 Anchors'!$C$23,IF(TRIM(_xlpm.a&"")="","",IF(OR(SUBSTITUTE(SUBSTITUTE(SUBSTITUTE(SUBSTITUTE(SUBSTITUTE(SUBSTITUTE(SUBSTITUTE(SUBSTITUTE(SUBSTITUTE(SUBSTITUTE(SUBSTITUTE(SUBSTITUTE(SUBSTITUTE(SUBSTITUTE(SUBSTITUTE(SUBSTITUTE(SUBSTITUTE(SUBSTITUTE(SUBSTITUTE(SUBSTITUTE(SUBSTITUTE(SUBSTITUTE(SUBSTITUTE(SUBSTITUTE(SUBSTITUTE(SUBSTITUTE(SUBSTITUTE(UPPER(_xlpm.a)," ",""),"CONTROL","CTRL"),"CTL","CTRL"),"ESCAPE","ESC"),"RETURN","ENTER"),"PAGEDOWN","PGDN"),"PGDOWN","PGDN"),"PAGEUP","PGUP"),"ARROWKEYS","ARROW"),"ARROWKEY","ARROW"),"ARROWS","ARROW"),"DOWNARROW","DOWN"),"UPARROW","UP"),"LEFTARROW","LEFT"),"RIGHTARROW","RIGHT"),"ARROWDOWN","DOWN"),"ARROWUP","UP"),"ARROWLEFT","LEFT"),"ARROWRIGHT","RIGHT"),"↓","DOWN"),"↑","UP"),"←","LEFT"),"→","RIGHT"),"SPACEBAR","SPACE"),"−","-"),"MINUS","-"),"PLUS","+")=Key!$E$56:$G$56),"✔ CLEAR","✘ TRY AGAIN"))),"✘ TRY AGAIN")} | F23: {=IF(E23="Show hint",Key!$B$56,"")} | G23: {=IF(LEFT(D23,1)="✔",IF(E23="Show hint",5,10),0)} -> 0
A25: TRAINING · recognize the move (pick from the list)
A26: # | B26: Mission | C26: Your answer | D26: Result | E26: Hint? | F26: Hint | G26: XP
A27: T1 | B27: Which move is this? An absolute reference never shifts when the formula is copied. | D27: {=IFERROR(IF('F1-3 Anchors'!$C$27&""="","",IF('F1-3 Anchors'!$C$27&""=Key!$C$57&"","✔ CLEAR","✘ TRY AGAIN")),"✘ TRY AGAIN")} | F27: {=IF(E27="Show hint",Key!$B$57,"")} | G27: {=IF(LEFT(D27,1)="✔",IF(E27="Show hint",5,10),0)} -> 0
A28: T2 | B28: Which move is this? Mixed reference: lock only the column ($A1) or only the row (A$1). | D28: {=IFERROR(IF('F1-3 Anchors'!$C$28&""="","",IF('F1-3 Anchors'!$C$28&""=Key!$C$58&"","✔ CLEAR","✘ TRY AGAIN")),"✘ TRY AGAIN")} | F28: {=IF(E28="Show hint",Key!$B$58,"")} | G28: {=IF(LEFT(D28,1)="✔",IF(E28="Show hint",5,10),0)} -> 0
A29: T3 | B29: Which key adds or cycles the $ signs on a reference you are editing? | D29: {=IFERROR(IF('F1-3 Anchors'!$C$29&""="","",IF('F1-3 Anchors'!$C$29&""=Key!$C$59&"","✔ CLEAR","✘ TRY AGAIN")),"✘ TRY AGAIN")} | F29: {=IF(E29="Show hint",Key!$B$59,"")} | G29: {=IF(LEFT(D29,1)="✔",IF(E29="Show hint",5,10),0)} -> 0
A30: T4 | B30: Which keys copy the top cell down into the selected cells? | D30: {=IFERROR(IF('F1-3 Anchors'!$C$30&""="","",IF('F1-3 Anchors'!$C$30&""=Key!$C$60&"","✔ CLEAR","✘ TRY AGAIN")),"✘ TRY AGAIN")} | F30: {=IF(E30="Show hint",Key!$B$60,"")} | G30: {=IF(LEFT(D30,1)="✔",IF(E30="Show hint",5,10),0)} -> 0
A32: CHALLENGES · recall it, then do it
B33: ▶ Open F1-3 Arena (or press Ctrl+PgDn)
A34: # | B34: Mission | C34: Your answer | D34: Result | E34: Hint? | F34: Hint | G34: XP
A35: C1 | B35: Type the absolute version of the reference E6. | D35: {=IFERROR(_xlfn.LET(_xlpm.a,'F1-3 Anchors'!$C$35,IF(TRIM(_xlpm.a&"")="","",IF(OR(SUBSTITUTE(SUBSTITUTE(SUBSTITUTE(SUBSTITUTE(SUBSTITUTE(SUBSTITUTE(SUBSTITUTE(SUBSTITUTE(SUBSTITUTE(SUBSTITUTE(SUBSTITUTE(SUBSTITUTE(SUBSTITUTE(SUBSTITUTE(SUBSTITUTE(SUBSTITUTE(SUBSTITUTE(SUBSTITUTE(SUBSTITUTE(SUBSTITUTE(SUBSTITUTE(SUBSTITUTE(SUBSTITUTE(SUBSTITUTE(SUBSTITUTE(SUBSTITUTE(SUBSTITUTE(UPPER(_xlpm.a)," ",""),"CONTROL","CTRL"),"CTL","CTRL"),"ESCAPE","ESC"),"RETURN","ENTER"),"PAGEDOWN","PGDN"),"PGDOWN","PGDN"),"PAGEUP","PGUP"),"ARROWKEYS","ARROW"),"ARROWKEY","ARROW"),"ARROWS","ARROW"),"DOWNARROW","DOWN"),"UPARROW","UP"),"LEFTARROW","LEFT"),"RIGHTARROW","RIGHT"),"ARROWDOWN","DOWN"),"ARROWUP","UP"),"ARROWLEFT","LEFT"),"ARROWRIGHT","RIGHT"),"↓","DOWN"),"↑","UP"),"←","LEFT"),"→","RIGHT"),"SPACEBAR","SPACE"),"−","-"),"MINUS","-"),"PLUS","+")=Key!$E$61:$E$61),"✔ CLEAR","✘ TRY AGAIN"))),"✘ TRY AGAIN")} | F35: {=IF(E35="Show hint",Key!$B$61,"")} | G35: {=IF(LEFT(D35,1)="✔",IF(E35="Show hint",5,10),0)} -> 0
A36: C2 | B36: Type a reference to C16 that locks only the row. | D36: {=IFERROR(_xlfn.LET(_xlpm.a,'F1-3 Anchors'!$C$36,IF(TRIM(_xlpm.a&"")="","",IF(OR(SUBSTITUTE(SUBSTITUTE(SUBSTITUTE(SUBSTITUTE(SUBSTITUTE(SUBSTITUTE(SUBSTITUTE(SUBSTITUTE(SUBSTITUTE(SUBSTITUTE(SUBSTITUTE(SUBSTITUTE(SUBSTITUTE(SUBSTITUTE(SUBSTITUTE(SUBSTITUTE(SUBSTITUTE(SUBSTITUTE(SUBSTITUTE(SUBSTITUTE(SUBSTITUTE(SUBSTITUTE(SUBSTITUTE(SUBSTITUTE(SUBSTITUTE(SUBSTITUTE(SUBSTITUTE(UPPER(_xlpm.a)," ",""),"CONTROL","CTRL"),"CTL","CTRL"),"ESCAPE","ESC"),"RETURN","ENTER"),"PAGEDOWN","PGDN"),"PGDOWN","PGDN"),"PAGEUP","PGUP"),"ARROWKEYS","ARROW"),"ARROWKEY","ARROW"),"ARROWS","ARROW"),"DOWNARROW","DOWN"),"UPARROW","UP"),"LEFTARROW","LEFT"),"RIGHTARROW","RIGHT"),"ARROWDOWN","DOWN"),"ARROWUP","UP"),"ARROWLEFT","LEFT"),"ARROWRIGHT","RIGHT"),"↓","DOWN"),"↑","UP"),"←","LEFT"),"→","RIGHT"),"SPACEBAR","SPACE"),"−","-"),"MINUS","-"),"PLUS","+")=Key!$E$62:$E$62),"✔ CLEAR","✘ TRY AGAIN"))),"✘ TRY AGAIN")} | F36: {=IF(E36="Show hint",Key!$B$62,"")} | G36: {=IF(LEFT(D36,1)="✔",IF(E36="Show hint",5,10),0)} -> 0
A37: C3 | B37: Which key adds or cycles the $ signs on a reference you are editing? | D37: {=IFERROR(_xlfn.LET(_xlpm.a,'F1-3 Anchors'!$C$37,IF(TRIM(_xlpm.a&"")="","",IF(OR(SUBSTITUTE(SUBSTITUTE(SUBSTITUTE(SUBSTITUTE(SUBSTITUTE(SUBSTITUTE(SUBSTITUTE(SUBSTITUTE(SUBSTITUTE(SUBSTITUTE(SUBSTITUTE(SUBSTITUTE(SUBSTITUTE(SUBSTITUTE(SUBSTITUTE(SUBSTITUTE(SUBSTITUTE(SUBSTITUTE(SUBSTITUTE(SUBSTITUTE(SUBSTITUTE(SUBSTITUTE(SUBSTITUTE(SUBSTITUTE(SUBSTITUTE(SUBSTITUTE(SUBSTITUTE(UPPER(_xlpm.a)," ",""),"CONTROL","CTRL"),"CTL","CTRL"),"ESCAPE","ESC"),"RETURN","ENTER"),"PAGEDOWN","PGDN"),"PGDOWN","PGDN"),"PAGEUP","PGUP"),"ARROWKEYS","ARROW"),"ARROWKEY","ARROW"),"ARROWS","ARROW"),"DOWNARROW","DOWN"),"UPARROW","UP"),"LEFTARROW","LEFT"),"RIGHTARROW","RIGHT"),"ARROWDOWN","DOWN"),"ARROWUP","UP"),"ARROWLEFT","LEFT"),"ARROWRIGHT","RIGHT"),"↓","DOWN"),"↑","UP"),"←","LEFT"),"→","RIGHT"),"SPACEBAR","SPACE"),"−","-"),"MINUS","-"),"PLUS","+")=Key!$E$63:$E$63),"✔ CLEAR","✘ TRY AGAIN"))),"✘ TRY AGAIN")} | F37: {=IF(E37="Show hint",Key!$B$63,"")} | G37: {=IF(LEFT(D37,1)="✔",IF(E37="Show hint",5,10),0)} -> 0
A38: C4 | B38: Which keys copy the top cell down into the selected cells? | D38: {=IFERROR(_xlfn.LET(_xlpm.a,'F1-3 Anchors'!$C$38,IF(TRIM(_xlpm.a&"")="","",IF(OR(SUBSTITUTE(SUBSTITUTE(SUBSTITUTE(SUBSTITUTE(SUBSTITUTE(SUBSTITUTE(SUBSTITUTE(SUBSTITUTE(SUBSTITUTE(SUBSTITUTE(SUBSTITUTE(SUBSTITUTE(SUBSTITUTE(SUBSTITUTE(SUBSTITUTE(SUBSTITUTE(SUBSTITUTE(SUBSTITUTE(SUBSTITUTE(SUBSTITUTE(SUBSTITUTE(SUBSTITUTE(SUBSTITUTE(SUBSTITUTE(SUBSTITUTE(SUBSTITUTE(SUBSTITUTE(UPPER(_xlpm.a)," ",""),"CONTROL","CTRL"),"CTL","CTRL"),"ESCAPE","ESC"),"RETURN","ENTER"),"PAGEDOWN","PGDN"),"PGDOWN","PGDN"),"PAGEUP","PGUP"),"ARROWKEYS","ARROW"),"ARROWKEY","ARROW"),"ARROWS","ARROW"),"DOWNARROW","DOWN"),"UPARROW","UP"),"LEFTARROW","LEFT"),"RIGHTARROW","RIGHT"),"ARROWDOWN","DOWN"),"ARROWUP","UP"),"ARROWLEFT","LEFT"),"ARROWRIGHT","RIGHT"),"↓","DOWN"),"↑","UP"),"←","LEFT"),"→","RIGHT"),"SPACEBAR","SPACE"),"−","-"),"MINUS","-"),"PLUS","+")=Key!$E$64:$E$64),"✔ CLEAR","✘ TRY AGAIN"))),"✘ TRY AGAIN")} | F38: {=IF(E38="Show hint",Key!$B$64,"")} | G38: {=IF(LEFT(D38,1)="✔",IF(E38="Show hint",5,10),0)} -> 0
A39: C5 | B39: In the arena, select C6 and type =B6*$E$6 (click E6, then press F4 to add the $ signs). Then select C6:C13 and press Ctrl+D to fill it down. | C39: ▶ ARENA C5 (cell C6) | D39: {=IF(COUNTA('F1-3 Arena'!$C$6,'F1-3 Arena'!$C$7,'F1-3 Arena'!$C$8,'F1-3 Arena'!$C$9,'F1-3 Arena'!$C$10,'F1-3 Arena'!$C$11,'F1-3 Arena'!$C$12,'F1-3 Arena'!$C$13)=0,"",IF(OR(NOT(_xlfn.ISFORMULA('F1-3 Arena'!$C$6)),NOT(_xlfn.ISFORMULA('F1-3 Arena'!$C$7)),NOT(_xlfn.ISFORMULA('F1-3 Arena'!$C$8)),NOT(_xlfn.ISFORMULA('F1-3 Arena'!$C$9)),NOT(_xlfn.ISFORMULA('F1-3 Arena'!$C$10)),NOT(_xlfn.ISFORMULA('F1-3 Arena'!$C$11)),NOT(_xlfn.ISFORMULA('F1-3 Arena'!$C$12)),NOT(_xlfn.ISFORMULA('F1-3 Arena'!$C$13))),"✘ Some cells aren't formulas yet",IF(OR(ISERROR('F1-3 Arena'!$C$6),ISERROR('F1-3 Arena'!$C$7),ISERROR('F1-3 Arena'!$C$8),ISERROR('F1-3 Arena'!$C$9),ISERROR('F1-3 Arena'!$C$10),ISERROR('F1-3 Arena'!$C$11),ISERROR('F1-3 Arena'!$C$12),ISERROR('F1-3 Arena'!$C$13)),"✘ Some cells show an error",IF(NOT(AND(IFERROR(AND(ISNUMBER('F1-3 Arena'!$C$6),ABS('F1-3 Arena'!$C$6-Key!$E$65)<=1E-9*MAX(1,ABS(Key!$E$65))),FALSE),IFERROR(AND(ISNUMBER('F1-3 Arena'!$C$7),ABS('F1-3 Arena'!$C$7-Key!$F$65)<=1E-9*MAX(1,ABS(Key!$F$65))),FALSE),IFERROR(AND(ISNUMBER('F1-3 Arena'!$C$8),ABS('F1-3 Arena'!$C$8-Key!$G$65)<=1E-9*MAX(1,ABS(Key!$G$65))),FALSE),IFERROR(AND(ISNUMBER('F1-3 Arena'!$C$9),ABS('F1-3 Arena'!$C$9-Key!$H$65)<=1E-9*MAX(1,ABS(Key!$H$65))),FALSE),IFERROR(AND(ISNUMBER('F1-3 Arena'!$C$10),ABS('F1-3 Arena'!$C$10-Key!$I$65)<=1E-9*MAX(1,ABS(Key!$I$65))),FALSE),IFERROR(AND(ISNUMBER('F1-3 Arena'!$C$11),ABS('F1-3 Arena'!$C$11-Key!$J$65)<=1E-9*MAX(1,ABS(Key!$J$65))),FALSE),IFERROR(AND(ISNUMBER('F1-3 Arena'!$C$12),ABS('F1-3 Arena'!$C$12-Key!$K$65)<=1E-9*MAX(1,ABS(Key!$K$65))),FALSE),IFERROR(AND(ISNUMBER('F1-3 Arena'!$C$13),ABS('F1-3 Arena'!$C$13-Key!$L$65)<=1E-9*MAX(1,ABS(Key!$L$65))),FALSE))),"✘ TRY AGAIN",IF(ISNUMBER(FIND("$",_xlfn.FORMULATEXT('F1-3 Arena'!$C$6))),"✔ CLEAR","✘ CLOSE · add $ so it fills correctly (F4)")))))} | F39: {=IF(E39="Show hint",Key!$B$65,"")} | G39: {=IF(LEFT(D39,1)="✔",IF(E39="Show hint",5,10),0)} -> 0
A40: C6 | B40: In C17 type =$B17*(1-C$16): $B locks the price column, $16 locks the discount row. Then select C17:C21 and press Ctrl+D. | C40: ▶ ARENA C6 (cell C17) | D40: {=IF(COUNTA('F1-3 Arena'!$C$17,'F1-3 Arena'!$C$18,'F1-3 Arena'!$C$19,'F1-3 Arena'!$C$20,'F1-3 Arena'!$C$21)=0,"",IF(OR(NOT(_xlfn.ISFORMULA('F1-3 Arena'!$C$17)),NOT(_xlfn.ISFORMULA('F1-3 Arena'!$C$18)),NOT(_xlfn.ISFORMULA('F1-3 Arena'!$C$19)),NOT(_xlfn.ISFORMULA('F1-3 Arena'!$C$20)),NOT(_xlfn.ISFORMULA('F1-3 Arena'!$C$21))),"✘ Some cells aren't formulas yet",IF(OR(ISERROR('F1-3 Arena'!$C$17),ISERROR('F1-3 Arena'!$C$18),ISERROR('F1-3 Arena'!$C$19),ISERROR('F1-3 Arena'!$C$20),ISERROR('F1-3 Arena'!$C$21)),"✘ Some cells show an error",IF(NOT(AND(IFERROR(AND(ISNUMBER('F1-3 Arena'!$C$17),ABS('F1-3 Arena'!$C$17-Key!$E$66)<=1E-9*MAX(1,ABS(Key!$E$66))),FALSE),IFERROR(AND(ISNUMBER('F1-3 Arena'!$C$18),ABS('F1-3 Arena'!$C$18-Key!$F$66)<=1E-9*MAX(1,ABS(Key!$F$66))),FALSE),IFERROR(AND(ISNUMBER('F1-3 Arena'!$C$19),ABS('F1-3 Arena'!$C$19-Key!$G$66)<=1E-9*MAX(1,ABS(Key!$G$66))),FALSE),IFERROR(AND(ISNUMBER('F1-3 Arena'!$C$20),ABS('F1-3 Arena'!$C$20-Key!$H$66)<=1E-9*MAX(1,ABS(Key!$H$66))),FALSE),IFERROR(AND(ISNUMBER('F1-3 Arena'!$C$21),ABS('F1-3 Arena'!$C$21-Key!$I$66)<=1E-9*MAX(1,ABS(Key!$I$66))),FALSE))),"✘ TRY AGAIN",IF(ISNUMBER(FIND("$",_xlfn.FORMULATEXT('F1-3 Arena'!$C$17))),"✔ CLEAR","✘ CLOSE · add $ so it fills correctly (F4)")))))} | F40: {=IF(E40="Show hint",Key!$B$66,"")} | G40: {=IF(LEFT(D40,1)="✔",IF(E40="Show hint",5,10),0)} -> 0

Sheet F1-3 Arena
A1: ARENA ▸ F1-3 ANCHORS
A2: Practice area · everything here is editable. Missions and their checks are on the stage sheet.
A3: PASS CODE | B3: ANCHOR | D3: ◀ Back to F1-3 Anchors
B5: Price | C5: Tax | E5: Tax rate
B6: 20 | E6: 0.08
B7: 35
B8: 12.5
B9: 80
B10: 46
B11: 9.99
B12: 150
B13: 64
B16: Price ↓ · Discount → | C16: 0.1 | D16: 0.2 | E16: 0.3
B17: 40
B18: 25
B19: 60
B20: 15
B21: 90

Sheet F1-4 Precision
A1: STAGE F1-4 ▸ PRECISION
A2: Goal: round numbers exactly the way you want
A3: {="SCORE "&TEXT(SUM($G$13:$G$33),"0000")&" / 0140"} -> SCORE 0000 / 0140 | C3: {=IF(SUM($G$13:$G$33)>=140,"★★★",IF(SUM($G$13:$G$33)>=140*0.8,"★★☆",IF(SUM($G$13:$G$33)>=140*0.5,"★☆☆","☆☆☆")))} -> ☆☆☆ | D3: {=REPT("█",ROUND(10*SUM($G$13:$G$33)/140,0))&REPT("░",10-ROUND(10*SUM($G$13:$G$33)/140,0))&" "&TEXT(SUM($G$13:$G$33)/140,"0%")} -> ░░░░░░░░░░ 0% | F3: {=IF(SUM($G$13:$G$33)>=140*0.5,"STAGE CLEAR! ▶ Next: F1-5 X-Ray","")}
A5: BRIEFING · new moves in this stage
A6: # | B6: What it does · Pro tip | C6: Keys / Syntax
A7: 1 | B7: Round to a number of digits: =ROUND(3.14159,2) gives 3.14. Tip: Negative digits round to tens or hundreds: =ROUND(1234,-2) is 1200. | C7: ROUND
A8: 2 | B8: Always round away from zero: =ROUNDUP(2.1,0) gives 3. Tip: Good for 'how many boxes do I need?' | C8: ROUNDUP
A9: 3 | B9: Always round toward zero: chop off the extra digits. Tip: =ROUNDDOWN(7.86,1) gives 7.8. | C9: ROUNDDOWN
A11: WARM-UP · flashback to earlier stages
A12: # | B12: Mission | C12: Your answer | D12: Result | E12: Hint? | F12: Hint | G12: XP
A13: W1 | B13: Type the absolute version of the reference E6. (from F1-3 Anchors) | D13: {=IFERROR(_xlfn.LET(_xlpm.a,'F1-4 Precision'!$C$13,IF(TRIM(_xlpm.a&"")="","",IF(OR(SUBSTITUTE(SUBSTITUTE(SUBSTITUTE(SUBSTITUTE(SUBSTITUTE(SUBSTITUTE(SUBSTITUTE(SUBSTITUTE(SUBSTITUTE(SUBSTITUTE(SUBSTITUTE(SUBSTITUTE(SUBSTITUTE(SUBSTITUTE(SUBSTITUTE(SUBSTITUTE(SUBSTITUTE(SUBSTITUTE(SUBSTITUTE(SUBSTITUTE(SUBSTITUTE(SUBSTITUTE(SUBSTITUTE(SUBSTITUTE(SUBSTITUTE(SUBSTITUTE(SUBSTITUTE(UPPER(_xlpm.a)," ",""),"CONTROL","CTRL"),"CTL","CTRL"),"ESCAPE","ESC"),"RETURN","ENTER"),"PAGEDOWN","PGDN"),"PGDOWN","PGDN"),"PAGEUP","PGUP"),"ARROWKEYS","ARROW"),"ARROWKEY","ARROW"),"ARROWS","ARROW"),"DOWNARROW","DOWN"),"UPARROW","UP"),"LEFTARROW","LEFT"),"RIGHTARROW","RIGHT"),"ARROWDOWN","DOWN"),"ARROWUP","UP"),"ARROWLEFT","LEFT"),"ARROWRIGHT","RIGHT"),"↓","DOWN"),"↑","UP"),"←","LEFT"),"→","RIGHT"),"SPACEBAR","SPACE"),"−","-"),"MINUS","-"),"PLUS","+")=Key!$E$67:$E$67),"✔ CLEAR","✘ TRY AGAIN"))),"✘ TRY AGAIN")} | F13: {=IF(E13="Show hint",Key!$B$67,"")} | G13: {=IF(LEFT(D13,1)="✔",IF(E13="Show hint",5,10),0)} -> 0
A14: W2 | B14: Type a reference to C16 that locks only the row. (from F1-3 Anchors) | D14: {=IFERROR(_xlfn.LET(_xlpm.a,'F1-4 Precision'!$C$14,IF(TRIM(_xlpm.a&"")="","",IF(OR(SUBSTITUTE(SUBSTITUTE(SUBSTITUTE(SUBSTITUTE(SUBSTITUTE(SUBSTITUTE(SUBSTITUTE(SUBSTITUTE(SUBSTITUTE(SUBSTITUTE(SUBSTITUTE(SUBSTITUTE(SUBSTITUTE(SUBSTITUTE(SUBSTITUTE(SUBSTITUTE(SUBSTITUTE(SUBSTITUTE(SUBSTITUTE(SUBSTITUTE(SUBSTITUTE(SUBSTITUTE(SUBSTITUTE(SUBSTITUTE(SUBSTITUTE(SUBSTITUTE(SUBSTITUTE(UPPER(_xlpm.a)," ",""),"CONTROL","CTRL"),"CTL","CTRL"),"ESCAPE","ESC"),"RETURN","ENTER"),"PAGEDOWN","PGDN"),"PGDOWN","PGDN"),"PAGEUP","PGUP"),"ARROWKEYS","ARROW"),"ARROWKEY","ARROW"),"ARROWS","ARROW"),"DOWNARROW","DOWN"),"UPARROW","UP"),"LEFTARROW","LEFT"),"RIGHTARROW","RIGHT"),"ARROWDOWN","DOWN"),"ARROWUP","UP"),"ARROWLEFT","LEFT"),"ARROWRIGHT","RIGHT"),"↓","DOWN"),"↑","UP"),"←","LEFT"),"→","RIGHT"),"SPACEBAR","SPACE"),"−","-"),"MINUS","-"),"PLUS","+")=Key!$E$68:$E$68),"✔ CLEAR","✘ TRY AGAIN"))),"✘ TRY AGAIN")} | F14: {=IF(E14="Show hint",Key!$B$68,"")} | G14: {=IF(LEFT(D14,1)="✔",IF(E14="Show hint",5,10),0)} -> 0
A15: W3 | B15: Which key adds or cycles the $ signs on a reference you are editing? (from F1-3 Anchors) | D15: {=IFERROR(_xlfn.LET(_xlpm.a,'F1-4 Precision'!$C$15,IF(TRIM(_xlpm.a&"")="","",IF(OR(SUBSTITUTE(SUBSTITUTE(SUBSTITUTE(SUBSTITUTE(SUBSTITUTE(SUBSTITUTE(SUBSTITUTE(SUBSTITUTE(SUBSTITUTE(SUBSTITUTE(SUBSTITUTE(SUBSTITUTE(SUBSTITUTE(SUBSTITUTE(SUBSTITUTE(SUBSTITUTE(SUBSTITUTE(SUBSTITUTE(SUBSTITUTE(SUBSTITUTE(SUBSTITUTE(SUBSTITUTE(SUBSTITUTE(SUBSTITUTE(SUBSTITUTE(SUBSTITUTE(SUBSTITUTE(UPPER(_xlpm.a)," ",""),"CONTROL","CTRL"),"CTL","CTRL"),"ESCAPE","ESC"),"RETURN","ENTER"),"PAGEDOWN","PGDN"),"PGDOWN","PGDN"),"PAGEUP","PGUP"),"ARROWKEYS","ARROW"),"ARROWKEY","ARROW"),"ARROWS","ARROW"),"DOWNARROW","DOWN"),"UPARROW","UP"),"LEFTARROW","LEFT"),"RIGHTARROW","RIGHT"),"ARROWDOWN","DOWN"),"ARROWUP","UP"),"ARROWLEFT","LEFT"),"ARROWRIGHT","RIGHT"),"↓","DOWN"),"↑","UP"),"←","LEFT"),"→","RIGHT"),"SPACEBAR","SPACE"),"−","-"),"MINUS","-"),"PLUS","+")=Key!$E$69:$E$69),"✔ CLEAR","✘ TRY AGAIN"))),"✘ TRY AGAIN")} | F15: {=IF(E15="Show hint",Key!$B$69,"")} | G15: {=IF(LEFT(D15,1)="✔",IF(E15="Show hint",5,10),0)} -> 0
A16: W4 | B16: Which keys copy the top cell down into the selected cells? (from F1-3 Anchors) | D16: {=IFERROR(_xlfn.LET(_xlpm.a,'F1-4 Precision'!$C$16,IF(TRIM(_xlpm.a&"")="","",IF(OR(SUBSTITUTE(SUBSTITUTE(SUBSTITUTE(SUBSTITUTE(SUBSTITUTE(SUBSTITUTE(SUBSTITUTE(SUBSTITUTE(SUBSTITUTE(SUBSTITUTE(SUBSTITUTE(SUBSTITUTE(SUBSTITUTE(SUBSTITUTE(SUBSTITUTE(SUBSTITUTE(SUBSTITUTE(SUBSTITUTE(SUBSTITUTE(SUBSTITUTE(SUBSTITUTE(SUBSTITUTE(SUBSTITUTE(SUBSTITUTE(SUBSTITUTE(SUBSTITUTE(SUBSTITUTE(UPPER(_xlpm.a)," ",""),"CONTROL","CTRL"),"CTL","CTRL"),"ESCAPE","ESC"),"RETURN","ENTER"),"PAGEDOWN","PGDN"),"PGDOWN","PGDN"),"PAGEUP","PGUP"),"ARROWKEYS","ARROW"),"ARROWKEY","ARROW"),"ARROWS","ARROW"),"DOWNARROW","DOWN"),"UPARROW","UP"),"LEFTARROW","LEFT"),"RIGHTARROW","RIGHT"),"ARROWDOWN","DOWN"),"ARROWUP","UP"),"ARROWLEFT","LEFT"),"ARROWRIGHT","RIGHT"),"↓","DOWN"),"↑","UP"),"←","LEFT"),"→","RIGHT"),"SPACEBAR","SPACE"),"−","-"),"MINUS","-"),"PLUS","+")=Key!$E$70:$E$70),"✔ CLEAR","✘ TRY AGAIN"))),"✘ TRY AGAIN")} | F16: {=IF(E16="Show hint",Key!$B$70,"")} | G16: {=IF(LEFT(D16,1)="✔",IF(E16="Show hint",5,10),0)} -> 0
A18: TRAINING · recognize the move (pick from the list)
A19: # | B19: Mission | C19: Your answer | D19: Result | E19: Hint? | F19: Hint | G19: XP
A20: T1 | B20: Which function rounds a number to a chosen number of digits? | D20: {=IFERROR(IF('F1-4 Precision'!$C$20&""="","",IF('F1-4 Precision'!$C$20&""=Key!$C$71&"","✔ CLEAR","✘ TRY AGAIN")),"✘ TRY AGAIN")} | F20: {=IF(E20="Show hint",Key!$B$71,"")} | G20: {=IF(LEFT(D20,1)="✔",IF(E20="Show hint",5,10),0)} -> 0
A21: T2 | B21: Which function always rounds up, away from zero? | D21: {=IFERROR(IF('F1-4 Precision'!$C$21&""="","",IF('F1-4 Precision'!$C$21&""=Key!$C$72&"","✔ CLEAR","✘ TRY AGAIN")),"✘ TRY AGAIN")} | F21: {=IF(E21="Show hint",Key!$B$72,"")} | G21: {=IF(LEFT(D21,1)="✔",IF(E21="Show hint",5,10),0)} -> 0
A22: T3 | B22: Which function always rounds down, toward zero? | D22: {=IFERROR(IF('F1-4 Precision'!$C$22&""="","",IF('F1-4 Precision'!$C$22&""=Key!$C$73&"","✔ CLEAR","✘ TRY AGAIN")),"✘ TRY AGAIN")} | F22: {=IF(E22="Show hint",Key!$B$73,"")} | G22: {=IF(LEFT(D22,1)="✔",IF(E22="Show hint",5,10),0)} -> 0
A24: CHALLENGES · recall it, then do it
B25: ▶ Open F1-4 Arena (or press Ctrl+PgDn)
A26: # | B26: Mission | C26: Your answer | D26: Result | E26: Hint? | F26: Hint | G26: XP
A27: C1 | B27: Which function rounds a number to a chosen number of digits? | D27: {=IFERROR(_xlfn.LET(_xlpm.a,'F1-4 Precision'!$C$27,IF(TRIM(_xlpm.a&"")="","",IF(OR(SUBSTITUTE(SUBSTITUTE(SUBSTITUTE(SUBSTITUTE(SUBSTITUTE(SUBSTITUTE(SUBSTITUTE(SUBSTITUTE(SUBSTITUTE(SUBSTITUTE(SUBSTITUTE(SUBSTITUTE(SUBSTITUTE(SUBSTITUTE(SUBSTITUTE(SUBSTITUTE(SUBSTITUTE(SUBSTITUTE(SUBSTITUTE(SUBSTITUTE(SUBSTITUTE(SUBSTITUTE(SUBSTITUTE(SUBSTITUTE(SUBSTITUTE(SUBSTITUTE(SUBSTITUTE(UPPER(_xlpm.a)," ",""),"CONTROL","CTRL"),"CTL","CTRL"),"ESCAPE","ESC"),"RETURN","ENTER"),"PAGEDOWN","PGDN"),"PGDOWN","PGDN"),"PAGEUP","PGUP"),"ARROWKEYS","ARROW"),"ARROWKEY","ARROW"),"ARROWS","ARROW"),"DOWNARROW","DOWN"),"UPARROW","UP"),"LEFTARROW","LEFT"),"RIGHTARROW","RIGHT"),"ARROWDOWN","DOWN"),"ARROWUP","UP"),"ARROWLEFT","LEFT"),"ARROWRIGHT","RIGHT"),"↓","DOWN"),"↑","UP"),"←","LEFT"),"→","RIGHT"),"SPACEBAR","SPACE"),"−","-"),"MINUS","-"),"PLUS","+")=Key!$E$74:$J$74),"✔ CLEAR","✘ TRY AGAIN"))),"✘ TRY AGAIN")} | F27: {=IF(E27="Show hint",Key!$B$74,"")} | G27: {=IF(LEFT(D27,1)="✔",IF(E27="Show hint",5,10),0)} -> 0
A28: C2 | B28: Which function always rounds up, away from zero? | D28: {=IFERROR(_xlfn.LET(_xlpm.a,'F1-4 Precision'!$C$28,IF(TRIM(_xlpm.a&"")="","",IF(OR(SUBSTITUTE(SUBSTITUTE(SUBSTITUTE(SUBSTITUTE(SUBSTITUTE(SUBSTITUTE(SUBSTITUTE(SUBSTITUTE(SUBSTITUTE(SUBSTITUTE(SUBSTITUTE(SUBSTITUTE(SUBSTITUTE(SUBSTITUTE(SUBSTITUTE(SUBSTITUTE(SUBSTITUTE(SUBSTITUTE(SUBSTITUTE(SUBSTITUTE(SUBSTITUTE(SUBSTITUTE(SUBSTITUTE(SUBSTITUTE(SUBSTITUTE(SUBSTITUTE(SUBSTITUTE(UPPER(_xlpm.a)," ",""),"CONTROL","CTRL"),"CTL","CTRL"),"ESCAPE","ESC"),"RETURN","ENTER"),"PAGEDOWN","PGDN"),"PGDOWN","PGDN"),"PAGEUP","PGUP"),"ARROWKEYS","ARROW"),"ARROWKEY","ARROW"),"ARROWS","ARROW"),"DOWNARROW","DOWN"),"UPARROW","UP"),"LEFTARROW","LEFT"),"RIGHTARROW","RIGHT"),"ARROWDOWN","DOWN"),"ARROWUP","UP"),"ARROWLEFT","LEFT"),"ARROWRIGHT","RIGHT"),"↓","DOWN"),"↑","UP"),"←","LEFT"),"→","RIGHT"),"SPACEBAR","SPACE"),"−","-"),"MINUS","-"),"PLUS","+")=Key!$E$75:$J$75),"✔ CLEAR","✘ TRY AGAIN"))),"✘ TRY AGAIN")} | F28: {=IF(E28="Show hint",Key!$B$75,"")} | G28: {=IF(LEFT(D28,1)="✔",IF(E28="Show hint",5,10),0)} -> 0
A29: C3 | B29: Which function always rounds down, toward zero? | D29: {=IFERROR(_xlfn.LET(_xlpm.a,'F1-4 Precision'!$C$29,IF(TRIM(_xlpm.a&"")="","",IF(OR(SUBSTITUTE(SUBSTITUTE(SUBSTITUTE(SUBSTITUTE(SUBSTITUTE(SUBSTITUTE(SUBSTITUTE(SUBSTITUTE(SUBSTITUTE(SUBSTITUTE(SUBSTITUTE(SUBSTITUTE(SUBSTITUTE(SUBSTITUTE(SUBSTITUTE(SUBSTITUTE(SUBSTITUTE(SUBSTITUTE(SUBSTITUTE(SUBSTITUTE(SUBSTITUTE(SUBSTITUTE(SUBSTITUTE(SUBSTITUTE(SUBSTITUTE(SUBSTITUTE(SUBSTITUTE(UPPER(_xlpm.a)," ",""),"CONTROL","CTRL"),"CTL","CTRL"),"ESCAPE","ESC"),"RETURN","ENTER"),"PAGEDOWN","PGDN"),"PGDOWN","PGDN"),"PAGEUP","PGUP"),"ARROWKEYS","ARROW"),"ARROWKEY","ARROW"),"ARROWS","ARROW"),"DOWNARROW","DOWN"),"UPARROW","UP"),"LEFTARROW","LEFT"),"RIGHTARROW","RIGHT"),"ARROWDOWN","DOWN"),"ARROWUP","UP"),"ARROWLEFT","LEFT"),"ARROWRIGHT","RIGHT"),"↓","DOWN"),"↑","UP"),"←","LEFT"),"→","RIGHT"),"SPACEBAR","SPACE"),"−","-"),"MINUS","-"),"PLUS","+")=Key!$E$76:$J$76),"✔ CLEAR","✘ TRY AGAIN"))),"✘ TRY AGAIN")} | F29: {=IF(E29="Show hint",Key!$B$76,"")} | G29: {=IF(LEFT(D29,1)="✔",IF(E29="Show hint",5,10),0)} -> 0
A30: C4 | B30: In D6, round B6 to 2 decimals with ROUND. | C30: ▶ ARENA C4 (cell D6) | D30: {=IF(ISBLANK('F1-4 Arena'!$D$6),"",IF(NOT(_xlfn.ISFORMULA('F1-4 Arena'!$D$6)),"✘ That's a typed value · enter a formula",IF(ISERROR('F1-4 Arena'!$D$6),"✘ Your formula returns "&IFERROR(CHOOSE(ERROR.TYPE('F1-4 Arena'!$D$6),"#NULL!","#DIV/0!","#VALUE!","#REF!","#NAME?","#NUM!","#N/A","#GETTING_DATA","#SPILL!","#CONNECT!","#BLOCKED!","#UNKNOWN!","#FIELD!","#CALC!"),"an error"),IF(NOT(AND(IFERROR(AND(ISNUMBER('F1-4 Arena'!$D$6),ABS('F1-4 Arena'!$D$6-Key!$C$77)<=1E-9*MAX(1,ABS(Key!$C$77))),FALSE))),"✘ TRY AGAIN",IF(AND(OR(ISNUMBER(FIND({"=","(",",","+","-","*","/","&"," ","<",">",":","@","^"}&"ROUND"&"(",UPPER(_xlfn.FORMULATEXT('F1-4 Arena'!$D$6)))))),"✔ CLEAR","✘ CLOSE · right value, but use ROUND")))))} | F30: {=IF(E30="Show hint",Key!$B$77,"")} | G30: {=IF(LEFT(D30,1)="✔",IF(E30="Show hint",5,10),0)} -> 0
A31: C5 | B31: In D7, round B7 UP to a whole number with ROUNDUP. | C31: ▶ ARENA C5 (cell D7) | D31: {=IF(ISBLANK('F1-4 Arena'!$D$7),"",IF(NOT(_xlfn.ISFORMULA('F1-4 Arena'!$D$7)),"✘ That's a typed value · enter a formula",IF(ISERROR('F1-4 Arena'!$D$7),"✘ Your formula returns "&IFERROR(CHOOSE(ERROR.TYPE('F1-4 Arena'!$D$7),"#NULL!","#DIV/0!","#VALUE!","#REF!","#NAME?","#NUM!","#N/A","#GETTING_DATA","#SPILL!","#CONNECT!","#BLOCKED!","#UNKNOWN!","#FIELD!","#CALC!"),"an error"),IF(NOT(AND(IFERROR(AND(ISNUMBER('F1-4 Arena'!$D$7),ABS('F1-4 Arena'!$D$7-Key!$C$78)<=1E-9*MAX(1,ABS(Key!$C$78))),FALSE))),"✘ TRY AGAIN",IF(AND(OR(ISNUMBER(FIND({"=","(",",","+","-","*","/","&"," ","<",">",":","@","^"}&"ROUNDUP"&"(",UPPER(_xlfn.FORMULATEXT('F1-4 Arena'!$D$7)))))),"✔ CLEAR","✘ CLOSE · right value, but use ROUNDUP")))))} | F31: {=IF(E31="Show hint",Key!$B$78,"")} | G31: {=IF(LEFT(D31,1)="✔",IF(E31="Show hint",5,10),0)} -> 0
A32: C6 | B32: In D8, round B8 DOWN to 1 decimal with ROUNDDOWN. | C32: ▶ ARENA C6 (cell D8) | D32: {=IF(ISBLANK('F1-4 Arena'!$D$8),"",IF(NOT(_xlfn.ISFORMULA('F1-4 Arena'!$D$8)),"✘ That's a typed value · enter a formula",IF(ISERROR('F1-4 Arena'!$D$8),"✘ Your formula returns "&IFERROR(CHOOSE(ERROR.TYPE('F1-4 Arena'!$D$8),"#NULL!","#DIV/0!","#VALUE!","#REF!","#NAME?","#NUM!","#N/A","#GETTING_DATA","#SPILL!","#CONNECT!","#BLOCKED!","#UNKNOWN!","#FIELD!","#CALC!"),"an error"),IF(NOT(AND(IFERROR(AND(ISNUMBER('F1-4 Arena'!$D$8),ABS('F1-4 Arena'!$D$8-Key!$C$79)<=1E-9*MAX(1,ABS(Key!$C$79))),FALSE))),"✘ TRY AGAIN",IF(AND(OR(ISNUMBER(FIND({"=","(",",","+","-","*","/","&"," ","<",">",":","@","^"}&"ROUNDDOWN"&"(",UPPER(_xlfn.FORMULATEXT('F1-4 Arena'!$D$8)))))),"✔ CLEAR","✘ CLOSE · right value, but use ROUNDDOWN")))))} | F32: {=IF(E32="Show hint",Key!$B$79,"")} | G32: {=IF(LEFT(D32,1)="✔",IF(E32="Show hint",5,10),0)} -> 0
A33: C7 | B33: In D9, round B9 to the nearest hundred with ROUND (use -2 digits). | C33: ▶ ARENA C7 (cell D9) | D33: {=IF(ISBLANK('F1-4 Arena'!$D$9),"",IF(NOT(_xlfn.ISFORMULA('F1-4 Arena'!$D$9)),"✘ That's a typed value · enter a formula",IF(ISERROR('F1-4 Arena'!$D$9),"✘ Your formula returns "&IFERROR(CHOOSE(ERROR.TYPE('F1-4 Arena'!$D$9),"#NULL!","#DIV/0!","#VALUE!","#REF!","#NAME?","#NUM!","#N/A","#GETTING_DATA","#SPILL!","#CONNECT!","#BLOCKED!","#UNKNOWN!","#FIELD!","#CALC!"),"an error"),IF(NOT(AND(IFERROR(AND(ISNUMBER('F1-4 Arena'!$D$9),ABS('F1-4 Arena'!$D$9-Key!$C$80)<=1E-9*MAX(1,ABS(Key!$C$80))),FALSE))),"✘ TRY AGAIN",IF(AND(OR(ISNUMBER(FIND({"=","(",",","+","-","*","/","&"," ","<",">",":","@","^"}&"ROUND"&"(",UPPER(_xlfn.FORMULATEXT('F1-4 Arena'!$D$9)))))),"✔ CLEAR","✘ CLOSE · right value, but use ROUND")))))} | F33: {=IF(E33="Show hint",Key!$B$80,"")} | G33: {=IF(LEFT(D33,1)="✔",IF(E33="Show hint",5,10),0)} -> 0

Sheet F1-4 Arena
A1: ARENA ▸ F1-4 PRECISION
A2: Practice area · everything here is editable. Missions and their checks are on the stage sheet.
A3: PASS CODE | B3: DECIMAL | D3: ◀ Back to F1-4 Precision
B5: Value | C5: Do this
B6: 3.14159 | C6: 2 decimals
B7: 2.4 | C7: up to a whole number
B8: 7.86 | C8: down to 1 decimal
B9: 1234.5 | C9: nearest hundred

Sheet F1-5 X-Ray
A1: STAGE F1-5 ▸ X-RAY
A2: Goal: see inside formulas and write them faster
A3: {="SCORE "&TEXT(SUM($G$15:$G$42),"0000")&" / 0210"} -> SCORE 0000 / 0210 | C3: {=IF(SUM($G$15:$G$42)>=210,"★★★",IF(SUM($G$15:$G$42)>=210*0.8,"★★☆",IF(SUM($G$15:$G$42)>=210*0.5,"★☆☆","☆☆☆")))} -> ☆☆☆ | D3: {=REPT("█",ROUND(10*SUM($G$15:$G$42)/210,0))&REPT("░",10-ROUND(10*SUM($G$15:$G$42)/210,0))&" "&TEXT(SUM($G$15:$G$42)/210,"0%")} -> ░░░░░░░░░░ 0% | F3: {=IF(SUM($G$15:$G$42)>=210*0.5,"STAGE CLEAR! ▶ Next: Boss","")}
A5: BRIEFING · new moves in this stage
A6: # | B6: What it does · Pro tip | C6: Keys / Syntax
A7: 1 | B7: Show formulas instead of results; press again to switch back. Tip: The ` key sits left of 1. Great for spotting typed-over formulas. | C7: Ctrl+`
A8: 2 | B8: Edit the active cell; its references light up in color. Tip: Each colored reference matches a colored box on the sheet. | C8: F2
A9: 3 | B9: While typing a function, Tab inserts the highlighted suggestion. Tip: Type =SU, arrow down to SUMIFS, press Tab: Excel types SUMIFS( for you. | C9: Tab
A10: 4 | B10: After a function name, insert its argument names. Tip: Type =XLOOKUP then Ctrl+Shift+A to see every argument at once. | C10: Ctrl+Shift+A
A11: 5 | B11: Open the Insert Function dialog. Tip: Search for a function by describing what you need. | C11: Shift+F3
A13: WARM-UP · flashback to earlier stages
A14: # | B14: Mission | C14: Your answer | D14: Result | E14: Hint? | F14: Hint | G14: XP
A15: W1 | B15: Which function rounds a number to a chosen number of digits? (from F1-4 Precision) | D15: {=IFERROR(_xlfn.LET(_xlpm.a,'F1-5 X-Ray'!$C$15,IF(TRIM(_xlpm.a&"")="","",IF(OR(SUBSTITUTE(SUBSTITUTE(SUBSTITUTE(SUBSTITUTE(SUBSTITUTE(SUBSTITUTE(SUBSTITUTE(SUBSTITUTE(SUBSTITUTE(SUBSTITUTE(SUBSTITUTE(SUBSTITUTE(SUBSTITUTE(SUBSTITUTE(SUBSTITUTE(SUBSTITUTE(SUBSTITUTE(SUBSTITUTE(SUBSTITUTE(SUBSTITUTE(SUBSTITUTE(SUBSTITUTE(SUBSTITUTE(SUBSTITUTE(SUBSTITUTE(SUBSTITUTE(SUBSTITUTE(UPPER(_xlpm.a)," ",""),"CONTROL","CTRL"),"CTL","CTRL"),"ESCAPE","ESC"),"RETURN","ENTER"),"PAGEDOWN","PGDN"),"PGDOWN","PGDN"),"PAGEUP","PGUP"),"ARROWKEYS","ARROW"),"ARROWKEY","ARROW"),"ARROWS","ARROW"),"DOWNARROW","DOWN"),"UPARROW","UP"),"LEFTARROW","LEFT"),"RIGHTARROW","RIGHT"),"ARROWDOWN","DOWN"),"ARROWUP","UP"),"ARROWLEFT","LEFT"),"ARROWRIGHT","RIGHT"),"↓","DOWN"),"↑","UP"),"←","LEFT"),"→","RIGHT"),"SPACEBAR","SPACE"),"−","-"),"MINUS","-"),"PLUS","+")=Key!$E$81:$J$81),"✔ CLEAR","✘ TRY AGAIN"))),"✘ TRY AGAIN")} | F15: {=IF(E15="Show hint",Key!$B$81,"")} | G15: {=IF(LEFT(D15,1)="✔",IF(E15="Show hint",5,10),0)} -> 0
A16: W2 | B16: Which function always rounds up, away from zero? (from F1-4 Precision) | D16: {=IFERROR(_xlfn.LET(_xlpm.a,'F1-5 X-Ray'!$C$16,IF(TRIM(_xlpm.a&"")="","",IF(OR(SUBSTITUTE(SUBSTITUTE(SUBSTITUTE(SUBSTITUTE(SUBSTITUTE(SUBSTITUTE(SUBSTITUTE(SUBSTITUTE(SUBSTITUTE(SUBSTITUTE(SUBSTITUTE(SUBSTITUTE(SUBSTITUTE(SUBSTITUTE(SUBSTITUTE(SUBSTITUTE(SUBSTITUTE(SUBSTITUTE(SUBSTITUTE(SUBSTITUTE(SUBSTITUTE(SUBSTITUTE(SUBSTITUTE(SUBSTITUTE(SUBSTITUTE(SUBSTITUTE(SUBSTITUTE(UPPER(_xlpm.a)," ",""),"CONTROL","CTRL"),"CTL","CTRL"),"ESCAPE","ESC"),"RETURN","ENTER"),"PAGEDOWN","PGDN"),"PGDOWN","PGDN"),"PAGEUP","PGUP"),"ARROWKEYS","ARROW"),"ARROWKEY","ARROW"),"ARROWS","ARROW"),"DOWNARROW","DOWN"),"UPARROW","UP"),"LEFTARROW","LEFT"),"RIGHTARROW","RIGHT"),"ARROWDOWN","DOWN"),"ARROWUP","UP"),"ARROWLEFT","LEFT"),"ARROWRIGHT","RIGHT"),"↓","DOWN"),"↑","UP"),"←","LEFT"),"→","RIGHT"),"SPACEBAR","SPACE"),"−","-"),"MINUS","-"),"PLUS","+")=Key!$E$82:$J$82),"✔ CLEAR","✘ TRY AGAIN"))),"✘ TRY AGAIN")} | F16: {=IF(E16="Show hint",Key!$B$82,"")} | G16: {=IF(LEFT(D16,1)="✔",IF(E16="Show hint",5,10),0)} -> 0
A17: W3 | B17: Which function always rounds down, toward zero? (from F1-4 Precision) | D17: {=IFERROR(_xlfn.LET(_xlpm.a,'F1-5 X-Ray'!$C$17,IF(TRIM(_xlpm.a&"")="","",IF(OR(SUBSTITUTE(SUBSTITUTE(SUBSTITUTE(SUBSTITUTE(SUBSTITUTE(SUBSTITUTE(SUBSTITUTE(SUBSTITUTE(SUBSTITUTE(SUBSTITUTE(SUBSTITUTE(SUBSTITUTE(SUBSTITUTE(SUBSTITUTE(SUBSTITUTE(SUBSTITUTE(SUBSTITUTE(SUBSTITUTE(SUBSTITUTE(SUBSTITUTE(SUBSTITUTE(SUBSTITUTE(SUBSTITUTE(SUBSTITUTE(SUBSTITUTE(SUBSTITUTE(SUBSTITUTE(UPPER(_xlpm.a)," ",""),"CONTROL","CTRL"),"CTL","CTRL"),"ESCAPE","ESC"),"RETURN","ENTER"),"PAGEDOWN","PGDN"),"PGDOWN","PGDN"),"PAGEUP","PGUP"),"ARROWKEYS","ARROW"),"ARROWKEY","ARROW"),"ARROWS","ARROW"),"DOWNARROW","DOWN"),"UPARROW","UP"),"LEFTARROW","LEFT"),"RIGHTARROW","RIGHT"),"ARROWDOWN","DOWN"),"ARROWUP","UP"),"ARROWLEFT","LEFT"),"ARROWRIGHT","RIGHT"),"↓","DOWN"),"↑","UP"),"←","LEFT"),"→","RIGHT"),"SPACEBAR","SPACE"),"−","-"),"MINUS","-"),"PLUS","+")=Key!$E$83:$J$83),"✔ CLEAR","✘ TRY AGAIN"))),"✘ TRY AGAIN")} | F17: {=IF(E17="Show hint",Key!$B$83,"")} | G17: {=IF(LEFT(D17,1)="✔",IF(E17="Show hint",5,10),0)} -> 0
A18: W4 | B18: Which character must every formula start with? (from F1-1 Power Up) | D18: {=IFERROR(_xlfn.LET(_xlpm.a,'F1-5 X-Ray'!$C$18,IF(TRIM(_xlpm.a&"")="","",IF(OR(SUBSTITUTE(SUBSTITUTE(SUBSTITUTE(SUBSTITUTE(SUBSTITUTE(SUBSTITUTE(SUBSTITUTE(SUBSTITUTE(SUBSTITUTE(SUBSTITUTE(SUBSTITUTE(SUBSTITUTE(SUBSTITUTE(SUBSTITUTE(SUBSTITUTE(SUBSTITUTE(SUBSTITUTE(SUBSTITUTE(SUBSTITUTE(SUBSTITUTE(SUBSTITUTE(SUBSTITUTE(SUBSTITUTE(SUBSTITUTE(SUBSTITUTE(SUBSTITUTE(SUBSTITUTE(UPPER(_xlpm.a)," ",""),"CONTROL","CTRL"),"CTL","CTRL"),"ESCAPE","ESC"),"RETURN","ENTER"),"PAGEDOWN","PGDN"),"PGDOWN","PGDN"),"PAGEUP","PGUP"),"ARROWKEYS","ARROW"),"ARROWKEY","ARROW"),"ARROWS","ARROW"),"DOWNARROW","DOWN"),"UPARROW","UP"),"LEFTARROW","LEFT"),"RIGHTARROW","RIGHT"),"ARROWDOWN","DOWN"),"ARROWUP","UP"),"ARROWLEFT","LEFT"),"ARROWRIGHT","RIGHT"),"↓","DOWN"),"↑","UP"),"←","LEFT"),"→","RIGHT"),"SPACEBAR","SPACE"),"−","-"),"MINUS","-"),"PLUS","+")=Key!$E$84:$H$84),"✔ CLEAR","✘ TRY AGAIN"))),"✘ TRY AGAIN")} | F18: {=IF(E18="Show hint",Key!$B$84,"")} | G18: {=IF(LEFT(D18,1)="✔",IF(E18="Show hint",5,10),0)} -> 0
A19: W5 | B19: Which operator raises a number to a power? (from F1-1 Power Up) | D19: {=IFERROR(_xlfn.LET(_xlpm.a,'F1-5 X-Ray'!$C$19,IF(TRIM(_xlpm.a&"")="","",IF(OR(SUBSTITUTE(SUBSTITUTE(SUBSTITUTE(SUBSTITUTE(SUBSTITUTE(SUBSTITUTE(SUBSTITUTE(SUBSTITUTE(SUBSTITUTE(SUBSTITUTE(SUBSTITUTE(SUBSTITUTE(SUBSTITUTE(SUBSTITUTE(SUBSTITUTE(SUBSTITUTE(SUBSTITUTE(SUBSTITUTE(SUBSTITUTE(SUBSTITUTE(SUBSTITUTE(SUBSTITUTE(SUBSTITUTE(SUBSTITUTE(SUBSTITUTE(SUBSTITUTE(SUBSTITUTE(UPPER(_xlpm.a)," ",""),"CONTROL","CTRL"),"CTL","CTRL"),"ESCAPE","ESC"),"RETURN","ENTER"),"PAGEDOWN","PGDN"),"PGDOWN","PGDN"),"PAGEUP","PGUP"),"ARROWKEYS","ARROW"),"ARROWKEY","ARROW"),"ARROWS","ARROW"),"DOWNARROW","DOWN"),"UPARROW","UP"),"LEFTARROW","LEFT"),"RIGHTARROW","RIGHT"),"ARROWDOWN","DOWN"),"ARROWUP","UP"),"ARROWLEFT","LEFT"),"ARROWRIGHT","RIGHT"),"↓","DOWN"),"↑","UP"),"←","LEFT"),"→","RIGHT"),"SPACEBAR","SPACE"),"−","-"),"MINUS","-"),"PLUS","+")=Key!$E$85:$F$85),"✔ CLEAR","✘ TRY AGAIN"))),"✘ TRY AGAIN")} | F19: {=IF(E19="Show hint",Key!$B$85,"")} | G19: {=IF(LEFT(D19,1)="✔",IF(E19="Show hint",5,10),0)} -> 0
A20: W6 | B20: What does =2+3*4 return? (from F1-1 Power Up) | D20: {=IFERROR(_xlfn.LET(_xlpm.a,'F1-5 X-Ray'!$C$20,IF(TRIM(_xlpm.a&"")="","",IF(OR(SUBSTITUTE(SUBSTITUTE(SUBSTITUTE(SUBSTITUTE(SUBSTITUTE(SUBSTITUTE(SUBSTITUTE(SUBSTITUTE(SUBSTITUTE(SUBSTITUTE(SUBSTITUTE(SUBSTITUTE(SUBSTITUTE(SUBSTITUTE(SUBSTITUTE(SUBSTITUTE(SUBSTITUTE(SUBSTITUTE(SUBSTITUTE(SUBSTITUTE(SUBSTITUTE(SUBSTITUTE(SUBSTITUTE(SUBSTITUTE(SUBSTITUTE(SUBSTITUTE(SUBSTITUTE(UPPER(_xlpm.a)," ",""),"CONTROL","CTRL"),"CTL","CTRL"),"ESCAPE","ESC"),"RETURN","ENTER"),"PAGEDOWN","PGDN"),"PGDOWN","PGDN"),"PAGEUP","PGUP"),"ARROWKEYS","ARROW"),"ARROWKEY","ARROW"),"ARROWS","ARROW"),"DOWNARROW","DOWN"),"UPARROW","UP"),"LEFTARROW","LEFT"),"RIGHTARROW","RIGHT"),"ARROWDOWN","DOWN"),"ARROWUP","UP"),"ARROWLEFT","LEFT"),"ARROWRIGHT","RIGHT"),"↓","DOWN"),"↑","UP"),"←","LEFT"),"→","RIGHT"),"SPACEBAR","SPACE"),"−","-"),"MINUS","-"),"PLUS","+")=Key!$E$86:$E$86),"✔ CLEAR","✘ TRY AGAIN"))),"✘ TRY AGAIN")} | F20: {=IF(E20="Show hint",Key!$B$86,"")} | G20: {=IF(LEFT(D20,1)="✔",IF(E20="Show hint",5,10),0)} -> 0
A21: W7 | B21: Type the formula that multiplies cell B2 by cell C2. (from F1-1 Power Up) | D21: {=IFERROR(_xlfn.LET(_xlpm.a,'F1-5 X-Ray'!$C$21,IF(TRIM(_xlpm.a&"")="","",IF(OR(SUBSTITUTE(SUBSTITUTE(SUBSTITUTE(SUBSTITUTE(SUBSTITUTE(SUBSTITUTE(SUBSTITUTE(SUBSTITUTE(SUBSTITUTE(SUBSTITUTE(SUBSTITUTE(SUBSTITUTE(SUBSTITUTE(SUBSTITUTE(SUBSTITUTE(SUBSTITUTE(SUBSTITUTE(SUBSTITUTE(SUBSTITUTE(SUBSTITUTE(SUBSTITUTE(SUBSTITUTE(SUBSTITUTE(SUBSTITUTE(SUBSTITUTE(SUBSTITUTE(SUBSTITUTE(UPPER(_xlpm.a)," ",""),"CONTROL","CTRL"),"CTL","CTRL"),"ESCAPE","ESC"),"RETURN","ENTER"),"PAGEDOWN","PGDN"),"PGDOWN","PGDN"),"PAGEUP","PGUP"),"ARROWKEYS","ARROW"),"ARROWKEY","ARROW"),"ARROWS","ARROW"),"DOWNARROW","DOWN"),"UPARROW","UP"),"LEFTARROW","LEFT"),"RIGHTARROW","RIGHT"),"ARROWDOWN","DOWN"),"ARROWUP","UP"),"ARROWLEFT","LEFT"),"ARROWRIGHT","RIGHT"),"↓","DOWN"),"↑","UP"),"←","LEFT"),"→","RIGHT"),"SPACEBAR","SPACE"),"−","-"),"MINUS","-"),"PLUS","+")=Key!$E$87:$H$87),"✔ CLEAR","✘ TRY AGAIN"))),"✘ TRY AGAIN")} | F21: {=IF(E21="Show hint",Key!$B$87,"")} | G21: {=IF(LEFT(D21,1)="✔",IF(E21="Show hint",5,10),0)} -> 0
A23: TRAINING · recognize the move (pick from the list)
A24: # | B24: Mission | C24: Your answer | D24: Result | E24: Hint? | F24: Hint | G24: XP
A25: T1 | B25: Which keys switch between showing results and showing formulas? | D25: {=IFERROR(IF('F1-5 X-Ray'!$C$25&""="","",IF('F1-5 X-Ray'!$C$25&""=Key!$C$88&"","✔ CLEAR","✘ TRY AGAIN")),"✘ TRY AGAIN")} | F25: {=IF(E25="Show hint",Key!$B$88,"")} | G25: {=IF(LEFT(D25,1)="✔",IF(E25="Show hint",5,10),0)} -> 0
A26: T2 | B26: Which key edits the active cell and color-codes its references? | D26: {=IFERROR(IF('F1-5 X-Ray'!$C$26&""="","",IF('F1-5 X-Ray'!$C$26&""=Key!$C$89&"","✔ CLEAR","✘ TRY AGAIN")),"✘ TRY AGAIN")} | F26: {=IF(E26="Show hint",Key!$B$89,"")} | G26: {=IF(LEFT(D26,1)="✔",IF(E26="Show hint",5,10),0)} -> 0
A27: T3 | B27: While typing a function name, which key inserts the highlighted AutoComplete suggestion? | D27: {=IFERROR(IF('F1-5 X-Ray'!$C$27&""="","",IF('F1-5 X-Ray'!$C$27&""=Key!$C$90&"","✔ CLEAR","✘ TRY AGAIN")),"✘ TRY AGAIN")} | F27: {=IF(E27="Show hint",Key!$B$90,"")} | G27: {=IF(LEFT(D27,1)="✔",IF(E27="Show hint",5,10),0)} -> 0
A28: T4 | B28: Which keys insert a function's argument names after you type its name? | D28: {=IFERROR(IF('F1-5 X-Ray'!$C$28&""="","",IF('F1-5 X-Ray'!$C$28&""=Key!$C$91&"","✔ CLEAR","✘ TRY AGAIN")),"✘ TRY AGAIN")} | F28: {=IF(E28="Show hint",Key!$B$91,"")} | G28: {=IF(LEFT(D28,1)="✔",IF(E28="Show hint",5,10),0)} -> 0
A29: T5 | B29: Which keys open the Insert Function dialog? | D29: {=IFERROR(IF('F1-5 X-Ray'!$C$29&""="","",IF('F1-5 X-Ray'!$C$29&""=Key!$C$92&"","✔ CLEAR","✘ TRY AGAIN")),"✘ TRY AGAIN")} | F29: {=IF(E29="Show hint",Key!$B$92,"")} | G29: {=IF(LEFT(D29,1)="✔",IF(E29="Show hint",5,10),0)} -> 0
A31: CHALLENGES · recall it, then do it
B32: ▶ Open F1-5 Arena (or press Ctrl+PgDn)
A33: # | B33: Mission | C33: Your answer | D33: Result | E33: Hint? | F33: Hint | G33: XP
A34: C1 | B34: Which keys switch between showing results and showing formulas? | D34: {=IFERROR(_xlfn.LET(_xlpm.a,'F1-5 X-Ray'!$C$34,IF(TRIM(_xlpm.a&"")="","",IF(OR(SUBSTITUTE(SUBSTITUTE(SUBSTITUTE(SUBSTITUTE(SUBSTITUTE(SUBSTITUTE(SUBSTITUTE(SUBSTITUTE(SUBSTITUTE(SUBSTITUTE(SUBSTITUTE(SUBSTITUTE(SUBSTITUTE(SUBSTITUTE(SUBSTITUTE(SUBSTITUTE(SUBSTITUTE(SUBSTITUTE(SUBSTITUTE(SUBSTITUTE(SUBSTITUTE(SUBSTITUTE(SUBSTITUTE(SUBSTITUTE(SUBSTITUTE(SUBSTITUTE(SUBSTITUTE(UPPER(_xlpm.a)," ",""),"CONTROL","CTRL"),"CTL","CTRL"),"ESCAPE","ESC"),"RETURN","ENTER"),"PAGEDOWN","PGDN"),"PGDOWN","PGDN"),"PAGEUP","PGUP"),"ARROWKEYS","ARROW"),"ARROWKEY","ARROW"),"ARROWS","ARROW"),"DOWNARROW","DOWN"),"UPARROW","UP"),"LEFTARROW","LEFT"),"RIGHTARROW","RIGHT"),"ARROWDOWN","DOWN"),"ARROWUP","UP"),"ARROWLEFT","LEFT"),"ARROWRIGHT","RIGHT"),"↓","DOWN"),"↑","UP"),"←","LEFT"),"→","RIGHT"),"SPACEBAR","SPACE"),"−","-"),"MINUS","-"),"PLUS","+")=Key!$E$93:$H$93),"✔ CLEAR","✘ TRY AGAIN"))),"✘ TRY AGAIN")} | F34: {=IF(E34="Show hint",Key!$B$93,"")} | G34: {=IF(LEFT(D34,1)="✔",IF(E34="Show hint",5,10),0)} -> 0
A35: C2 | B35: Which key edits the active cell and color-codes its references? | D35: {=IFERROR(_xlfn.LET(_xlpm.a,'F1-5 X-Ray'!$C$35,IF(TRIM(_xlpm.a&"")="","",IF(OR(SUBSTITUTE(SUBSTITUTE(SUBSTITUTE(SUBSTITUTE(SUBSTITUTE(SUBSTITUTE(SUBSTITUTE(SUBSTITUTE(SUBSTITUTE(SUBSTITUTE(SUBSTITUTE(SUBSTITUTE(SUBSTITUTE(SUBSTITUTE(SUBSTITUTE(SUBSTITUTE(SUBSTITUTE(SUBSTITUTE(SUBSTITUTE(SUBSTITUTE(SUBSTITUTE(SUBSTITUTE(SUBSTITUTE(SUBSTITUTE(SUBSTITUTE(SUBSTITUTE(SUBSTITUTE(UPPER(_xlpm.a)," ",""),"CONTROL","CTRL"),"CTL","CTRL"),"ESCAPE","ESC"),"RETURN","ENTER"),"PAGEDOWN","PGDN"),"PGDOWN","PGDN"),"PAGEUP","PGUP"),"ARROWKEYS","ARROW"),"ARROWKEY","ARROW"),"ARROWS","ARROW"),"DOWNARROW","DOWN"),"UPARROW","UP"),"LEFTARROW","LEFT"),"RIGHTARROW","RIGHT"),"ARROWDOWN","DOWN"),"ARROWUP","UP"),"ARROWLEFT","LEFT"),"ARROWRIGHT","RIGHT"),"↓","DOWN"),"↑","UP"),"←","LEFT"),"→","RIGHT"),"SPACEBAR","SPACE"),"−","-"),"MINUS","-"),"PLUS","+")=Key!$E$94:$E$94),"✔ CLEAR","✘ TRY AGAIN"))),"✘ TRY AGAIN")} | F35: {=IF(E35="Show hint",Key!$B$94,"")} | G35: {=IF(LEFT(D35,1)="✔",IF(E35="Show hint",5,10),0)} -> 0
A36: C3 | B36: While typing a function name, which key inserts the highlighted AutoComplete suggestion? | D36: {=IFERROR(_xlfn.LET(_xlpm.a,'F1-5 X-Ray'!$C$36,IF(TRIM(_xlpm.a&"")="","",IF(OR(SUBSTITUTE(SUBSTITUTE(SUBSTITUTE(SUBSTITUTE(SUBSTITUTE(SUBSTITUTE(SUBSTITUTE(SUBSTITUTE(SUBSTITUTE(SUBSTITUTE(SUBSTITUTE(SUBSTITUTE(SUBSTITUTE(SUBSTITUTE(SUBSTITUTE(SUBSTITUTE(SUBSTITUTE(SUBSTITUTE(SUBSTITUTE(SUBSTITUTE(SUBSTITUTE(SUBSTITUTE(SUBSTITUTE(SUBSTITUTE(SUBSTITUTE(SUBSTITUTE(SUBSTITUTE(UPPER(_xlpm.a)," ",""),"CONTROL","CTRL"),"CTL","CTRL"),"ESCAPE","ESC"),"RETURN","ENTER"),"PAGEDOWN","PGDN"),"PGDOWN","PGDN"),"PAGEUP","PGUP"),"ARROWKEYS","ARROW"),"ARROWKEY","ARROW"),"ARROWS","ARROW"),"DOWNARROW","DOWN"),"UPARROW","UP"),"LEFTARROW","LEFT"),"RIGHTARROW","RIGHT"),"ARROWDOWN","DOWN"),"ARROWUP","UP"),"ARROWLEFT","LEFT"),"ARROWRIGHT","RIGHT"),"↓","DOWN"),"↑","UP"),"←","LEFT"),"→","RIGHT"),"SPACEBAR","SPACE"),"−","-"),"MINUS","-"),"PLUS","+")=Key!$E$95:$E$95),"✔ CLEAR","✘ TRY AGAIN"))),"✘ TRY AGAIN")} | F36: {=IF(E36="Show hint",Key!$B$95,"")} | G36: {=IF(LEFT(D36,1)="✔",IF(E36="Show hint",5,10),0)} -> 0
A37: C4 | B37: Which keys insert a function's argument names after you type its name? | D37: {=IFERROR(_xlfn.LET(_xlpm.a,'F1-5 X-Ray'!$C$37,IF(TRIM(_xlpm.a&"")="","",IF(OR(SUBSTITUTE(SUBSTITUTE(SUBSTITUTE(SUBSTITUTE(SUBSTITUTE(SUBSTITUTE(SUBSTITUTE(SUBSTITUTE(SUBSTITUTE(SUBSTITUTE(SUBSTITUTE(SUBSTITUTE(SUBSTITUTE(SUBSTITUTE(SUBSTITUTE(SUBSTITUTE(SUBSTITUTE(SUBSTITUTE(SUBSTITUTE(SUBSTITUTE(SUBSTITUTE(SUBSTITUTE(SUBSTITUTE(SUBSTITUTE(SUBSTITUTE(SUBSTITUTE(SUBSTITUTE(UPPER(_xlpm.a)," ",""),"CONTROL","CTRL"),"CTL","CTRL"),"ESCAPE","ESC"),"RETURN","ENTER"),"PAGEDOWN","PGDN"),"PGDOWN","PGDN"),"PAGEUP","PGUP"),"ARROWKEYS","ARROW"),"ARROWKEY","ARROW"),"ARROWS","ARROW"),"DOWNARROW","DOWN"),"UPARROW","UP"),"LEFTARROW","LEFT"),"RIGHTARROW","RIGHT"),"ARROWDOWN","DOWN"),"ARROWUP","UP"),"ARROWLEFT","LEFT"),"ARROWRIGHT","RIGHT"),"↓","DOWN"),"↑","UP"),"←","LEFT"),"→","RIGHT"),"SPACEBAR","SPACE"),"−","-"),"MINUS","-"),"PLUS","+")=Key!$E$96:$F$96),"✔ CLEAR","✘ TRY AGAIN"))),"✘ TRY AGAIN")} | F37: {=IF(E37="Show hint",Key!$B$96,"")} | G37: {=IF(LEFT(D37,1)="✔",IF(E37="Show hint",5,10),0)} -> 0
A38: C5 | B38: Which keys open the Insert Function dialog? | D38: {=IFERROR(_xlfn.LET(_xlpm.a,'F1-5 X-Ray'!$C$38,IF(TRIM(_xlpm.a&"")="","",IF(OR(SUBSTITUTE(SUBSTITUTE(SUBSTITUTE(SUBSTITUTE(SUBSTITUTE(SUBSTITUTE(SUBSTITUTE(SUBSTITUTE(SUBSTITUTE(SUBSTITUTE(SUBSTITUTE(SUBSTITUTE(SUBSTITUTE(SUBSTITUTE(SUBSTITUTE(SUBSTITUTE(SUBSTITUTE(SUBSTITUTE(SUBSTITUTE(SUBSTITUTE(SUBSTITUTE(SUBSTITUTE(SUBSTITUTE(SUBSTITUTE(SUBSTITUTE(SUBSTITUTE(SUBSTITUTE(UPPER(_xlpm.a)," ",""),"CONTROL","CTRL"),"CTL","CTRL"),"ESCAPE","ESC"),"RETURN","ENTER"),"PAGEDOWN","PGDN"),"PGDOWN","PGDN"),"PAGEUP","PGUP"),"ARROWKEYS","ARROW"),"ARROWKEY","ARROW"),"ARROWS","ARROW"),"DOWNARROW","DOWN"),"UPARROW","UP"),"LEFTARROW","LEFT"),"RIGHTARROW","RIGHT"),"ARROWDOWN","DOWN"),"ARROWUP","UP"),"ARROWLEFT","LEFT"),"ARROWRIGHT","RIGHT"),"↓","DOWN"),"↑","UP"),"←","LEFT"),"→","RIGHT"),"SPACEBAR","SPACE"),"−","-"),"MINUS","-"),"PLUS","+")=Key!$E$97:$E$97),"✔ CLEAR","✘ TRY AGAIN"))),"✘ TRY AGAIN")} | F38: {=IF(E38="Show hint",Key!$B$97,"")} | G38: {=IF(LEFT(D38,1)="✔",IF(E38="Show hint",5,10),0)} -> 0
A39: C6 | B39: In the arena press Ctrl+` to show formulas. One cell in C6:C15 is a typed number, not a formula. Type its address, then press Ctrl+` again to switch back. | D39: {=IFERROR(_xlfn.LET(_xlpm.a,'F1-5 X-Ray'!$C$39,IF(TRIM(_xlpm.a&"")="","",IF(SUBSTITUTE(SUBSTITUTE(UPPER(_xlpm.a&"")," ",""),"$","")=Key!$C$98,"✔ CLEAR","✘ TRY AGAIN"))),"✘ TRY AGAIN")} | F39: {=IF(E39="Show hint",Key!$B$98,"")} | G39: {=IF(LEFT(D39,1)="✔",IF(E39="Show hint",5,10),0)} -> 0
A40: C7 | B40: In the arena select E6 and press F2. Each reference lights up in its own color. One reference points outside the Points column: type its address, then press Esc. | D40: {=IFERROR(_xlfn.LET(_xlpm.a,'F1-5 X-Ray'!$C$40,IF(TRIM(_xlpm.a&"")="","",IF(SUBSTITUTE(SUBSTITUTE(UPPER(_xlpm.a&"")," ",""),"$","")=Key!$C$99,"✔ CLEAR","✘ TRY AGAIN"))),"✘ TRY AGAIN")} | F40: {=IF(E40="Show hint",Key!$B$99,"")} | G40: {=IF(LEFT(D40,1)="✔",IF(E40="Show hint",5,10),0)} -> 0
A41: C8 | B41: In G8 type =AVER, then press Tab when AutoComplete highlights AVERAGE. Finish the formula so it averages C6:C15. | C41: ▶ ARENA C8 (cell G8) | D41: {=IF(ISBLANK('F1-5 Arena'!$G$8),"",IF(NOT(_xlfn.ISFORMULA('F1-5 Arena'!$G$8)),"✘ That's a typed value · enter a formula",IF(ISERROR('F1-5 Arena'!$G$8),"✘ Your formula returns "&IFERROR(CHOOSE(ERROR.TYPE('F1-5 Arena'!$G$8),"#NULL!","#DIV/0!","#VALUE!","#REF!","#NAME?","#NUM!","#N/A","#GETTING_DATA","#SPILL!","#CONNECT!","#BLOCKED!","#UNKNOWN!","#FIELD!","#CALC!"),"an error"),IF(NOT(AND(IFERROR(AND(ISNUMBER('F1-5 Arena'!$G$8),ABS('F1-5 Arena'!$G$8-Key!$C$100)<=1E-9*MAX(1,ABS(Key!$C$100))),FALSE))),"✘ TRY AGAIN",IF(AND(OR(ISNUMBER(FIND({"=","(",",","+","-","*","/","&"," ","<",">",":","@","^"}&"AVERAGE"&"(",UPPER(_xlfn.FORMULATEXT('F1-5 Arena'!$G$8)))))),"✔ CLEAR","✘ CLOSE · right value, but use AVERAGE")))))} | F41: {=IF(E41="Show hint",Key!$B$100,"")} | G41: {=IF(LEFT(D41,1)="✔",IF(E41="Show hint",5,10),0)} -> 0
A42: C9 | B42: In G9 type =ROUND and press Ctrl+Shift+A: Excel writes ROUND(number,num_digits). Replace the argument names so G9 shows E6 divided by 7, rounded to 1 decimal. | C42: ▶ ARENA C9 (cell G9) | D42: {=IF(ISBLANK('F1-5 Arena'!$G$9),"",IF(NOT(_xlfn.ISFORMULA('F1-5 Arena'!$G$9)),"✘ That's a typed value · enter a formula",IF(ISERROR('F1-5 Arena'!$G$9),"✘ Your formula returns "&IFERROR(CHOOSE(ERROR.TYPE('F1-5 Arena'!$G$9),"#NULL!","#DIV/0!","#VALUE!","#REF!","#NAME?","#NUM!","#N/A","#GETTING_DATA","#SPILL!","#CONNECT!","#BLOCKED!","#UNKNOWN!","#FIELD!","#CALC!"),"an error"),IF(NOT(AND(IFERROR(AND(ISNUMBER('F1-5 Arena'!$G$9),ABS('F1-5 Arena'!$G$9-Key!$C$101)<=1E-9*MAX(1,ABS(Key!$C$101))),FALSE))),"✘ TRY AGAIN",IF(AND(OR(ISNUMBER(FIND({"=","(",",","+","-","*","/","&"," ","<",">",":","@","^"}&"ROUND"&"(",UPPER(_xlfn.FORMULATEXT('F1-5 Arena'!$G$9)))))),"✔ CLEAR","✘ CLOSE · right value, but use ROUND")))))} | F42: {=IF(E42="Show hint",Key!$B$101,"")} | G42: {=IF(LEFT(D42,1)="✔",IF(E42="Show hint",5,10),0)} -> 0

Sheet F1-5 Arena
A1: ARENA ▸ F1-5 X-RAY
A2: Practice area · everything here is editable. Missions and their checks are on the stage sheet.
A3: PASS CODE | B3: XRAY | D3: ◀ Back to F1-5 X-Ray
B5: Day | C5: Points | E5: Total
B6: 1 | C6: {=B6*10+5} -> 15 | E6: {=SUM(C6:C15)+H20} -> 650
B7: 2 | C7: {=B7*10+5} -> 25
B8: 3 | C8: {=B8*10+5} -> 35 | F8: Average points
B9: 4 | C9: {=B9*10+5} -> 45 | F9: Total ÷ 7, 1 decimal
B10: 5 | C10: {=B10*10+5} -> 55
B11: 6 | C11: {=B11*10+5} -> 65
B12: 7 | C12: 75
B13: 8 | C13: {=B13*10+5} -> 85
B14: 9 | C14: {=B14*10+5} -> 95
B15: 10 | C15: {=B15*10+5} -> 105
H19: Bonus
H20: 50

Sheet Boss
A1: BOSS ▸ FORMULA BASICS
A2: Every move from this world in one gauntlet. Clear it under par for rank S.
A3: {="SCORE "&TEXT(SUM($G$14:$G$33),"0000")&" / 0160"} -> SCORE 0000 / 0160 | C3: {=IF(SUM($G$14:$G$33)>=160,"★★★",IF(SUM($G$14:$G$33)>=160*0.8,"★★☆",IF(SUM($G$14:$G$33)>=160*0.5,"★☆☆","☆☆☆")))} -> ☆☆☆ | D3: {=REPT("█",ROUND(10*SUM($G$14:$G$33)/160,0))&REPT("░",10-ROUND(10*SUM($G$14:$G$33)/160,0))&" "&TEXT(SUM($G$14:$G$33)/160,"0%")} -> ░░░░░░░░░░ 0%
A5: SPEEDRUN · stamp START, beat the Boss, stamp FINISH
B6: START · select C6 and press Ctrl+Shift+:
B7: FINISH · select C7 and press Ctrl+Shift+:
B8: TIME | C8: {=IF(OR(C6="",C7=""),"",ROUND(MOD(C7-C6,1)*1440,0))}
B9: PAR | C9: 15
B10: BOSS GATE | C10: {=IF(AND(SUM('F1-1 Power Up'!$G$14:$G$37)>=170*0.5,SUM('F1-2 Big Six'!$G$17:$G$51)>=280*0.5,SUM('F1-3 Anchors'!$G$14:$G$40)>=200*0.5,SUM('F1-4 Precision'!$G$13:$G$33)>=140*0.5,SUM('F1-5 X-Ray'!$G$15:$G$42)>=210*0.5),"OPEN","LOCKED")} -> LOCKED | D10: {=IF(C10="OPEN","Gate open · go!","Earn ★ on every stage to open the gate")} -> Earn ★ on every stage to open the gate
A12: FLASHBACK · moves from earlier worlds
A13: # | B13: Mission | C13: Your answer | D13: Result | E13: Hint? | F13: Hint | G13: XP
A14: F1 | B14: {=IF($C$10="OPEN","Which keys switch between showing results and showing formulas? (from F1-5 X-Ray)","LOCKED · earn ★ on every stage to open the Boss gate")} -> LOCKED · earn ★ on every stage to open the Boss gate | D14: {=IF($C$10="OPEN",IFERROR(_xlfn.LET(_xlpm.a,Boss!$C$14,IF(TRIM(_xlpm.a&"")="","",IF(OR(SUBSTITUTE(SUBSTITUTE(SUBSTITUTE(SUBSTITUTE(SUBSTITUTE(SUBSTITUTE(SUBSTITUTE(SUBSTITUTE(SUBSTITUTE(SUBSTITUTE(SUBSTITUTE(SUBSTITUTE(SUBSTITUTE(SUBSTITUTE(SUBSTITUTE(SUBSTITUTE(SUBSTITUTE(SUBSTITUTE(SUBSTITUTE(SUBSTITUTE(SUBSTITUTE(SUBSTITUTE(SUBSTITUTE(SUBSTITUTE(SUBSTITUTE(SUBSTITUTE(SUBSTITUTE(UPPER(_xlpm.a)," ",""),"CONTROL","CTRL"),"CTL","CTRL"),"ESCAPE","ESC"),"RETURN","ENTER"),"PAGEDOWN","PGDN"),"PGDOWN","PGDN"),"PAGEUP","PGUP"),"ARROWKEYS","ARROW"),"ARROWKEY","ARROW"),"ARROWS","ARROW"),"DOWNARROW","DOWN"),"UPARROW","UP"),"LEFTARROW","LEFT"),"RIGHTARROW","RIGHT"),"ARROWDOWN","DOWN"),"ARROWUP","UP"),"ARROWLEFT","LEFT"),"ARROWRIGHT","RIGHT"),"↓","DOWN"),"↑","UP"),"←","LEFT"),"→","RIGHT"),"SPACEBAR","SPACE"),"−","-"),"MINUS","-"),"PLUS","+")=Key!$E$102:$H$102),"✔ CLEAR","✘ TRY AGAIN"))),"✘ TRY AGAIN"),"LOCKED")} -> LOCKED | F14: {=IF(E14="Show hint",Key!$B$102,"")} | G14: {=IF(LEFT(D14,1)="✔",IF(E14="Show hint",5,10),0)} -> 0
A15: F2 | B15: {=IF($C$10="OPEN","Which key edits the active cell and color-codes its references? (from F1-5 X-Ray)","LOCKED · earn ★ on every stage to open the Boss gate")} -> LOCKED · earn ★ on every stage to open the Boss gate | D15: {=IF($C$10="OPEN",IFERROR(_xlfn.LET(_xlpm.a,Boss!$C$15,IF(TRIM(_xlpm.a&"")="","",IF(OR(SUBSTITUTE(SUBSTITUTE(SUBSTITUTE(SUBSTITUTE(SUBSTITUTE(SUBSTITUTE(SUBSTITUTE(SUBSTITUTE(SUBSTITUTE(SUBSTITUTE(SUBSTITUTE(SUBSTITUTE(SUBSTITUTE(SUBSTITUTE(SUBSTITUTE(SUBSTITUTE(SUBSTITUTE(SUBSTITUTE(SUBSTITUTE(SUBSTITUTE(SUBSTITUTE(SUBSTITUTE(SUBSTITUTE(SUBSTITUTE(SUBSTITUTE(SUBSTITUTE(SUBSTITUTE(UPPER(_xlpm.a)," ",""),"CONTROL","CTRL"),"CTL","CTRL"),"ESCAPE","ESC"),"RETURN","ENTER"),"PAGEDOWN","PGDN"),"PGDOWN","PGDN"),"PAGEUP","PGUP"),"ARROWKEYS","ARROW"),"ARROWKEY","ARROW"),"ARROWS","ARROW"),"DOWNARROW","DOWN"),"UPARROW","UP"),"LEFTARROW","LEFT"),"RIGHTARROW","RIGHT"),"ARROWDOWN","DOWN"),"ARROWUP","UP"),"ARROWLEFT","LEFT"),"ARROWRIGHT","RIGHT"),"↓","DOWN"),"↑","UP"),"←","LEFT"),"→","RIGHT"),"SPACEBAR","SPACE"),"−","-"),"MINUS","-"),"PLUS","+")=Key!$E$103:$E$103),"✔ CLEAR","✘ TRY AGAIN"))),"✘ TRY AGAIN"),"LOCKED")} -> LOCKED | F15: {=IF(E15="Show hint",Key!$B$103,"")} | G15: {=IF(LEFT(D15,1)="✔",IF(E15="Show hint",5,10),0)} -> 0
A16: F3 | B16: {=IF($C$10="OPEN","While typing a function name, which key inserts the highlighted AutoComplete suggestion? (from F1-5 X-Ray)","LOCKED · earn ★ on every stage to open the Boss gate")} -> LOCKED · earn ★ on every stage to open the Boss gate | D16: {=IF($C$10="OPEN",IFERROR(_xlfn.LET(_xlpm.a,Boss!$C$16,IF(TRIM(_xlpm.a&"")="","",IF(OR(SUBSTITUTE(SUBSTITUTE(SUBSTITUTE(SUBSTITUTE(SUBSTITUTE(SUBSTITUTE(SUBSTITUTE(SUBSTITUTE(SUBSTITUTE(SUBSTITUTE(SUBSTITUTE(SUBSTITUTE(SUBSTITUTE(SUBSTITUTE(SUBSTITUTE(SUBSTITUTE(SUBSTITUTE(SUBSTITUTE(SUBSTITUTE(SUBSTITUTE(SUBSTITUTE(SUBSTITUTE(SUBSTITUTE(SUBSTITUTE(SUBSTITUTE(SUBSTITUTE(SUBSTITUTE(UPPER(_xlpm.a)," ",""),"CONTROL","CTRL"),"CTL","CTRL"),"ESCAPE","ESC"),"RETURN","ENTER"),"PAGEDOWN","PGDN"),"PGDOWN","PGDN"),"PAGEUP","PGUP"),"ARROWKEYS","ARROW"),"ARROWKEY","ARROW"),"ARROWS","ARROW"),"DOWNARROW","DOWN"),"UPARROW","UP"),"LEFTARROW","LEFT"),"RIGHTARROW","RIGHT"),"ARROWDOWN","DOWN"),"ARROWUP","UP"),"ARROWLEFT","LEFT"),"ARROWRIGHT","RIGHT"),"↓","DOWN"),"↑","UP"),"←","LEFT"),"→","RIGHT"),"SPACEBAR","SPACE"),"−","-"),"MINUS","-"),"PLUS","+")=Key!$E$104:$E$104),"✔ CLEAR","✘ TRY AGAIN"))),"✘ TRY AGAIN"),"LOCKED")} -> LOCKED | F16: {=IF(E16="Show hint",Key!$B$104,"")} | G16: {=IF(LEFT(D16,1)="✔",IF(E16="Show hint",5,10),0)} -> 0
A17: F4 | B17: {=IF($C$10="OPEN","Which keys insert a function's argument names after you type its name? (from F1-5 X-Ray)","LOCKED · earn ★ on every stage to open the Boss gate")} -> LOCKED · earn ★ on every stage to open the Boss gate | D17: {=IF($C$10="OPEN",IFERROR(_xlfn.LET(_xlpm.a,Boss!$C$17,IF(TRIM(_xlpm.a&"")="","",IF(OR(SUBSTITUTE(SUBSTITUTE(SUBSTITUTE(SUBSTITUTE(SUBSTITUTE(SUBSTITUTE(SUBSTITUTE(SUBSTITUTE(SUBSTITUTE(SUBSTITUTE(SUBSTITUTE(SUBSTITUTE(SUBSTITUTE(SUBSTITUTE(SUBSTITUTE(SUBSTITUTE(SUBSTITUTE(SUBSTITUTE(SUBSTITUTE(SUBSTITUTE(SUBSTITUTE(SUBSTITUTE(SUBSTITUTE(SUBSTITUTE(SUBSTITUTE(SUBSTITUTE(SUBSTITUTE(UPPER(_xlpm.a)," ",""),"CONTROL","CTRL"),"CTL","CTRL"),"ESCAPE","ESC"),"RETURN","ENTER"),"PAGEDOWN","PGDN"),"PGDOWN","PGDN"),"PAGEUP","PGUP"),"ARROWKEYS","ARROW"),"ARROWKEY","ARROW"),"ARROWS","ARROW"),"DOWNARROW","DOWN"),"UPARROW","UP"),"LEFTARROW","LEFT"),"RIGHTARROW","RIGHT"),"ARROWDOWN","DOWN"),"ARROWUP","UP"),"ARROWLEFT","LEFT"),"ARROWRIGHT","RIGHT"),"↓","DOWN"),"↑","UP"),"←","LEFT"),"→","RIGHT"),"SPACEBAR","SPACE"),"−","-"),"MINUS","-"),"PLUS","+")=Key!$E$105:$F$105),"✔ CLEAR","✘ TRY AGAIN"))),"✘ TRY AGAIN"),"LOCKED")} -> LOCKED | F17: {=IF(E17="Show hint",Key!$B$105,"")} | G17: {=IF(LEFT(D17,1)="✔",IF(E17="Show hint",5,10),0)} -> 0
A18: F5 | B18: {=IF($C$10="OPEN","Which keys open the Insert Function dialog? (from F1-5 X-Ray)","LOCKED · earn ★ on every stage to open the Boss gate")} -> LOCKED · earn ★ on every stage to open the Boss gate | D18: {=IF($C$10="OPEN",IFERROR(_xlfn.LET(_xlpm.a,Boss!$C$18,IF(TRIM(_xlpm.a&"")="","",IF(OR(SUBSTITUTE(SUBSTITUTE(SUBSTITUTE(SUBSTITUTE(SUBSTITUTE(SUBSTITUTE(SUBSTITUTE(SUBSTITUTE(SUBSTITUTE(SUBSTITUTE(SUBSTITUTE(SUBSTITUTE(SUBSTITUTE(SUBSTITUTE(SUBSTITUTE(SUBSTITUTE(SUBSTITUTE(SUBSTITUTE(SUBSTITUTE(SUBSTITUTE(SUBSTITUTE(SUBSTITUTE(SUBSTITUTE(SUBSTITUTE(SUBSTITUTE(SUBSTITUTE(SUBSTITUTE(UPPER(_xlpm.a)," ",""),"CONTROL","CTRL"),"CTL","CTRL"),"ESCAPE","ESC"),"RETURN","ENTER"),"PAGEDOWN","PGDN"),"PGDOWN","PGDN"),"PAGEUP","PGUP"),"ARROWKEYS","ARROW"),"ARROWKEY","ARROW"),"ARROWS","ARROW"),"DOWNARROW","DOWN"),"UPARROW","UP"),"LEFTARROW","LEFT"),"RIGHTARROW","RIGHT"),"ARROWDOWN","DOWN"),"ARROWUP","UP"),"ARROWLEFT","LEFT"),"ARROWRIGHT","RIGHT"),"↓","DOWN"),"↑","UP"),"←","LEFT"),"→","RIGHT"),"SPACEBAR","SPACE"),"−","-"),"MINUS","-"),"PLUS","+")=Key!$E$106:$E$106),"✔ CLEAR","✘ TRY AGAIN"))),"✘ TRY AGAIN"),"LOCKED")} -> LOCKED | F18: {=IF(E18="Show hint",Key!$B$106,"")} | G18: {=IF(LEFT(D18,1)="✔",IF(E18="Show hint",5,10),0)} -> 0
A19: F6 | B19: {=IF($C$10="OPEN","Which function adds up a range of numbers? (from F1-2 Big Six)","LOCKED · earn ★ on every stage to open the Boss gate")} -> LOCKED · earn ★ on every stage to open the Boss gate | D19: {=IF($C$10="OPEN",IFERROR(_xlfn.LET(_xlpm.a,Boss!$C$19,IF(TRIM(_xlpm.a&"")="","",IF(OR(SUBSTITUTE(SUBSTITUTE(SUBSTITUTE(SUBSTITUTE(SUBSTITUTE(SUBSTITUTE(SUBSTITUTE(SUBSTITUTE(SUBSTITUTE(SUBSTITUTE(SUBSTITUTE(SUBSTITUTE(SUBSTITUTE(SUBSTITUTE(SUBSTITUTE(SUBSTITUTE(SUBSTITUTE(SUBSTITUTE(SUBSTITUTE(SUBSTITUTE(SUBSTITUTE(SUBSTITUTE(SUBSTITUTE(SUBSTITUTE(SUBSTITUTE(SUBSTITUTE(SUBSTITUTE(UPPER(_xlpm.a)," ",""),"CONTROL","CTRL"),"CTL","CTRL"),"ESCAPE","ESC"),"RETURN","ENTER"),"PAGEDOWN","PGDN"),"PGDOWN","PGDN"),"PAGEUP","PGUP"),"ARROWKEYS","ARROW"),"ARROWKEY","ARROW"),"ARROWS","ARROW"),"DOWNARROW","DOWN"),"UPARROW","UP"),"LEFTARROW","LEFT"),"RIGHTARROW","RIGHT"),"ARROWDOWN","DOWN"),"ARROWUP","UP"),"ARROWLEFT","LEFT"),"ARROWRIGHT","RIGHT"),"↓","DOWN"),"↑","UP"),"←","LEFT"),"→","RIGHT"),"SPACEBAR","SPACE"),"−","-"),"MINUS","-"),"PLUS","+")=Key!$E$107:$J$107),"✔ CLEAR","✘ TRY AGAIN"))),"✘ TRY AGAIN"),"LOCKED")} -> LOCKED | F19: {=IF(E19="Show hint",Key!$B$107,"")} | G19: {=IF(LEFT(D19,1)="✔",IF(E19="Show hint",5,10),0)} -> 0
A20: F7 | B20: {=IF($C$10="OPEN","Which function returns the mean of a range? (from F1-2 Big Six)","LOCKED · earn ★ on every stage to open the Boss gate")} -> LOCKED · earn ★ on every stage to open the Boss gate | D20: {=IF($C$10="OPEN",IFERROR(_xlfn.LET(_xlpm.a,Boss!$C$20,IF(TRIM(_xlpm.a&"")="","",IF(OR(SUBSTITUTE(SUBSTITUTE(SUBSTITUTE(SUBSTITUTE(SUBSTITUTE(SUBSTITUTE(SUBSTITUTE(SUBSTITUTE(SUBSTITUTE(SUBSTITUTE(SUBSTITUTE(SUBSTITUTE(SUBSTITUTE(SUBSTITUTE(SUBSTITUTE(SUBSTITUTE(SUBSTITUTE(SUBSTITUTE(SUBSTITUTE(SUBSTITUTE(SUBSTITUTE(SUBSTITUTE(SUBSTITUTE(SUBSTITUTE(SUBSTITUTE(SUBSTITUTE(SUBSTITUTE(UPPER(_xlpm.a)," ",""),"CONTROL","CTRL"),"CTL","CTRL"),"ESCAPE","ESC"),"RETURN","ENTER"),"PAGEDOWN","PGDN"),"PGDOWN","PGDN"),"PAGEUP","PGUP"),"ARROWKEYS","ARROW"),"ARROWKEY","ARROW"),"ARROWS","ARROW"),"DOWNARROW","DOWN"),"UPARROW","UP"),"LEFTARROW","LEFT"),"RIGHTARROW","RIGHT"),"ARROWDOWN","DOWN"),"ARROWUP","UP"),"ARROWLEFT","LEFT"),"ARROWRIGHT","RIGHT"),"↓","DOWN"),"↑","UP"),"←","LEFT"),"→","RIGHT"),"SPACEBAR","SPACE"),"−","-"),"MINUS","-"),"PLUS","+")=Key!$E$108:$J$108),"✔ CLEAR","✘ TRY AGAIN"))),"✘ TRY AGAIN"),"LOCKED")} -> LOCKED | F20: {=IF(E20="Show hint",Key!$B$108,"")} | G20: {=IF(LEFT(D20,1)="✔",IF(E20="Show hint",5,10),0)} -> 0
A21: F8 | B21: {=IF($C$10="OPEN","Which function returns the largest number in a range? (from F1-2 Big Six)","LOCKED · earn ★ on every stage to open the Boss gate")} -> LOCKED · earn ★ on every stage to open the Boss gate | D21: {=IF($C$10="OPEN",IFERROR(_xlfn.LET(_xlpm.a,Boss!$C$21,IF(TRIM(_xlpm.a&"")="","",IF(OR(SUBSTITUTE(SUBSTITUTE(SUBSTITUTE(SUBSTITUTE(SUBSTITUTE(SUBSTITUTE(SUBSTITUTE(SUBSTITUTE(SUBSTITUTE(SUBSTITUTE(SUBSTITUTE(SUBSTITUTE(SUBSTITUTE(SUBSTITUTE(SUBSTITUTE(SUBSTITUTE(SUBSTITUTE(SUBSTITUTE(SUBSTITUTE(SUBSTITUTE(SUBSTITUTE(SUBSTITUTE(SUBSTITUTE(SUBSTITUTE(SUBSTITUTE(SUBSTITUTE(SUBSTITUTE(UPPER(_xlpm.a)," ",""),"CONTROL","CTRL"),"CTL","CTRL"),"ESCAPE","ESC"),"RETURN","ENTER"),"PAGEDOWN","PGDN"),"PGDOWN","PGDN"),"PAGEUP","PGUP"),"ARROWKEYS","ARROW"),"ARROWKEY","ARROW"),"ARROWS","ARROW"),"DOWNARROW","DOWN"),"UPARROW","UP"),"LEFTARROW","LEFT"),"RIGHTARROW","RIGHT"),"ARROWDOWN","DOWN"),"ARROWUP","UP"),"ARROWLEFT","LEFT"),"ARROWRIGHT","RIGHT"),"↓","DOWN"),"↑","UP"),"←","LEFT"),"→","RIGHT"),"SPACEBAR","SPACE"),"−","-"),"MINUS","-"),"PLUS","+")=Key!$E$109:$J$109),"✔ CLEAR","✘ TRY AGAIN"))),"✘ TRY AGAIN"),"LOCKED")} -> LOCKED | F21: {=IF(E21="Show hint",Key!$B$109,"")} | G21: {=IF(LEFT(D21,1)="✔",IF(E21="Show hint",5,10),0)} -> 0
A23: BOSS MISSIONS
B24: ▶ Open Boss Arena (or press Ctrl+PgDn)
A25: # | B25: Mission | C25: Your answer | D25: Result | E25: Hint? | F25: Hint | G25: XP
A26: B1 | B26: {=IF($C$10="OPEN","In J8, total the Qty column (E6:E15) with SUM.","LOCKED · earn ★ on every stage to open the Boss gate")} -> LOCKED · earn ★ on every stage to open the Boss gate | C26: ▶ ARENA B1 (cell J8) | D26: {=IF($C$10="OPEN",IF(ISBLANK('Boss Arena'!$J$8),"",IF(NOT(_xlfn.ISFORMULA('Boss Arena'!$J$8)),"✘ That's a typed value · enter a formula",IF(ISERROR('Boss Arena'!$J$8),"✘ Your formula returns "&IFERROR(CHOOSE(ERROR.TYPE('Boss Arena'!$J$8),"#NULL!","#DIV/0!","#VALUE!","#REF!","#NAME?","#NUM!","#N/A","#GETTING_DATA","#SPILL!","#CONNECT!","#BLOCKED!","#UNKNOWN!","#FIELD!","#CALC!"),"an error"),IF(NOT(AND(IFERROR(AND(ISNUMBER('Boss Arena'!$J$8),ABS('Boss Arena'!$J$8-Key!$C$110)<=1E-9*MAX(1,ABS(Key!$C$110))),FALSE))),"✘ TRY AGAIN",IF(AND(OR(ISNUMBER(FIND({"=","(",",","+","-","*","/","&"," ","<",">",":","@","^"}&"SUM"&"(",UPPER(_xlfn.FORMULATEXT('Boss Arena'!$J$8)))))),"✔ CLEAR","✘ CLOSE · right value, but use SUM"))))),"LOCKED")} -> LOCKED | F26: {=IF(E26="Show hint",Key!$B$110,"")} | G26: {=IF(LEFT(D26,1)="✔",IF(E26="Show hint",5,10),0)} -> 0
A27: B2 | B27: {=IF($C$10="OPEN","In J9, average the Price column with AVERAGE.","LOCKED · earn ★ on every stage to open the Boss gate")} -> LOCKED · earn ★ on every stage to open the Boss gate | C27: ▶ ARENA B2 (cell J9) | D27: {=IF($C$10="OPEN",IF(ISBLANK('Boss Arena'!$J$9),"",IF(NOT(_xlfn.ISFORMULA('Boss Arena'!$J$9)),"✘ That's a typed value · enter a formula",IF(ISERROR('Boss Arena'!$J$9),"✘ Your formula returns "&IFERROR(CHOOSE(ERROR.TYPE('Boss Arena'!$J$9),"#NULL!","#DIV/0!","#VALUE!","#REF!","#NAME?","#NUM!","#N/A","#GETTING_DATA","#SPILL!","#CONNECT!","#BLOCKED!","#UNKNOWN!","#FIELD!","#CALC!"),"an error"),IF(NOT(AND(IFERROR(AND(ISNUMBER('Boss Arena'!$J$9),ABS('Boss Arena'!$J$9-Key!$C$111)<=1E-9*MAX(1,ABS(Key!$C$111))),FALSE))),"✘ TRY AGAIN",IF(AND(OR(ISNUMBER(FIND({"=","(",",","+","-","*","/","&"," ","<",">",":","@","^"}&"AVERAGE"&"(",UPPER(_xlfn.FORMULATEXT('Boss Arena'!$J$9)))))),"✔ CLEAR","✘ CLOSE · right value, but use AVERAGE"))))),"LOCKED")} -> LOCKED | F27: {=IF(E27="Show hint",Key!$B$111,"")} | G27: {=IF(LEFT(D27,1)="✔",IF(E27="Show hint",5,10),0)} -> 0
A28: B3 | B28: {=IF($C$10="OPEN","In J10, find the largest Qty with MAX.","LOCKED · earn ★ on every stage to open the Boss gate")} -> LOCKED · earn ★ on every stage to open the Boss gate | C28: ▶ ARENA B3 (cell J10) | D28: {=IF($C$10="OPEN",IF(ISBLANK('Boss Arena'!$J$10),"",IF(NOT(_xlfn.ISFORMULA('Boss Arena'!$J$10)),"✘ That's a typed value · enter a formula",IF(ISERROR('Boss Arena'!$J$10),"✘ Your formula returns "&IFERROR(CHOOSE(ERROR.TYPE('Boss Arena'!$J$10),"#NULL!","#DIV/0!","#VALUE!","#REF!","#NAME?","#NUM!","#N/A","#GETTING_DATA","#SPILL!","#CONNECT!","#BLOCKED!","#UNKNOWN!","#FIELD!","#CALC!"),"an error"),IF(NOT(AND(IFERROR(AND(ISNUMBER('Boss Arena'!$J$10),ABS('Boss Arena'!$J$10-Key!$C$112)<=1E-9*MAX(1,ABS(Key!$C$112))),FALSE))),"✘ TRY AGAIN",IF(AND(OR(ISNUMBER(FIND({"=","(",",","+","-","*","/","&"," ","<",">",":","@","^"}&"MAX"&"(",UPPER(_xlfn.FORMULATEXT('Boss Arena'!$J$10)))))),"✔ CLEAR","✘ CLOSE · right value, but use MAX"))))),"LOCKED")} -> LOCKED | F28: {=IF(E28="Show hint",Key!$B$112,"")} | G28: {=IF(LEFT(D28,1)="✔",IF(E28="Show hint",5,10),0)} -> 0
A29: B4 | B29: {=IF($C$10="OPEN","In J11, count the Ratings that are numbers (F6:F15).","LOCKED · earn ★ on every stage to open the Boss gate")} -> LOCKED · earn ★ on every stage to open the Boss gate | C29: ▶ ARENA B4 (cell J11) | D29: {=IF($C$10="OPEN",IF(ISBLANK('Boss Arena'!$J$11),"",IF(NOT(_xlfn.ISFORMULA('Boss Arena'!$J$11)),"✘ That's a typed value · enter a formula",IF(ISERROR('Boss Arena'!$J$11),"✘ Your formula returns "&IFERROR(CHOOSE(ERROR.TYPE('Boss Arena'!$J$11),"#NULL!","#DIV/0!","#VALUE!","#REF!","#NAME?","#NUM!","#N/A","#GETTING_DATA","#SPILL!","#CONNECT!","#BLOCKED!","#UNKNOWN!","#FIELD!","#CALC!"),"an error"),IF(NOT(AND(IFERROR(AND(ISNUMBER('Boss Arena'!$J$11),ABS('Boss Arena'!$J$11-Key!$C$113)<=1E-9*MAX(1,ABS(Key!$C$113))),FALSE))),"✘ TRY AGAIN",IF(AND(OR(ISNUMBER(FIND({"=","(",",","+","-","*","/","&"," ","<",">",":","@","^"}&"COUNT"&"(",UPPER(_xlfn.FORMULATEXT('Boss Arena'!$J$11)))))),"✔ CLEAR","✘ CLOSE · right value, but use COUNT"))))),"LOCKED")} -> LOCKED | F29: {=IF(E29="Show hint",Key!$B$113,"")} | G29: {=IF(LEFT(D29,1)="✔",IF(E29="Show hint",5,10),0)} -> 0
A30: B5 | B30: {=IF($C$10="OPEN","In G6 calculate the profit: (Price - Cost) × Qty. Fill it down to G15 with Ctrl+D.","LOCKED · earn ★ on every stage to open the Boss gate")} -> LOCKED · earn ★ on every stage to open the Boss gate | C30: ▶ ARENA B5 (cell G6) | D30: {=IF($C$10="OPEN",IF(COUNTA('Boss Arena'!$G$6,'Boss Arena'!$G$7,'Boss Arena'!$G$8,'Boss Arena'!$G$9,'Boss Arena'!$G$10,'Boss Arena'!$G$11,'Boss Arena'!$G$12,'Boss Arena'!$G$13,'Boss Arena'!$G$14,'Boss Arena'!$G$15)=0,"",IF(OR(NOT(_xlfn.ISFORMULA('Boss Arena'!$G$6)),NOT(_xlfn.ISFORMULA('Boss Arena'!$G$7)),NOT(_xlfn.ISFORMULA('Boss Arena'!$G$8)),NOT(_xlfn.ISFORMULA('Boss Arena'!$G$9)),NOT(_xlfn.ISFORMULA('Boss Arena'!$G$10)),NOT(_xlfn.ISFORMULA('Boss Arena'!$G$11)),NOT(_xlfn.ISFORMULA('Boss Arena'!$G$12)),NOT(_xlfn.ISFORMULA('Boss Arena'!$G$13)),NOT(_xlfn.ISFORMULA('Boss Arena'!$G$14)),NOT(_xlfn.ISFORMULA('Boss Arena'!$G$15))),"✘ Some cells aren't formulas yet",IF(OR(ISERROR('Boss Arena'!$G$6),ISERROR('Boss Arena'!$G$7),ISERROR('Boss Arena'!$G$8),ISERROR('Boss Arena'!$G$9),ISERROR('Boss Arena'!$G$10),ISERROR('Boss Arena'!$G$11),ISERROR('Boss Arena'!$G$12),ISERROR('Boss Arena'!$G$13),ISERROR('Boss Arena'!$G$14),ISERROR('Boss Arena'!$G$15)),"✘ Some cells show an error",IF(NOT(AND(IFERROR(AND(ISNUMBER('Boss Arena'!$G$6),ABS('Boss Arena'!$G$6-Key!$E$114)<=1E-9*MAX(1,ABS(Key!$E$114))),FALSE),IFERROR(AND(ISNUMBER('Boss Arena'!$G$7),ABS('Boss Arena'!$G$7-Key!$F$114)<=1E-9*MAX(1,ABS(Key!$F$114))),FALSE),IFERROR(AND(ISNUMBER('Boss Arena'!$G$8),ABS('Boss Arena'!$G$8-Key!$G$114)<=1E-9*MAX(1,ABS(Key!$G$114))),FALSE),IFERROR(AND(ISNUMBER('Boss Arena'!$G$9),ABS('Boss Arena'!$G$9-Key!$H$114)<=1E-9*MAX(1,ABS(Key!$H$114))),FALSE),IFERROR(AND(ISNUMBER('Boss Arena'!$G$10),ABS('Boss Arena'!$G$10-Key!$I$114)<=1E-9*MAX(1,ABS(Key!$I$114))),FALSE),IFERROR(AND(ISNUMBER('Boss Arena'!$G$11),ABS('Boss Arena'!$G$11-Key!$J$114)<=1E-9*MAX(1,ABS(Key!$J$114))),FALSE),IFERROR(AND(ISNUMBER('Boss Arena'!$G$12),ABS('Boss Arena'!$G$12-Key!$K$114)<=1E-9*MAX(1,ABS(Key!$K$114))),FALSE),IFERROR(AND(ISNUMBER('Boss Arena'!$G$13),ABS('Boss Arena'!$G$13-Key!$L$114)<=1E-9*MAX(1,ABS(Key!$L$114))),FALSE),IFERROR(AND(ISNUMBER('Boss Arena'!$G$14),ABS('Boss Arena'!$G$14-Key!$M$114)<=1E-9*MAX(1,ABS(Key!$M$114))),FALSE),IFERROR(AND(ISNUMBER('Boss Arena'!$G$15),ABS('Boss Arena'!$G$15-Key!$N$114)<=1E-9*MAX(1,ABS(Key!$N$114))),FALSE))),"✘ TRY AGAIN","✔ CLEAR")))),"LOCKED")} -> LOCKED | F30: {=IF(E30="Show hint",Key!$B$114,"")} | G30: {=IF(LEFT(D30,1)="✔",IF(E30="Show hint",5,10),0)} -> 0
A31: B6 | B31: {=IF($C$10="OPEN","In H6 calculate the tax: Price × the rate in K6. Lock K6 with F4, then fill down to H15.","LOCKED · earn ★ on every stage to open the Boss gate")} -> LOCKED · earn ★ on every stage to open the Boss gate | C31: ▶ ARENA B6 (cell H6) | D31: {=IF($C$10="OPEN",IF(COUNTA('Boss Arena'!$H$6,'Boss Arena'!$H$7,'Boss Arena'!$H$8,'Boss Arena'!$H$9,'Boss Arena'!$H$10,'Boss Arena'!$H$11,'Boss Arena'!$H$12,'Boss Arena'!$H$13,'Boss Arena'!$H$14,'Boss Arena'!$H$15)=0,"",IF(OR(NOT(_xlfn.ISFORMULA('Boss Arena'!$H$6)),NOT(_xlfn.ISFORMULA('Boss Arena'!$H$7)),NOT(_xlfn.ISFORMULA('Boss Arena'!$H$8)),NOT(_xlfn.ISFORMULA('Boss Arena'!$H$9)),NOT(_xlfn.ISFORMULA('Boss Arena'!$H$10)),NOT(_xlfn.ISFORMULA('Boss Arena'!$H$11)),NOT(_xlfn.ISFORMULA('Boss Arena'!$H$12)),NOT(_xlfn.ISFORMULA('Boss Arena'!$H$13)),NOT(_xlfn.ISFORMULA('Boss Arena'!$H$14)),NOT(_xlfn.ISFORMULA('Boss Arena'!$H$15))),"✘ Some cells aren't formulas yet",IF(OR(ISERROR('Boss Arena'!$H$6),ISERROR('Boss Arena'!$H$7),ISERROR('Boss Arena'!$H$8),ISERROR('Boss Arena'!$H$9),ISERROR('Boss Arena'!$H$10),ISERROR('Boss Arena'!$H$11),ISERROR('Boss Arena'!$H$12),ISERROR('Boss Arena'!$H$13),ISERROR('Boss Arena'!$H$14),ISERROR('Boss Arena'!$H$15)),"✘ Some cells show an error",IF(NOT(AND(IFERROR(AND(ISNUMBER('Boss Arena'!$H$6),ABS('Boss Arena'!$H$6-Key!$E$115)<=1E-9*MAX(1,ABS(Key!$E$115))),FALSE),IFERROR(AND(ISNUMBER('Boss Arena'!$H$7),ABS('Boss Arena'!$H$7-Key!$F$115)<=1E-9*MAX(1,ABS(Key!$F$115))),FALSE),IFERROR(AND(ISNUMBER('Boss Arena'!$H$8),ABS('Boss Arena'!$H$8-Key!$G$115)<=1E-9*MAX(1,ABS(Key!$G$115))),FALSE),IFERROR(AND(ISNUMBER('Boss Arena'!$H$9),ABS('Boss Arena'!$H$9-Key!$H$115)<=1E-9*MAX(1,ABS(Key!$H$115))),FALSE),IFERROR(AND(ISNUMBER('Boss Arena'!$H$10),ABS('Boss Arena'!$H$10-Key!$I$115)<=1E-9*MAX(1,ABS(Key!$I$115))),FALSE),IFERROR(AND(ISNUMBER('Boss Arena'!$H$11),ABS('Boss Arena'!$H$11-Key!$J$115)<=1E-9*MAX(1,ABS(Key!$J$115))),FALSE),IFERROR(AND(ISNUMBER('Boss Arena'!$H$12),ABS('Boss Arena'!$H$12-Key!$K$115)<=1E-9*MAX(1,ABS(Key!$K$115))),FALSE),IFERROR(AND(ISNUMBER('Boss Arena'!$H$13),ABS('Boss Arena'!$H$13-Key!$L$115)<=1E-9*MAX(1,ABS(Key!$L$115))),FALSE),IFERROR(AND(ISNUMBER('Boss Arena'!$H$14),ABS('Boss Arena'!$H$14-Key!$M$115)<=1E-9*MAX(1,ABS(Key!$M$115))),FALSE),IFERROR(AND(ISNUMBER('Boss Arena'!$H$15),ABS('Boss Arena'!$H$15-Key!$N$115)<=1E-9*MAX(1,ABS(Key!$N$115))),FALSE))),"✘ TRY AGAIN",IF(ISNUMBER(FIND("$",_xlfn.FORMULATEXT('Boss Arena'!$H$6))),"✔ CLEAR","✘ CLOSE · add $ so it fills correctly (F4)"))))),"LOCKED")} -> LOCKED | F31: {=IF(E31="Show hint",Key!$B$115,"")} | G31: {=IF(LEFT(D31,1)="✔",IF(E31="Show hint",5,10),0)} -> 0
A32: B7 | B32: {=IF($C$10="OPEN","In J12, average the Price column and round to 1 decimal in one formula.","LOCKED · earn ★ on every stage to open the Boss gate")} -> LOCKED · earn ★ on every stage to open the Boss gate | C32: ▶ ARENA B7 (cell J12) | D32: {=IF($C$10="OPEN",IF(ISBLANK('Boss Arena'!$J$12),"",IF(NOT(_xlfn.ISFORMULA('Boss Arena'!$J$12)),"✘ That's a typed value · enter a formula",IF(ISERROR('Boss Arena'!$J$12),"✘ Your formula returns "&IFERROR(CHOOSE(ERROR.TYPE('Boss Arena'!$J$12),"#NULL!","#DIV/0!","#VALUE!","#REF!","#NAME?","#NUM!","#N/A","#GETTING_DATA","#SPILL!","#CONNECT!","#BLOCKED!","#UNKNOWN!","#FIELD!","#CALC!"),"an error"),IF(NOT(AND(IFERROR(AND(ISNUMBER('Boss Arena'!$J$12),ABS('Boss Arena'!$J$12-Key!$C$116)<=1E-9*MAX(1,ABS(Key!$C$116))),FALSE))),"✘ TRY AGAIN",IF(AND(OR(ISNUMBER(FIND({"=","(",",","+","-","*","/","&"," ","<",">",":","@","^"}&"ROUND"&"(",UPPER(_xlfn.FORMULATEXT('Boss Arena'!$J$12))))),OR(ISNUMBER(FIND({"=","(",",","+","-","*","/","&"," ","<",">",":","@","^"}&"AVERAGE"&"(",UPPER(_xlfn.FORMULATEXT('Boss Arena'!$J$12)))))),"✔ CLEAR","✘ CLOSE · right value, but use ROUND and AVERAGE"))))),"LOCKED")} -> LOCKED | F32: {=IF(E32="Show hint",Key!$B$116,"")} | G32: {=IF(LEFT(D32,1)="✔",IF(E32="Show hint",5,10),0)} -> 0
A33: B8 | B33: {=IF($C$10="OPEN","Press Ctrl+` in the Boss Arena. One cell in L6:L15 was typed over. Type its address.","LOCKED · earn ★ on every stage to open the Boss gate")} -> LOCKED · earn ★ on every stage to open the Boss gate | D33: {=IF($C$10="OPEN",IFERROR(_xlfn.LET(_xlpm.a,Boss!$C$33,IF(TRIM(_xlpm.a&"")="","",IF(SUBSTITUTE(SUBSTITUTE(UPPER(_xlpm.a&"")," ",""),"$","")=Key!$C$117,"✔ CLEAR","✘ TRY AGAIN"))),"✘ TRY AGAIN"),"LOCKED")} -> LOCKED | F33: {=IF(E33="Show hint",Key!$B$117,"")} | G33: {=IF(LEFT(D33,1)="✔",IF(E33="Show hint",5,10),0)} -> 0

Sheet Boss Arena
A1: BOSS ARENA ▸ FORMULA BASICS
A2: Practice area · everything here is editable. Missions and their checks are on the stage sheet.
A3: PASS CODE | B3: FORMULON | D3: ◀ Back to Boss
B5: Item | C5: Cost | D5: Price | E5: Qty | F5: Rating | G5: Profit | H5: Tax | K5: Tax rate | L5: Double qty
B6: Lamp | C6: 12 | D6: 30 | E6: 5 | F6: 4 | K6: 0.07 | L6: {=E6*2} -> 10
B7: Mug | C7: 3 | D7: 9 | E7: 20 | F7: 5 | L7: {=E7*2} -> 40
B8: Desk | C8: 85 | D8: 160 | E8: 2 | F8: TBD | I8: Total qty | L8: {=E8*2} -> 4
B9: Chair | C9: 40 | D9: 95 | E9: 4 | F9: 3 | I9: Average price | L9: 8
B10: Pen | C10: 0.4 | D10: 1.6 | E10: 100 | F10: 5 | I10: Largest qty | L10: {=E10*2} -> 200
B11: Book | C11: 6 | D11: 18 | E11: 12 | F11: 4 | I11: Numeric ratings | L11: {=E11*2} -> 24
B12: Clock | C12: 10 | D12: 25 | E12: 6 | F12: TBD | I12: Avg price, 1 dp | L12: {=E12*2} -> 12
B13: Plant | C13: 4 | D13: 11 | E13: 9 | F13: 2 | L13: {=E13*2} -> 18
B14: Rug | C14: 30 | D14: 70 | E14: 3 | F14: 5 | L14: {=E14*2} -> 6
B15: Fan | C15: 22 | D15: 45 | E15: 7 | F15: 4 | L15: {=E15*2} -> 14

Sheet Cheat Codes
A1: CHEAT CODES ▸ FORMULA BASICS
A2: Every move from this world on one page. Keep it open while you play, or print it (Ctrl+P).
A4: Stage | B4: Keys / Syntax | C4: What it does | D4: Pro tip
A5: F1-1 | B5: = | C5: Every formula starts with an equals sign. | D5: Without =, Excel stores what you typed as plain text.
A6: F1-1 | B6: + - * / ^ | C6: Arithmetic: add, subtract, multiply, divide, power. | D6: * multiplies, / divides, ^ raises to a power (2^3 = 8).
A7: F1-1 | B7: ( ) first | C7: Order: parentheses, then ^, then * and /, then + and -. | D7: =2+3*4 is 14, but =(2+3)*4 is 20.
A8: F1-1 | B8: =B2*C2 | C8: Point at cells instead of typing numbers. | D8: Change B2 and the result updates by itself.
A9: F1-2 | B9: SUM | C9: Add up numbers: =SUM(B2:B10). | D9: A range is first:last joined by a colon.
A10: F1-2 | B10: AVERAGE | C10: The mean of the numbers in a range. | D10: Blank cells and text are skipped, not counted as 0.
A11: F1-2 | B11: MAX | C11: The largest number in a range. | D11: Pair it with MIN to see the spread.
A12: F1-2 | B12: MIN | C12: The smallest number in a range. | D12: Text such as n/a is ignored.
A13: F1-2 | B13: COUNT | C13: Count the cells that hold numbers. | D13: Text doesn't count: use COUNTA for any filled cell.
A14: F1-2 | B14: COUNTA | C14: Count the cells that are not empty (numbers, text, anything). | D14: The A stands for 'all'.
A15: F1-2 | B15: Alt+= | C15: AutoSum: insert =SUM() over the numbers above or to the left. | D15: Select the cell under a column of numbers, press Alt+=, then Enter.
... A27: F1-5 | B27: Shift+F3 | C27: Open the Insert Function dialog. | D27: Search for a function by describing what you need.

Sheet Key
A1: Challenge | B1: Hint | C1: Expected | E1: Lists / per-cell expectations →
A2: F1-1 Power Up W1 | B2: A function key, or Ctrl plus G. | E2: CTRL+G | F2: F5
A3: F1-1 Power Up W2 | B3: Ctrl plus Page Down. | E3: CTRL+PGDN
A4: F1-1 Power Up W3 | B4: Ctrl plus Page Up. | E4: CTRL+PGUP
A5: F1-1 Power Up W4 | B5: Page Down. | E5: PGDN
A6: F1-1 Power Up W5 | B6: Alt plus Page Down. | E6: ALT+PGDN
A7: F1-1 Power Up T1 | B7: The key left of Backspace. | C7: = | E7: = | F7: ( ) first | G7: =B2*C2 | H7: $A$1
A8: F1-1 Power Up T2 | B8: Shift+6 on a US keyboard. | C8: + - * / ^ | E8: + - * / ^ | F8: $A$1 | G8: ( ) first | H8: $A1 / A$1
A9: F1-1 Power Up T3 | B9: Multiply before you add. | C9: ( ) first | E9: $A$1 | F9: =B2*C2 | G9: $A1 / A$1 | H9: ( ) first
A10: F1-1 Power Up T4 | B10: Start with = then the two cell addresses. | C10: =B2*C2 | E10: =B2*C2 | F10: = | G10: + - * / ^ | H10: $A$1
A11: F1-1 Power Up C1 | B11: The key left of Backspace. | E11: = | F11: EQUALS | G11: EQUALSIGN | H11: EQUALSSIGN
A12: F1-1 Power Up C2 | B12: Shift+6 on a US keyboard. | E12: CARET | F12: ^
A13: F1-1 Power Up C3 | B13: Multiply before you add. | E13: 14
A14: F1-1 Power Up C4 | B14: Start with = then the two cell addresses. | E14: =B2*C2 | F14: =C2*B2 | G14: B2*C2 | H14: C2*B2
A15: F1-1 Power Up C5 | B15: Type =C6*D6. | C15: {='F1-1 Arena'!$C$6*'F1-1 Arena'!$D$6} -> 10
A16: F1-1 Power Up C6 | B16: Wrap the addition in ( ). | C16: {=('F1-1 Arena'!$C$7+3)*'F1-1 Arena'!$D$7} -> 36
A17: F1-1 Power Up C7 | B17: Type =D8^2. | C17: {='F1-1 Arena'!$D$8^2} -> 64
A18: F1-1 Power Up C8 | B18: Multiply first: 2*3 = 6. | C18: 4
A19: F1-2 Big Six W1 | B19: The key left of Backspace. | E19: = | F19: EQUALS | G19: EQUALSIGN | H19: EQUALSSIGN
A20: F1-2 Big Six W2 | B20: Shift+6 on a US keyboard. | E20: CARET | F20: ^
A21: F1-2 Big Six W3 | B21: Multiply before you add. | E21: 14
A22: F1-2 Big Six W4 | B22: Start with = then the two cell addresses. | E22: =B2*C2 | F22: =C2*B2 | G22: B2*C2 | H22: C2*B2
A23: F1-2 Big Six W5 | B23: Hold Shift and tap an arrow. | E23: SHIFT+ARROW | F23: SHIFT+DOWN | G23: SHIFT+LEFT | H23: SHIFT+RIGHT | I23: SHIFT+UP
A24: F1-2 Big Six W6 | B24: The warp-zone keys plus Shift. | E24: CTRL+SHIFT+ARROW | F24: CTRL+SHIFT+DOWN | G24: CTRL+SHIFT+LEFT | H24: CTRL+SHIFT+RIGHT | I24: CTRL+SHIFT+UP | J24: SHIFT+CTRL+ARROW | K24: SHIFT+CTRL+DOWN | L24: SHIFT+CTRL+LEFT | M24: SHIFT+CTRL+RIGHT | N24: SHIFT+CTRL+UP
A25: F1-2 Big Six W7 | B25: Ctrl+End plus Shift. | E25: CTRL+SHIFT+END | F25: SHIFT+CTRL+END
A26: F1-2 Big Six W8 | B26: Ctrl+Home plus Shift. | E26: CTRL+SHIFT+HOME | F26: SHIFT+CTRL+HOME
A27: F1-2 Big Six T1 | B27: Three letters. | C27: SUM | E27: COUNT | F27: SUM | G27: AVERAGE | H27: ROUNDUP
A28: F1-2 Big Six T2 | B28: Starts with AVER. | C28: AVERAGE | E28: SUM | F28: AVERAGE | G28: MIN | H28: COUNT
A29: F1-2 Big Six T3 | B29: Short for maximum. | C29: MAX | E29: COUNT | F29: MAX | G29: ROUND | H29: COUNTA
A30: F1-2 Big Six T4 | B30: Short for minimum. | C30: MIN | E30: COUNTA | F30: ROUNDUP | G30: AVERAGE | H30: MIN
A31: F1-2 Big Six T5 | B31: The plain counting function. | C31: COUNT | E31: ROUNDUP | F31: MAX | G31: COUNT | H31: COUNTA
A32: F1-2 Big Six T6 | B32: COUNT plus one letter. | C32: COUNTA | E32: ROUNDDOWN | F32: AVERAGE | G32: SUM | H32: COUNTA
A33: F1-2 Big Six T7 | B33: Alt plus the equals key. | C33: Alt+= | E33: Shift+F3 | F33: Alt+= | G33: Ctrl+` | H33: Tab
A34: F1-2 Big Six C1 | B34: Three letters. | E34: =SUM | F34: =SUM( | G34: =SUM() | H34: SUM | I34: SUM( | J34: SUM()
A35: F1-2 Big Six C2 | B35: Starts with AVER. | E35: =AVERAGE | F35: =AVERAGE( | G35: =AVERAGE() | H35: AVERAGE | I35: AVERAGE( | J35: AVERAGE()
A36: F1-2 Big Six C3 | B36: Short for maximum. | E36: =MAX | F36: =MAX( | G36: =MAX() | H36: MAX | I36: MAX( | J36: MAX()
A37: F1-2 Big Six C4 | B37: Short for minimum. | E37: =MIN | F37: =MIN( | G37: =MIN() | H37: MIN | I37: MIN( | J37: MIN()
A38: F1-2 Big Six C5 | B38: The plain counting function. | E38: =COUNT | F38: =COUNT( | G38: =COUNT() | H38: COUNT | I38: COUNT( | J38: COUNT()
A39: F1-2 Big Six C6 | B39: COUNT plus one letter. | E39: =COUNTA | F39: =COUNTA( | G39: =COUNTA() | H39: COUNTA | I39: COUNTA( | J39: COUNTA()
A40: F1-2 Big Six C7 | B40: Alt plus the equals key. | E40: ALT+=
A41: F1-2 Big Six C8 | B41: Alt and = together. | C41: {=SUM('F1-2 Arena'!$C$6:$C$17)} -> 6690
A42: F1-2 Big Six C9 | B42: =AVERAGE(C6:C17) | C42: {=AVERAGE('F1-2 Arena'!$C$6:$C$17)} -> 557.5
A43: F1-2 Big Six C10 | B43: =MAX(C6:C17) | C43: {=MAX('F1-2 Arena'!$C$6:$C$17)} -> 720
A44: F1-2 Big Six C11 | B44: =MIN(C6:C17) | C44: {=MIN('F1-2 Arena'!$C$6:$C$17)} -> 380
A45: F1-2 Big Six C12 | B45: COUNT skips n/a. | C45: {=COUNT('F1-2 Arena'!$D$6:$D$17)} -> 10
A46: F1-2 Big Six C13 | B46: COUNTA counts text too. | C46: {=COUNTA('F1-2 Arena'!$D$6:$D$17)} -> 12
A47: F1-3 Anchors W1 | B47: Three letters. | E47: =SUM | F47: =SUM( | G47: =SUM() | H47: SUM | I47: SUM( | J47: SUM()
A48: F1-3 Anchors W2 | B48: Starts with AVER. | E48: =AVERAGE | F48: =AVERAGE( | G48: =AVERAGE() | H48: AVERAGE | I48: AVERAGE( | J48: AVERAGE()
A49: F1-3 Anchors W3 | B49: Short for maximum. | E49: =MAX | F49: =MAX( | G49: =MAX() | H49: MAX | I49: MAX( | J49: MAX()
A50: F1-3 Anchors W4 | B50: Short for minimum. | E50: =MIN | F50: =MIN( | G50: =MIN() | H50: MIN | I50: MIN( | J50: MIN()
A51: F1-3 Anchors W5 | B51: The plain counting function. | E51: =COUNT | F51: =COUNT( | G51: =COUNT() | H51: COUNT | I51: COUNT( | J51: COUNT()
A52: F1-3 Anchors W6 | B52: COUNT plus one letter. | E52: =COUNTA | F52: =COUNTA( | G52: =COUNTA() | H52: COUNTA | I52: COUNTA( | J52: COUNTA()
A53: F1-3 Anchors W7 | B53: Alt plus the equals key. | E53: ALT+=
A54: F1-3 Anchors W8 | B54: The long key plus Shift. | E54: SHIFT+SPACE
A55: F1-3 Anchors W9 | B55: The long key plus Ctrl. | E55: CTRL+SPACE
A56: F1-3 Anchors W10 | B56: Think 'A' for All. | E56: CTRL+A | F56: CTRL+SHIFT+SPACE | G56: SHIFT+CTRL+SPACE
A57: F1-3 Anchors T1 | B57: Put $ before the column and the row. | C57: $A$1 | E57: $A1 / A$1 | F57: ( ) first | G57: $A$1 | H57: =B2*C2
A58: F1-3 Anchors T2 | B58: The $ goes right before 16. | C58: $A1 / A$1 | E58: $A1 / A$1 | F58: =B2*C2 | G58: + - * / ^ | H58: $A$1
A59: F1-3 Anchors T3 | B59: A function key between F3 and F5. | C59: F4 | E59: Alt+= | F59: Shift+F3 | G59: F4 | H59: Ctrl+Shift+A
A60: F1-3 Anchors T4 | B60: D for Down. | C60: Ctrl+D | E60: Tab | F60: F2 | G60: Ctrl+D | H60: Ctrl+Shift+A
A61: F1-3 Anchors C1 | B61: Put $ before the column and the row. | E61: $E$6
A62: F1-3 Anchors C2 | B62: The $ goes right before 16. | E62: C$16
A63: F1-3 Anchors C3 | B63: A function key between F3 and F5. | E63: F4
A64: F1-3 Anchors C4 | B64: D for Down. | E64: CTRL+D
A65: F1-3 Anchors C5 | B65: Without $, the rate cell slides down. | E65: {='F1-3 Arena'!$B$6*'F1-3 Arena'!$E$6} -> 1.6 | F65: {='F1-3 Arena'!$B$7*'F1-3 Arena'!$E$6} -> 2.8 | G65: {='F1-3 Arena'!$B$8*'F1-3 Arena'!$E$6} -> 1 | H65: {='F1-3 Arena'!$B$9*'F1-3 Arena'!$E$6} -> 6.4 | I65: {='F1-3 Arena'!$B$10*'F1-3 Arena'!$E$6} -> 3.68 | J65: {='F1-3 Arena'!$B$11*'F1-3 Arena'!$E$6} -> 0.7992 | K65: {='F1-3 Arena'!$B$12*'F1-3 Arena'!$E$6} -> 12 | L65: {='F1-3 Arena'!$B$13*'F1-3 Arena'!$E$6} -> 5.12
A66: F1-3 Anchors C6 | B66: Two $ signs, in different places. | E66: {='F1-3 Arena'!$B$17*(1-'F1-3 Arena'!$C$16)} -> 36 | F66: {='F1-3 Arena'!$B$18*(1-'F1-3 Arena'!$C$16)} -> 22.5 | G66: {='F1-3 Arena'!$B$19*(1-'F1-3 Arena'!$C$16)} -> 54 | H66: {='F1-3 Arena'!$B$20*(1-'F1-3 Arena'!$C$16)} -> 13.5 | I66: {='F1-3 Arena'!$B$21*(1-'F1-3 Arena'!$C$16)} -> 81
A67: F1-4 Precision W1 | B67: Put $ before the column and the row. | E67: $E$6
A68: F1-4 Precision W2 | B68: The $ goes right before 16. | E68: C$16
A69: F1-4 Precision W3 | B69: A function key between F3 and F5. | E69: F4
A70: F1-4 Precision W4 | B70: D for Down. | E70: CTRL+D
A71: F1-4 Precision T1 | B71: The plain rounding function. | C71: ROUND | E71: COUNT | F71: ROUND | G71: MAX | H71: AVERAGE
A72: F1-4 Precision T2 | B72: ROUND plus a direction. | C72: ROUNDUP | E72: COUNTA | F72: ROUNDUP | G72: SUM | H72: ROUNDDOWN
A73: F1-4 Precision T3 | B73: ROUND plus the other direction. | C73: ROUNDDOWN | E73: ROUND | F73: COUNTA | G73: ROUNDDOWN | H73: COUNT
A74: F1-4 Precision C1 | B74: The plain rounding function. | E74: =ROUND | F74: =ROUND( | G74: =ROUND() | H74: ROUND | I74: ROUND( | J74: ROUND()
A75: F1-4 Precision C2 | B75: ROUND plus a direction. | E75: =ROUNDUP | F75: =ROUNDUP( | G75: =ROUNDUP() | H75: ROUNDUP | I75: ROUNDUP( | J75: ROUNDUP()
A76: F1-4 Precision C3 | B76: ROUND plus the other direction. | E76: =ROUNDDOWN | F76: =ROUNDDOWN( | G76: =ROUNDDOWN() | H76: ROUNDDOWN | I76: ROUNDDOWN( | J76: ROUNDDOWN()
A77: F1-4 Precision C4 | B77: =ROUND(B6,2) | C77: {=ROUND('F1-4 Arena'!$B$6,2)} -> 3.14
A78: F1-4 Precision C5 | B78: 0 digits = whole number. | C78: {=ROUNDUP('F1-4 Arena'!$B$7,0)} -> 3
A79: F1-4 Precision C6 | B79: =ROUNDDOWN(B8,1) | C79: {=ROUNDDOWN('F1-4 Arena'!$B$8,1)} -> 7.8
A80: F1-4 Precision C7 | B80: Negative digits. | C80: {=ROUND('F1-4 Arena'!$B$9,-2)} -> 1200
A81: F1-5 X-Ray W1 | B81: The plain rounding function. | E81: =ROUND | F81: =ROUND( | G81: =ROUND() | H81: ROUND | I81: ROUND( | J81: ROUND()
A82: F1-5 X-Ray W2 | B82: ROUND plus a direction. | E82: =ROUNDUP | F82: =ROUNDUP( | G82: =ROUNDUP() | H82: ROUNDUP | I82: ROUNDUP( | J82: ROUNDUP()
A83: F1-5 X-Ray W3 | B83: ROUND plus the other direction. | E83: =ROUNDDOWN | F83: =ROUNDDOWN( | G83: =ROUNDDOWN() | H83: ROUNDDOWN | I83: ROUNDDOWN( | J83: ROUNDDOWN()
A84: F1-5 X-Ray W4 | B84: The key left of Backspace. | E84: = | F84: EQUALS | G84: EQUALSIGN | H84: EQUALSSIGN
A85: F1-5 X-Ray W5 | B85: Shift+6 on a US keyboard. | E85: CARET | F85: ^
A86: F1-5 X-Ray W6 | B86: Multiply before you add. | E86: 14
A87: F1-5 X-Ray W7 | B87: Start with = then the two cell addresses. | E87: =B2*C2 | F87: =C2*B2 | G87: B2*C2 | H87: C2*B2
A88: F1-5 X-Ray T1 | B88: Ctrl plus the key left of 1. | C88: Ctrl+` | E88: Ctrl+` | F88: F4 | G88: Ctrl+D | H88: Tab
A89: F1-5 X-Ray T2 | B89: The function key after F1. | C89: F2 | E89: Shift+F3 | F89: F4 | G89: Ctrl+D | H89: F2
A90: F1-5 X-Ray T3 | B90: The key above Caps Lock. | C90: Tab | E90: Tab | F90: Ctrl+D | G90: Ctrl+Shift+A | H90: Alt+=
A91: F1-5 X-Ray T4 | B91: Ctrl+Shift plus A for arguments. | C91: Ctrl+Shift+A | E91: Ctrl+Shift+A | F91: Alt+= | G91: Ctrl+` | H91: Tab
A92: F1-5 X-Ray T5 | B92: Shift plus F3. | C92: Shift+F3 | E92: Ctrl+Shift+A | F92: F2 | G92: Shift+F3 | H92: Tab
A93: F1-5 X-Ray C1 | B93: Ctrl plus the key left of 1. | E93: CTRL+BACKTICK | F93: CTRL+GRAVE | G93: CTRL+GRAVEACCENT | H93: CTRL+`
A94: F1-5 X-Ray C2 | B94: The function key after F1. | E94: F2
A95: F1-5 X-Ray C3 | B95: The key above Caps Lock. | E95: TAB
A96: F1-5 X-Ray C4 | B96: Ctrl+Shift plus A for arguments. | E96: CTRL+SHIFT+A | F96: SHIFT+CTRL+A
A97: F1-5 X-Ray C5 | B97: Shift plus F3. | E97: SHIFT+F3
A98: F1-5 X-Ray C6 | B98: Look for the cell without an = sign. | C98: C12
A99: F1-5 X-Ray C7 | B99: It's not in column C. | C99: H20
A100: F1-5 X-Ray C8 | B100: Tab accepts the suggestion. | C100: {=AVERAGE('F1-5 Arena'!$C$6:$C$15)} -> 60
...
